Workbook
Name L_Transitaria: LISTAS!$A$5:$A$7
Name L_Region: LISTAS!$B$5:$B$7
Name L_SiNo: LISTAS!$C$5:$C$6
Name L_Prorrateo: LISTAS!$D$5:$D$6
Name L_BaseCom: LISTAS!$E$5:$E$6
Name L_Estado: LISTAS!$F$5:$F$6
Name L_TipoCont: LISTAS!$G$5:$G$8
Name L_Grupo: LISTAS!$H$5:$H$6
Name L_Centro: LISTAS!$I$5:$I$8
Name L_Elemento: LISTAS!$J$5:$J$10
Name L_TipoActivo: LISTAS!$K$5:$K$7
Name L_Territorio: LISTAS!$L$5:$L$21
Name L_TerrRegion: LISTAS!$M$5:$M$21
Name Empresa: PARAMETROS!$C$6
Name Fecha_Inicio: PARAMETROS!$C$7
Name Metodo_Prorrateo: PARAMETROS!$C$8
Name Base_Comision: PARAMETROS!$C$9
Name Tolerancia_Comb: PARAMETROS!$C$10
Name Mes_Corte: PARAMETROS!$C$11
Name Std_Viajes_Puerto: PARAMETROS!$C$13
Name Litros_Puerto_Viaje: PARAMETROS!$C$14
Name Km_Puerto_Viaje: PARAMETROS!$C$15
Name Rend_Desagrupe: PARAMETROS!$C$16
Name Rend_Desagrupe_CT: PARAMETROS!$C$17
Name Cap_Camion_OCC: PARAMETROS!$C$18
Name Cap_Camion_CEN: PARAMETROS!$C$19
Name Cap_Camion_ORI: PARAMETROS!$C$20
Name L_Dist_OCC: PARAMETROS!$C$21
Name L_Tras_CEN: PARAMETROS!$C$22
Name L_Dist_CEN: PARAMETROS!$C$23
Name L_Tras_ORI: PARAMETROS!$C$24
Name L_Dist_ORI: PARAMETROS!$C$25
Name Pct_Reclamaciones: PARAMETROS!$C$27
Name Pct_Banco: PARAMETROS!$C$28
Name Imp_Ventas_Serv: PARAMETROS!$C$30
Name Contrib_Territorial: PARAMETROS!$C$31
Name Contrib_SS: PARAMETROS!$C$32
Name Imp_Fuerza_Trabajo: PARAMETROS!$C$33
Name Imp_Utilidades: PARAMETROS!$C$34

Sheet INICIO
B2: ANÁLISIS DE RENTABILIDAD – NEGOCIO DE PAQUETERÍA
B3: =Empresa&" · Modelo por contenedor, por región y por mes · Importes en USD" -> Empresa de Paquetería (editar) · Modelo por contenedor, por región y por mes · Importes en USD
B5: Flujo modelado
B6: 1. PUERTO (vehículo propio: cita, combustible, dieta, desgaste) → 2. TRANSITARIA ENCI / A.V (desagrupe por jornal) → 3. DISTRIBUCIÓN: Occidente directa · Centro y Oriente con traslado, centro transitorio y distribución → 4. COMERCIALIZACIÓN (21 gestores: fijo + variable)
B8: Hojas del libro
B9: Hoja | C9: Contenido | D9: Cuándo se usa
B10: GUIA_USO | C10: Resumen de la guía (la guía completa con imágenes es el PDF que acompaña al libro). | D10: Antes de empezar
B11: ANALISIS | C11: Diagnóstico, metodología, clasificación de costos y propuestas de mejora. | D11: Para decidir
B12: PARAMETROS | C12: Normas técnicas, porcentajes, tributos y métodos de cálculo. | D12: Una vez / si cambia una norma
B13: PRECIOS | C13: Tarifas y precios con fecha de vigencia (historial auditable). | D13: Una vez / si cambia un precio
B14: ACTIVOS | C14: Vehículos y equipos: depreciación, mantenimiento y seguros. | D14: Una vez / al comprar o vender
B15: COSTOS_FIJOS | C15: Costos fijos mensuales por centro de costo y tributos sobre salarios. | D15: Una vez / cierre de mes
B16: COMERCIAL | C16: 21 gestores: pago fijo, liquidación variable y conciliación mensual. | D16: Cierre de mes
B17: ENTRADA | C17: Registro de contenedores: la hoja donde se trabaja a diario. | D17: Con cada contenedor
B18: CALCULO | C18: Cálculo automático completo por contenedor y por región. | D18: Solo consulta
B19: RESUMEN_MES | C19: Rentabilidad mensual, punto de equilibrio e impuesto anual estimado. | D19: Cierre de mes
B20: DASHBOARD | C20: Panel de indicadores y gráficos del período elegido. | D20: Para informar
... B22: LISTAS | C22: Listas de los desplegables (técnica). | D22: No se toca
B24: Su rutina de trabajo (una sola persona lleva el libro)
B25: Una sola vez, al empezar | C25: PARAMETROS → PRECIOS → ACTIVOS → COSTOS_FIJOS → COMERCIAL. Después, borrar los datos de ejemplo.
B26: Con cada contenedor | C26: ENTRADA: 1) al llegar, ID, fecha, transitaria y kg por región; 2) al terminar la distribución, datos reales y Estado «Cerrado».
B27: Cuando cambia un precio | C27: PRECIOS: agregar una fila nueva con la fecha desde la que rige. Nunca sobrescribir la anterior.
B28: Cada fin de mes | C28: Revisar alertas en INICIO → gastos reales en COSTOS_FIJOS → liquidación en COMERCIAL → RESUMEN_MES y DASHBOARD → guardar una copia con fecha.
B30: Leyenda de colores
B31: 1.234 | C31: Dato de entrada: se puede escribir (letra azul, fondo amarillo).
B32: 1234 | C32: Fórmula: no escribir (letra negra).
B33: 1234 | C33: Enlace a otra hoja (letra verde).
B35: Estado del libro (controles automáticos)
B36: Contenedores registrados | C36: =COUNTIF(ENTRADA!$B$6:$B$305,"?*") -> 4
B37: Contenedores con alertas | C37: =COUNTIF(CALCULO!$CT$6:$CT$305,"?*") -> 1
B38: Contenedores abiertos (sin cerrar) | C38: =COUNTIF(CALCULO!$F$6:$F$305,"Abierto") -> 1
B39: Cuadre de regiones (CALCULO) | C39: =IF(AND(MAX(CALCULO!$CO$6:$CO$305)<0.01,MIN(CALCULO!$CO$6:$CO$305)>-0.01),"OK","REVISAR") -> OK
B40: Cuadre mensual (RESUMEN_MES) | C40: =IF(AND(MAX(RESUMEN_MES!$AA$6:$AA$29)<0.01,MIN(RESUMEN_MES!$AA$6:$AA$29)>-0.01),"OK","REVISAR") -> OK
B41: Conciliación de comercialización | C41: =COMERCIAL!G39 -> CUADRA
B42: Utilidad antes de impuesto acumulada | C42: =RESUMEN_MES!O30 -> 9168.3167
B45: Los datos que contiene el libro son de EJEMPLO para mostrar su funcionamiento. Sustitúyalos siguiendo la guía en PDF (capítulo «Preparar el libro con sus datos»).

Sheet GUIA_USO
B2: GUÍA DE USO (RESUMEN)
B4: Este libro calcula de forma automática cuánto gana o pierde la empresa con cada contenedor de paquetería, en cada región y en cada mes. Lo lleva UNA sola persona, que solo escribe datos en las celdas de entrada (amarillas, letra azul). Todo lo demás se calcula con fórmulas. La guía completa, con imágenes y ejercicios paso a paso, es el PDF «Guia_de_Uso_Rentabilidad_Paqueteria.pdf» que acompaña a este archivo.
B6: 1. Colores y convenciones
B7: Aspecto de la celda | C7: Significado | D7: ¿Se puede escribir?
B8: Fondo amarillo claro, letra azul | C8: Dato de entrada (valor que usted escribe) | D8: SÍ
B9: Letra negra | C9: Fórmula de cálculo | D9: NO
B10: Letra verde | C10: Enlace a otra hoja | D10: NO
B11: Fondo gris en encabezados | C11: Títulos de columnas y secciones | D11: NO
B12: Celda vacía en columnas «(opcional)» | C12: El libro usa la norma técnica de PARAMETROS | D12: Sí, si hay dato real
B14: Las hojas están protegidas sin contraseña para evitar borrar fórmulas por error. Si necesita modificar la estructura: Revisar > Desproteger hoja. Vuelva a protegerla al terminar.
B16: 2. Configuración inicial (una sola vez)
B17: 1. PARAMETROS: escriba el nombre de la empresa, el primer mes del período (Fecha_Inicio) y revise las normas técnicas: litros por viaje, kilómetros, capacidad de los camiones y rendimiento del desagrupe (kg por jornal). Revise también los porcentajes de reclamaciones, de comisiones bancarias y las tasas tributarias.
B18: 2. PRECIOS: en la primera fila escriba las tarifas por kg que cobra la empresa en cada región, el precio del diésel, la cita del puerto, la dieta, el pago por jornal y las comisiones de comercialización, con la fecha desde la que rigen.
B19: 3. ACTIVOS: registre cada vehículo propio y cada equipo con su fecha de alta, valor de compra, valor residual y vida útil. El libro calcula la depreciación mensual y deja de calcularla al terminar la vida útil o en la fecha de baja.
B20: 4. COSTOS_FIJOS: escriba en la columna «Valor base mensual» cada gasto fijo (salarios de oficina, alquiler, electricidad, servicios contratados de chofer y ayudante por región, etc.). Indique si es salario de un trabajador propio («Sí» en la columna correspondiente): así se calculan la seguridad social (14 %) y el impuesto por la utilización de la fuerza de trabajo (5 %).
B21: 5. COMERCIAL: escriba los nombres de los 21 gestores (5 del grupo central y 16 provinciales) y el pago fijo mensual de cada uno. El total pasa solo a COSTOS_FIJOS.
B22: 6. Borre los datos de EJEMPLO de las hojas ENTRADA, PRECIOS, ACTIVOS y COMERCIAL. Seleccione las celdas y pulse la tecla Supr. NUNCA elimine filas ni columnas.
B23: 3. Registro de cada contenedor (hoja ENTRADA)
B24: Use una fila por contenedor. Los datos se registran en dos momentos:
B26: 1. Al recibir el contenedor: ID del contenedor, fecha de arribo, transitaria (ENCI o A.V), tipo, número de bultos y kg que van a cada región (Occidente, Centro, Oriente), según el manifiesto o desglose. Ponga el Estado en «Abierto».
B27: 2. Al terminar la distribución, escriba los datos REALES que tenga: viajes y litros al puerto, dieta pagada, jornales del desagrupe, litros de traslado y de distribución por región, jornales de los centros transitorios, cargos por estadía o almacenaje, otros gastos directos con su detalle y otros ingresos. Ponga la fecha de fin de la distribución y cambie el Estado a «Cerrado».
... B40: 6. Cómo leer los resultados
B41: Indicador | C41: Qué significa | D41: Cómo se calcula
B42: Margen de contribución (MC) | C42: Lo que queda de los ingresos para cubrir los costos fijos | D42: Ingresos − costos variables
B43: Utilidad antes de impuesto (UAI) | C43: Ganancia o pérdida después de todos los costos y de los tributos sobre ingresos | D43: MC − costos fijos − impuesto sobre ventas y servicios − contribución territorial
B44: Utilidad neta estimada | C44: Ganancia después del impuesto sobre utilidades (estimado) | D44: UAI − 35 % de la UAI positiva
B45: Costo total por kg | C45: Lo que cuesta mover 1 kg de punta a punta | D45: Costos totales ÷ kg
B46: Punto de equilibrio (kg) | C46: kg mínimos del mes para no perder dinero | D46: Costos fijos ÷ (MC − tributos sobre ingresos) por kg
B47: Margen de seguridad | C47: Cuánto pueden caer los kg antes de entrar en pérdida | D47: (kg reales − kg de equilibrio) ÷ kg reales
B48: Fijos no absorbidos | C48: Costos fijos del mes que ningún contenedor cubrió (meses sin arribos o regiones sin carga) | D48: Fijos del mes − fijos asignados a contenedores
B49: Tarifa mínima (SIMULADOR) | C49: Precio por kg por debajo del cual la región pierde dinero | D49: Costos de la región ÷ kg ajustados por los % sobre ingreso
B51: • Utilidad de una región: ingresos de la región menos sus costos propios (combustible, desagrupe, comisión y fijos regionales), menos su parte de los costos compartidos (puerto, transitaria, fijos generales) según sus kg.
B52: • El impuesto sobre utilidades es una ESTIMACIÓN. La liquidación oficial es anual: use la tabla anual de RESUMEN_MES y valídela con el contador y la ONAT.
B53: 7. Simulador («¿qué pasaría si...?»)
B54: En SIMULADOR la columna «Valor actual» trae los datos reales del libro. Escriba un valor en «Valor a simular» para probar un escenario: subir la tarifa, subir el diésel, recibir más contenedores, etc. Borre el valor para volver al dato real. Las tablas de sensibilidad muestran la utilidad mensual para distintas tarifas, precios del diésel y cantidades de contenedores. El simulador no modifica ningún dato del libro.
B56: 8. Alertas y cómo resolverlas
B57: Alerta | C57: Causa | D57: Qué hacer
B58: Falta fecha / Falta transitaria | C58: Dato obligatorio vacío | D58: Complete la columna en ENTRADA
B59: Mes fuera del rango de COSTOS_FIJOS | C59: La fecha cae fuera de los 24 meses del período | D59: Corrija la fecha, o cambie Fecha_Inicio en PARAMETROS al comenzar un nuevo período (guarde antes una copia)
B60: Sin kg | C60: No se registraron kg por región | D60: Escriba los kg de Occidente, Centro y Oriente
B61: Combustible X % sobre norma | C61: El consumo real supera la norma más la tolerancia | D61: Revise vales y hojas de ruta. Si la norma está desactualizada, corríjala en PARAMETROS
B62: Fecha anterior a la 1ª vigencia de precios | C62: No hay precios para esa fecha | D62: Agregue en PRECIOS una vigencia anterior
B63: Contenedor con pérdida | C63: Los costos superan los ingresos | D63: Analice la causa en CALCULO (región, combustible, estadía)
B65: 9. Reglas de oro
B66: • Nunca elimine filas ni columnas. Para borrar datos, seleccione las celdas y pulse Supr.
B67: • Escriba solo en las celdas amarillas. No copie y pegue formatos desde otros archivos: use «Pegar valores».
B68: • Escriba los números sin texto: 60, no «60 L». Escriba las fechas como dd/mm/aaaa.
B69: • Trabaje siempre sobre un único archivo maestro. No haga copias de trabajo paralelas: las copias con fecha son solo respaldos.
B70: • Haga una copia de respaldo semanal y otra en cada cierre mensual.
B71: • El libro admite 300 contenedores en ENTRADA y 24 meses. Al llegar al límite, guarde el archivo como histórico y empiece uno nuevo con Fecha_Inicio actualizada.
B72: 10. Preguntas frecuentes
B73: • ¿Por qué cambia la utilidad de un contenedor cuando registro otro del mismo mes? Porque los costos fijos del mes se reparten entre todos los contenedores del mes según sus kg. El resultado de un mes es definitivo al cerrarlo.
B74: • ¿Puedo cambiar el método de reparto de los fijos? Sí, en PARAMETROS > Metodo_Prorrateo: KG (recomendado) o CONTENEDOR (partes iguales).
B75: • ¿Cómo registro un gasto que no aparece en ninguna columna? Úselo como «Otros gastos directos» en ENTRADA, si es del contenedor, o como fila «Otros fijos» en COSTOS_FIJOS, si es del mes.
B76: • ¿Qué hago si cambian los impuestos? Actualice las tasas en PARAMETROS, sección D, después de consultarlo con el contador.
B77: • ¿Por qué los meses futuros no muestran costos fijos? Porque todavía no han ocurrido. Los resultados llegan hasta el «mes de corte»: el último mes con contenedores, o el que se fije en PARAMETROS > Mes_Corte. Un mes YA transcurrido sin arribos sí carga sus costos fijos, porque es capacidad ociosa real.

Sheet ANALISIS
B1: Fuentes de tributos y combustible: ver README (enlaces). Valores ILUSTRATIVOS marcados en PARAMETROS y PRECIOS.
B2: ANÁLISIS ECONÓMICO Y PROPUESTA
B4: Objetivo: medir con rigor la rentabilidad del negocio de paquetería por contenedor, por región y por mes; identificar dónde se gana y dónde se pierde dinero; y dar a la dirección indicadores para decidir tarifas, rutas y volumen.
B6: 1. Diagnóstico del flujo actual
B7: Etapa | C7: Actividad | D7: Recurso | E7: Costos identificados | F7: Comportamiento
B8: 1. Puerto | C8: Recogida del contenedor en el muelle | D8: Vehículo PROPIO | E8: Cita (10 USD), 60 L de combustible, dieta del chofer, desgaste, depreciación, mantenimiento | F8: Variable por viaje + fijo mensual
B9: 2. Transitaria (ENCI / A.V) | C9: Desagrupe y clasificación por destinatario | D9: Mano de obra por jornada | E9: Jornales; posibles cargos de la transitaria, almacenaje y estadía | F9: Variable por kg / contenedor
B10: 3a. Occidente | C10: Distribución directa | D10: Servicio contratado a terceros | E10: Chofer y ayudante (pago fijo mensual) + combustible de distribución | F10: Fijo mensual + variable
B11: 3b. Centro y Oriente | C11: Traslado a centro transitorio, desagrupe y distribución | D11: Servicio contratado a terceros | E11: Chofer y ayudante + combustible de traslado + jornales de desagrupe + combustible de distribución | F11: Fijo mensual + variable
B12: 4. Comercialización | C12: Gestión y cobro en 16 territorios + grupo central de 5 | D12: 21 gestores | E12: Pago fijo igual para todos + parte variable según lo gestionado | F12: Fijo mensual + variable
B13: Transversal | C13: Dirección, contabilidad, local, servicios | D13: Estructura | E13: Salarios, alquiler, electricidad, comunicaciones, seguros, tributos | F13: Fijo mensual
B15: 2. Problemas de la medición actual
B16: • No se separan los costos fijos de los variables. Sin esa separación no se puede calcular el punto de equilibrio ni saber cuánto aporta cada kg.
B17: • Faltan costos ocultos: depreciación y mantenimiento del vehículo propio, tributos sobre ingresos y salarios, estadía y almacenaje del contenedor, mermas y reclamaciones, y comisiones bancarias. Por eso la rentabilidad aparente es MAYOR que la real.
B18: • Centro y Oriente tienen dos tramos de transporte y un segundo desagrupe. Con una tarifa por kg igual en todo el país, el Occidente probablemente subsidia al Oriente. Hoy no se puede ver.
B19: • No existen normas de consumo de combustible por ruta. Los desvíos (consumo excesivo, pérdidas) no se detectan.
B20: • Los precios cambian (el diésel en USD varía desde mayo de 2026) y no hay historial. Si se sobrescriben, se pierde el costo real de los contenedores anteriores.
B21: • La parte variable de la comercialización no se concilia con los kg o ingresos realmente entregados y cobrados.
B22: 3. Metodología del modelo propuesto
B23: • Costeo variable (direct costing) para decidir: margen de contribución por contenedor, por kg y por región, punto de equilibrio y margen de seguridad.
B24: • Costeo por absorción para conocer el costo completo: los costos fijos mensuales se reparten entre los contenedores del mes según sus kg o en partes iguales. Los fijos regionales se reparten solo entre los kg de esa región.
B25: • Centros de costo: Puerto, Transitaria, Occidente, Centro, Oriente, Comercialización y Generales. Cada costo tiene un inductor: viajes, kg, jornales, litros o ingreso.
B26: • Precios con vigencia (hoja PRECIOS): cada contenedor se valora con los precios de su fecha de arribo. El historial queda intacto y es auditable.
... B30: 4. Clasificación de costos
B31: Concepto | C31: Centro de costo | D31: Tipo | E31: Inductor | F31: Elemento de gasto
B32: Cita del puerto | C32: Puerto | D32: Variable | E32: Viaje | F32: Otros gastos monetarios
B33: Combustible al puerto | C33: Puerto | D33: Variable | E33: Litros (norma 60 L/viaje) | F33: Combustibles y lubricantes
B34: Dieta del chofer | C34: Puerto | D34: Variable | E34: Viaje | F34: Otros gastos monetarios
B35: Desgaste (neumáticos, lubricantes) | C35: Puerto | D35: Variable | E35: Km recorridos | F35: Materias primas y materiales
B36: Depreciación del vehículo propio | C36: Generales | D36: Fijo | E36: Mes (vida útil) | F36: Depreciación y amortización
B37: Mantenimiento preventivo, seguros y licencias | C37: Generales | D37: Fijo | E37: Mes | F37: Otros gastos monetarios
B38: Jornales de desagrupe (ENCI / A.V) | C38: Transitaria | D38: Variable | E38: Jornal (kg / rendimiento) | F38: Gastos de fuerza de trabajo
B39: Servicio de la transitaria, estadía y almacenaje | C39: Transitaria | D39: Variable | E39: Contenedor / días | F39: Otros gastos monetarios
B40: Chofer y ayudante (servicio contratado) | C40: Occidente / Centro / Oriente | D40: Fijo | E40: Mes | F40: Otros gastos monetarios
B41: Combustible de traslado y distribución | C41: Occidente / Centro / Oriente | D41: Variable | E41: Litros (viajes × norma) | F41: Combustibles y lubricantes
B42: Jornales de desagrupe en centro transitorio | C42: Centro / Oriente | D42: Variable | E42: Jornal | F42: Gastos de fuerza de trabajo
... B50: Impuesto sobre utilidades (35 %) | C50: Resultado | D50: Sobre utilidad | E50: Utilidad anual | F50: Tributo
B52: 5. Propuestas de mejora (ordenadas por impacto económico)
B53: # | C53: Propuesta | D53: Beneficio esperado | E53: Prioridad
B54: 1 | C54: Tarifa diferenciada por región (la hoja SIMULADOR calcula la tarifa mínima de cada región) | D54: Evita que Occidente subsidie a Centro y Oriente; protege el margen | E54: ALTA
B55: 2 | C55: Normas de consumo de combustible por ruta, con hoja de ruta, kilometraje y vales por viaje | D55: El combustible es el mayor costo variable: un control del 10 % se nota directamente en la utilidad | E55: ALTA
B56: 3 | C56: Recoger el contenedor dentro de los días libres de la naviera y de la transitaria | D56: Elimina los cargos por estadía, demora y almacenaje | E56: ALTA
B57: 4 | C57: Liquidar la comercialización variable sobre lo COBRADO, con conciliación mensual (hoja COMERCIAL) | D57: Evita pagar comisiones sobre carga no cobrada y detecta diferencias | E57: ALTA
B58: 5 | C58: Pedir a ENCI y A.V sus tarifas por escrito y compararlas para cada contenedor | D58: Elegir la transitaria más económica según el volumen | E58: MEDIA
B59: 6 | C59: Consolidar viajes a Centro y Oriente: no salir con el camión a menos del 80 % de su capacidad | D59: Menos viajes y menos litros por kg | E59: MEDIA
B60: 7 | C60: Evaluar si conviene contratar servicios fijos mensuales o pagar por viaje, según el volumen de cada región | D60: Convertir costo fijo en variable cuando hay pocos contenedores reduce el riesgo | E60: MEDIA
B61: 8 | C61: Buscar carga de retorno para los camiones que vuelven vacíos de Centro y Oriente | D61: Ingreso adicional casi sin costo | E61: MEDIA
B62: 9 | C62: Crear un fondo de reposición del vehículo propio igual a la depreciación mensual | D62: Garantiza la continuidad de la operación | E62: MEDIA
B63: 10 | C63: Asegurar la mercancía en tránsito y crear una provisión para reclamaciones | D63: Protege contra pérdidas extraordinarias | E63: MEDIA
B64: 11 | C64: Registrar los kg y bultos por provincia en cada contenedor; más adelante, por cliente o agencia emisora | D64: Permite saber la rentabilidad por cliente y por provincia | E64: BAJA
B65: 12 | C65: Cuando el volumen supere unos 25 contenedores al mes, pasar el registro a una base de datos o a un sistema de gestión (ERP) | D65: Escalabilidad, varios usuarios y trazabilidad | E65: BAJA
B67: 6. Indicadores que la dirección debe revisar cada mes
B68: • Utilidad antes de impuesto y margen % del mes y del año (DASHBOARD).
B69: • Costo total por kg e ingreso por kg. La diferencia es la utilidad por kg.
B70: • Utilidad por región y su tendencia.
B71: • Punto de equilibrio (kg y contenedores por mes) y margen de seguridad.
B72: • Desvío del consumo de combustible respecto a la norma (%).
B73: • Días de ciclo: desde el arribo hasta el fin de la distribución.
B74: • Costos fijos no absorbidos: indican capacidad ociosa.
B75: 7. Supuestos del modelo y datos por confirmar
B76: Supuesto | C76: Valor usado | D76: Fuente / estado
B77: Moneda de registro | C77: USD para todo | D77: Indicado por la empresa
B78: Ingreso | C78: Tarifa por kg por región | D78: Indicado por la empresa; el valor 0,80 USD/kg es ILUSTRATIVO
B79: Unidad de análisis | C79: Contenedor; consolidado mensual para los fijos | D79: Indicado por la empresa
B80: Cita del puerto | C80: 10 USD por viaje | D80: Indicado por la empresa
B81: Combustible al puerto | C81: 60 L por viaje | D81: Indicado por la empresa
B82: Precio del diésel | C82: 2,00 USD/L | D82: Referencia oficial de CUPET para 2026 (diésel regular). Varía por operación: confirmar con las facturas
B83: Vehículo propio | C83: Solo en la recogida en el puerto | D83: Indicado por la empresa
B84: Distribución regional | C84: Servicio de terceros: chofer y ayudante con pago fijo mensual | D84: Indicado por la empresa
B85: Desagrupe | C85: Pago por jornal, igual en ENCI y A.V | D85: Indicado por la empresa
B86: Comercialización | C86: 21 gestores (5 + 16) con fijo igual + variable según lo gestionado | D86: Indicado por la empresa; las tasas son ILUSTRATIVAS
B87: Tributos | C87: Ventas y servicios 10 %, territorial 1 %, seguridad social 14 %, fuerza de trabajo 5 %, utilidades 35 % | D87: Régimen general de MIPYMES (Ley 113 y Ley del Presupuesto 2026). Confirmar el régimen de la empresa con el contador y la ONAT
... B89: Gastos fijos y salarios | C89: Valores de COSTOS_FIJOS | D89: ILUSTRATIVOS: sustituir por los registros contables
B91: 8. Plan de implantación
B92: 1. Semana 1: el responsable del libro carga PRECIOS, ACTIVOS, COSTOS_FIJOS y COMERCIAL con datos reales y borra los ejemplos.
B93: 2. Semanas 2 a 4: el responsable registra los contenedores del mes en curso y, si hay datos, de los 2 o 3 meses anteriores.
B94: 3. Mes 1: se miden en la práctica las normas de combustible y de desagrupe, y se ajusta PARAMETROS.
B95: 4. Mes 2: primer cierre mensual con conciliación de la comercialización. Se presenta a la dirección la tarifa mínima por región (SIMULADOR).
B96: 5. Mes 3: decisión sobre las tarifas diferenciadas y la consolidación de viajes. Se revisa el resultado frente a la contabilidad oficial.

Sheet DASHBOARD
A1: Panel de rentabilidad
A2: ="Empresa: "&Empresa -> Empresa: Empresa de Paquetería (editar)
B4: Período desde (mes) | C4: 46266 | D4: Elija el primer día del mes (dd/mm/aaaa) o seleccione de la lista.
B5: Período hasta (mes) | C5: 46296 | D5: =IF(C5<C4,"ATENCIÓN: «hasta» es anterior a «desde»","")
B7: INDICADOR | C7: VALOR | G7: INDICADOR | H7: VALOR
B8: Contenedores | C8: =SUMIFS(RESUMEN_MES!$B$6:$B$29,RESUMEN_MES!$A$6:$A$29,">="&$C$4,RESUMEN_MES!$A$6:$A$29,"<="&$C$5) -> 4 | G8: Margen neto % | H8: =IF(C10=0,0,C18/C10) -> 0.18490245
B9: kg distribuidos | C9: =SUMIFS(RESUMEN_MES!$F$6:$F$29,RESUMEN_MES!$A$6:$A$29,">="&$C$4,RESUMEN_MES!$A$6:$A$29,"<="&$C$5) -> 40100 | G9: Ingreso por kg | H9: =IF(C9=0,0,C10/C9) -> 0.80374065
B10: Ingresos | C10: =SUMIFS(RESUMEN_MES!$G$6:$G$29,RESUMEN_MES!$A$6:$A$29,">="&$C$4,RESUMEN_MES!$A$6:$A$29,"<="&$C$5) -> 32230 | G10: Costo total por kg | H10: =IF(C9=0,0,(C11+C14+C15)/C9) -> 0.57510432
B11: Costos variables | C11: =SUMIFS(RESUMEN_MES!$H$6:$H$29,RESUMEN_MES!$A$6:$A$29,">="&$C$4,RESUMEN_MES!$A$6:$A$29,"<="&$C$5) -> 13036.25 | G11: Utilidad antes de impuesto por kg | H11: =IF(C9=0,0,C16/C9) -> 0.22863633
B12: Margen de contribución | C12: =C10-C11 -> 19193.75 | G12: Utilidad media por contenedor | H12: =IF(C8=0,0,C16/C8) -> 2292.0792
B13: MC % | C13: =IF(C10=0,0,C12/C10) -> 0.59552436 | G13: Punto de equilibrio del período (kg) | H13: =IF(C9=0,"s/d",IF(C12-C15<=0,"No cubre",C14/((C12-C15)/C9))) -> 16605.692
B14: Costos fijos del período | C14: =SUMIFS(RESUMEN_MES!$K$6:$K$29,RESUMEN_MES!$A$6:$A$29,">="&$C$4,RESUMEN_MES!$A$6:$A$29,"<="&$C$5) -> 6480.1333 | G14: Punto de equilibrio (contenedores) | H14: =IF(ISNUMBER(H13),H13/(C9/C8),"s/d") -> 1.6564282
B15: Tributos sobre ingresos | C15: =SUMIFS(RESUMEN_MES!$N$6:$N$29,RESUMEN_MES!$A$6:$A$29,">="&$C$4,RESUMEN_MES!$A$6:$A$29,"<="&$C$5) -> 3545.3 | G15: Margen de seguridad | H15: =IF(ISNUMBER(H13),(C9-H13)/C9,"s/d") -> 0.58589296
B16: UTILIDAD ANTES DE IMPUESTO | C16: =C12-C14-C15 -> 9168.3167 | G16: Fijos no absorbidos (capacidad ociosa) | H16: =SUMIFS(RESUMEN_MES!$M$6:$M$29,RESUMEN_MES!$A$6:$A$29,">="&$C$4,RESUMEN_MES!$A$6:$A$29,"<="&$C$5) -> 0
B17: Impuesto sobre utilidades (estimado) | C17: =MAX(0,C16)*Imp_Utilidades -> 3208.9108 | G17: Contenedores con alerta (todo el libro) | H17: =COUNTIF(CALCULO!$CT$6:$CT$305,"?*") -> 1
B18: UTILIDAD NETA ESTIMADA | C18: =C16-C17 -> 5959.4058 | G18: Desvío medio del combustible | H18: =IFERROR(SUMIFS(CALCULO!$CQ$6:$CQ$305,CALCULO!$D$6:$D$305,">="&$C$4,CALCULO!$D$6:$D$305,"<="&$C$5)/SUMIFS(CALCULO!$CP$6:$CP$305,CALCULO!$D$6:$D$305,">="&$C$4,CALCULO!$D$6:$D$305,"<="&$C$5)-1,0) -> 0.0043307087
B20: Estructura de costos del período | G20: Rentabilidad por región del período
B21: Concepto | C21: USD | D21: % de los ingresos | E21: USD por kg | G21: Región | H21: kg | I21: Ingresos | J21: Utilidad antes de impuesto | K21: Margen %
B22: Puerto (vehículo propio) | C22: =SUMIFS(CALCULO!$Y$6:$Y$305,CALCULO!$D$6:$D$305,">="&$C$4,CALCULO!$D$6:$D$305,"<="&$C$5) -> 650.4 | D22: =IF($C$10=0,0,C22/$C$10) -> 0.020179957 | E22: =IF($C$9=0,0,C22/$C$9) -> 0.016219451 | G22: Occidente | H22: =SUMIFS(CALCULO!$G$6:$G$305,CALCULO!$D$6:$D$305,">="&$C$4,CALCULO!$D$6:$D$305,"<="&$C$5) -> 19700 | I22: =SUMIFS(CALCULO!$M$6:$M$305,CALCULO!$D$6:$D$305,">="&$C$4,CALCULO!$D$6:$D$305,"<="&$C$5) -> 15760 | J22: =SUMIFS(RESUMEN_MES!$W$6:$W$29,RESUMEN_MES!$A$6:$A$29,">="&$C$4,RESUMEN_MES!$A$6:$A$29,"<="&$C$5) -> 8420.2208 | K22: =IF(I22=0,0,J22/I22) -> 0.53427797
B23: Transitaria (desagrupe y estadía) | C23: =SUMIFS(CALCULO!$AE$6:$AE$305,CALCULO!$D$6:$D$305,">="&$C$4,CALCULO!$D$6:$D$305,"<="&$C$5) -> 765 | D23: =IF($C$10=0,0,C23/$C$10) -> 0.02373565 | E23: =IF($C$9=0,0,C23/$C$9) -> 0.019077307 | G23: Centro | H23: =SUMIFS(CALCULO!$H$6:$H$305,CALCULO!$D$6:$D$305,">="&$C$4,CALCULO!$D$6:$D$305,"<="&$C$5) -> 9100 | I23: =SUMIFS(CALCULO!$N$6:$N$305,CALCULO!$D$6:$D$305,">="&$C$4,CALCULO!$D$6:$D$305,"<="&$C$5) -> 7280 | J23: =SUMIFS(RESUMEN_MES!$X$6:$X$29,RESUMEN_MES!$A$6:$A$29,">="&$C$4,RESUMEN_MES!$A$6:$A$29,"<="&$C$5) -> 861.63433 | K23: =IF(I23=0,0,J23/I23) -> 0.11835636
B24: Distribución Occidente | C24: =SUMIFS(CALCULO!$AI$6:$AI$305,CALCULO!$D$6:$D$305,">="&$C$4,CALCULO!$D$6:$D$305,"<="&$C$5) -> 1260 | D24: =IF($C$10=0,0,C24/$C$10) -> 0.039094012 | E24: =IF($C$9=0,0,C24/$C$9) -> 0.031421446 | G24: Oriente | H24: =SUMIFS(CALCULO!$I$6:$I$305,CALCULO!$D$6:$D$305,">="&$C$4,CALCULO!$D$6:$D$305,"<="&$C$5) -> 11300 | I24: =SUMIFS(CALCULO!$O$6:$O$305,CALCULO!$D$6:$D$305,">="&$C$4,CALCULO!$D$6:$D$305,"<="&$C$5) -> 9040 | J24: =SUMIFS(RESUMEN_MES!$Y$6:$Y$29,RESUMEN_MES!$A$6:$A$29,">="&$C$4,RESUMEN_MES!$A$6:$A$29,"<="&$C$5) -> -113.5385 | K24: =IF(I24=0,0,J24/I24) -> -0.012559568
B25: Distribución Centro | C25: =SUMIFS(CALCULO!$AS$6:$AS$305,CALCULO!$D$6:$D$305,">="&$C$4,CALCULO!$D$6:$D$305,"<="&$C$5) -> 3395 | D25: =IF($C$10=0,0,C25/$C$10) -> 0.10533664 | E25: =IF($C$9=0,0,C25/$C$9) -> 0.084663342 | G25: Fijos no absorbidos | J25: =SUMIFS(RESUMEN_MES!$Z$6:$Z$29,RESUMEN_MES!$A$6:$A$29,">="&$C$4,RESUMEN_MES!$A$6:$A$29,"<="&$C$5) -> 0
B26: Distribución Oriente | C26: =SUMIFS(CALCULO!$BC$6:$BC$305,CALCULO!$D$6:$D$305,">="&$C$4,CALCULO!$D$6:$D$305,"<="&$C$5) -> 5485 | D26: =IF($C$10=0,0,C26/$C$10) -> 0.17018306 | E26: =IF($C$9=0,0,C26/$C$9) -> 0.13678304 | G26: TOTAL | H26: =SUM(H22:H24) -> 40100 | I26: =SUM(I22:I24) -> 32080 | J26: =SUM(J22:J25) -> 9168.3167 | K26: =IF(I26=0,0,J26/I26) -> 0.28579541
B27: Comercialización variable | C27: =SUMIFS(CALCULO!$BH$6:$BH$305,CALCULO!$D$6:$D$305,">="&$C$4,CALCULO!$D$6:$D$305,"<="&$C$5) -> 962.4 | D27: =IF($C$10=0,0,C27/$C$10) -> 0.029860379 | E27: =IF($C$9=0,0,C27/$C$9) -> 0.024 | G27: Los ingresos regionales no incluyen «otros ingresos», que se reparten en la utilidad según los kg.
B28: Reclamaciones y banca | C28: =SUMIFS(CALCULO!$BI$6:$BI$305,CALCULO!$D$6:$D$305,">="&$C$4,CALCULO!$D$6:$D$305,"<="&$C$5)+SUMIFS(CALCULO!$BJ$6:$BJ$305,CALCULO!$D$6:$D$305,">="&$C$4,CALCULO!$D$6:$D$305,"<="&$C$5) -> 483.45 | D28: =IF($C$10=0,0,C28/$C$10) -> 0.015 | E28: =IF($C$9=0,0,C28/$C$9) -> 0.01205611
B29: Otros gastos directos | C29: =SUMIFS(CALCULO!$BK$6:$BK$305,CALCULO!$D$6:$D$305,">="&$C$4,CALCULO!$D$6:$D$305,"<="&$C$5) -> 35 | D29: =IF($C$10=0,0,C29/$C$10) -> 0.0010859448 | E29: =IF($C$9=0,0,C29/$C$9) -> 0.00087281796
B30: Costos fijos | C30: =SUMIFS(RESUMEN_MES!$K$6:$K$29,RESUMEN_MES!$A$6:$A$29,">="&$C$4,RESUMEN_MES!$A$6:$A$29,"<="&$C$5) -> 6480.1333 | D30: =IF($C$10=0,0,C30/$C$10) -> 0.20105905 | E30: =IF($C$9=0,0,C30/$C$9) -> 0.16159933
B31: Tributos sobre ingresos | C31: =SUMIFS(RESUMEN_MES!$N$6:$N$29,RESUMEN_MES!$A$6:$A$29,">="&$C$4,RESUMEN_MES!$A$6:$A$29,"<="&$C$5) -> 3545.3 | D31: =IF($C$10=0,0,C31/$C$10) -> 0.11 | E31: =IF($C$9=0,0,C31/$C$9) -> 0.088411471
B32: TOTAL COSTOS | C32: =SUM(C22:C31) -> 23061.683 | D32: =IF($C$10=0,0,C32/$C$10) -> 0.7155347 | E32: =IF($C$9=0,0,C32/$C$9) -> 0.57510432
B33: Control: ingresos − costos − utilidad (debe ser 0) | C33: =ROUND(C10-C32-C16,2) -> 0
B35: Evolución mensual del período (máx. 12 meses)
B36: Mes | C36: Ingresos | D36: Costos totales | E36: Utilidad antes de impuesto
B37: =IF(EDATE($C$4,0)>$C$5,"",EDATE($C$4,0)) -> 46266 | C37: =IF($B37="","",SUMIFS(RESUMEN_MES!$G$6:$G$29,RESUMEN_MES!$A$6:$A$29,$B37)) -> 15600 | D37: =IF($B37="","",SUMIFS(RESUMEN_MES!$AB$6:$AB$29,RESUMEN_MES!$A$6:$A$29,$B37)) -> 11530.267 | E37: =IF($B37="","",SUMIFS(RESUMEN_MES!$O$6:$O$29,RESUMEN_MES!$A$6:$A$29,$B37)) -> 4069.7333
B38: =IF(EDATE($C$4,1)>$C$5,"",EDATE($C$4,1)) -> 46296 | C38: =IF($B38="","",SUMIFS(RESUMEN_MES!$G$6:$G$29,RESUMEN_MES!$A$6:$A$29,$B38)) -> 16630 | D38: =IF($B38="","",SUMIFS(RESUMEN_MES!$AB$6:$AB$29,RESUMEN_MES!$A$6:$A$29,$B38)) -> 11531.417 | E38: =IF($B38="","",SUMIFS(RESUMEN_MES!$O$6:$O$29,RESUMEN_MES!$A$6:$A$29,$B38)) -> 5098.5833
B39: =IF(EDATE($C$4,2)>$C$5,"",EDATE($C$4,2)) | C39: =IF($B39="","",SUMIFS(RESUMEN_MES!$G$6:$G$29,RESUMEN_MES!$A$6:$A$29,$B39)) | D39: =IF($B39="","",SUMIFS(RESUMEN_MES!$AB$6:$AB$29,RESUMEN_MES!$A$6:$A$29,$B39)) | E39: =IF($B39="","",SUMIFS(RESUMEN_MES!$O$6:$O$29,RESUMEN_MES!$A$6:$A$29,$B39))
B40: =IF(EDATE($C$4,3)>$C$5,"",EDATE($C$4,3)) | C40: =IF($B40="","",SUMIFS(RESUMEN_MES!$G$6:$G$29,RESUMEN_MES!$A$6:$A$29,$B40)) | D40: =IF($B40="","",SUMIFS(RESUMEN_MES!$AB$6:$AB$29,RESUMEN_MES!$A$6:$A$29,$B40)) | E40: =IF($B40="","",SUMIFS(RESUMEN_MES!$O$6:$O$29,RESUMEN_MES!$A$6:$A$29,$B40))
B41: =IF(EDATE($C$4,4)>$C$5,"",EDATE($C$4,4)) | C41: =IF($B41="","",SUMIFS(RESUMEN_MES!$G$6:$G$29,RESUMEN_MES!$A$6:$A$29,$B41)) | D41: =IF($B41="","",SUMIFS(RESUMEN_MES!$AB$6:$AB$29,RESUMEN_MES!$A$6:$A$29,$B41)) | E41: =IF($B41="","",SUMIFS(RESUMEN_MES!$O$6:$O$29,RESUMEN_MES!$A$6:$A$29,$B41))
B42: =IF(EDATE($C$4,5)>$C$5,"",EDATE($C$4,5)) | C42: =IF($B42="","",SUMIFS(RESUMEN_MES!$G$6:$G$29,RESUMEN_MES!$A$6:$A$29,$B42)) | D42: =IF($B42="","",SUMIFS(RESUMEN_MES!$AB$6:$AB$29,RESUMEN_MES!$A$6:$A$29,$B42)) | E42: =IF($B42="","",SUMIFS(RESUMEN_MES!$O$6:$O$29,RESUMEN_MES!$A$6:$A$29,$B42))
B43: =IF(EDATE($C$4,6)>$C$5,"",EDATE($C$4,6)) | C43: =IF($B43="","",SUMIFS(RESUMEN_MES!$G$6:$G$29,RESUMEN_MES!$A$6:$A$29,$B43)) | D43: =IF($B43="","",SUMIFS(RESUMEN_MES!$AB$6:$AB$29,RESUMEN_MES!$A$6:$A$29,$B43)) | E43: =IF($B43="","",SUMIFS(RESUMEN_MES!$O$6:$O$29,RESUMEN_MES!$A$6:$A$29,$B43))
B44: =IF(EDATE($C$4,7)>$C$5,"",EDATE($C$4,7)) | C44: =IF($B44="","",SUMIFS(RESUMEN_MES!$G$6:$G$29,RESUMEN_MES!$A$6:$A$29,$B44)) | D44: =IF($B44="","",SUMIFS(RESUMEN_MES!$AB$6:$AB$29,RESUMEN_MES!$A$6:$A$29,$B44)) | E44: =IF($B44="","",SUMIFS(RESUMEN_MES!$O$6:$O$29,RESUMEN_MES!$A$6:$A$29,$B44))
B45: =IF(EDATE($C$4,8)>$C$5,"",EDATE($C$4,8)) | C45: =IF($B45="","",SUMIFS(RESUMEN_MES!$G$6:$G$29,RESUMEN_MES!$A$6:$A$29,$B45)) | D45: =IF($B45="","",SUMIFS(RESUMEN_MES!$AB$6:$AB$29,RESUMEN_MES!$A$6:$A$29,$B45)) | E45: =IF($B45="","",SUMIFS(RESUMEN_MES!$O$6:$O$29,RESUMEN_MES!$A$6:$A$29,$B45))
B46: =IF(EDATE($C$4,9)>$C$5,"",EDATE($C$4,9)) | C46: =IF($B46="","",SUMIFS(RESUMEN_MES!$G$6:$G$29,RESUMEN_MES!$A$6:$A$29,$B46)) | D46: =IF($B46="","",SUMIFS(RESUMEN_MES!$AB$6:$AB$29,RESUMEN_MES!$A$6:$A$29,$B46)) | E46: =IF($B46="","",SUMIFS(RESUMEN_MES!$O$6:$O$29,RESUMEN_MES!$A$6:$A$29,$B46))
B47: =IF(EDATE($C$4,10)>$C$5,"",EDATE($C$4,10)) | C47: =IF($B47="","",SUMIFS(RESUMEN_MES!$G$6:$G$29,RESUMEN_MES!$A$6:$A$29,$B47)) | D47: =IF($B47="","",SUMIFS(RESUMEN_MES!$AB$6:$AB$29,RESUMEN_MES!$A$6:$A$29,$B47)) | E47: =IF($B47="","",SUMIFS(RESUMEN_MES!$O$6:$O$29,RESUMEN_MES!$A$6:$A$29,$B47))
B48: =IF(EDATE($C$4,11)>$C$5,"",EDATE($C$4,11)) | C48: =IF($B48="","",SUMIFS(RESUMEN_MES!$G$6:$G$29,RESUMEN_MES!$A$6:$A$29,$B48)) | D48: =IF($B48="","",SUMIFS(RESUMEN_MES!$AB$6:$AB$29,RESUMEN_MES!$A$6:$A$29,$B48)) | E48: =IF($B48="","",SUMIFS(RESUMEN_MES!$O$6:$O$29,RESUMEN_MES!$A$6:$A$29,$B48))

Sheet ENTRADA
A1: Registro de contenedores (ENTRADA DE DATOS)
A2: Una fila por contenedor. Columnas «(opcional)»: si se dejan vacías se usa la norma técnica de PARAMETROS. Para borrar datos use la tecla Supr; nunca elimine filas.
A4: IDENTIFICACIÓN | G4: VOLUMEN (kg) | J4: ETAPA 1 · PUERTO | M4: ETAPA 2 · TRANSITARIA | O4: ETAPA 3 · DISTRIBUCIÓN | V4: OTROS | Y4: CONTROL | AB4: RESULTADO
A5: Nº | B5: ID contenedor | C5: Fecha de arribo | D5: Transitaria | E5: Tipo | F5: Nº de bultos | G5: kg Occidente | H5: kg Centro | I5: kg Oriente | J5: Viajes al puerto (opcional) | K5: Litros reales al puerto (opcional) | L5: Dieta pagada (USD, opcional) | M5: Jornales del desagrupe (opcional) | N5: Estadía / almacenaje / demora (USD) | O5: Litros de distribución en Occidente (opcional) | P5: Litros de traslado a Centro (opcional) | Q5: Litros de distribución en Centro (opcional) | R5: Jornales del centro transitorio en Centro (opcional) | S5: Litros de traslado a Oriente (opcional) | T5: Litros de distribución en Oriente (opcional) | U5: Jornales del centro transitorio en Oriente (opcional) | V5: Otros gastos directos (USD) | W5: Detalle de otros gastos | X5: Otros ingresos (USD) | Y5: Fecha de fin de la distribución | Z5: Estado | AA5: Observaciones / documentos de soporte | AB5: Alertas (automático) | AC5: Utilidad antes de impuesto (automático)
A6: =IF(B6="","",ROW()-5) -> 1 | B6: CONT-EJEMPLO-01 | C6: 46273 | D6: ENCI | E6: 40' HC | F6: 1050 | G6: 5200 | H6: 2600 | I6: 2300 | K6: 62 | M6: 11 | N6: 0 | V6: 0 | X6: 0 | Y6: 46283 | Z6: Cerrado | AA6: EJEMPLO – borrar | AB6: =CALCULO!CT6 | AC6: =CALCULO!CD6 -> 2175.8201
A7: =IF(B7="","",ROW()-5) -> 2 | B7: CONT-EJEMPLO-02 | C7: 46287 | D7: A.V | E7: 40' | F7: 900 | G7: 4600 | H7: 2100 | I7: 2700 | N7: 120 | S7: 480 | V7: 0 | X7: 0 | Y7: 46298 | Z7: Cerrado | AA7: EJEMPLO – 2 días de estadía | AB7: =CALCULO!CT7 | AC7: =CALCULO!CD7 -> 1893.9132
A8: =IF(B8="","",ROW()-5) -> 3 | B8: CONT-EJEMPLO-03 | C8: 46301 | D8: ENCI | E8: 40' HC | F8: 1180 | G8: 6100 | H8: 2900 | I8: 2400 | N8: 0 | O8: 150 | T8: 260 | V8: 35 | W8: Reempaque de bultos dañados | X8: 150 | Y8: 46311 | Z8: Cerrado | AA8: EJEMPLO – desvío de combustible en Oriente | AB8: =CALCULO!CT8 -> Combustible distribución Oriente +44% sobre norma. | AC8: =CALCULO!CD8 -> 3043.8013
A9: =IF(B9="","",ROW()-5) -> 4 | B9: CONT-EJEMPLO-04 | C9: 46315 | D9: A.V | E9: 40' | F9: 860 | G9: 3800 | H9: 1500 | I9: 3900 | N9: 0 | V9: 0 | X9: 0 | Z9: Abierto | AA9: EJEMPLO – pendiente de datos reales | AB9: =CALCULO!CT9 | AC9: =CALCULO!CD9 -> 2054.7821
A10: =IF(B10="","",ROW()-5) | AB10: =CALCULO!CT10 | AC10: =CALCULO!CD10
A11: =IF(B11="","",ROW()-5) | AB11: =CALCULO!CT11 | AC11: =CALCULO!CD11
A12: =IF(B12="","",ROW()-5) | AB12: =CALCULO!CT12 | AC12: =CALCULO!CD12
A13: =IF(B13="","",ROW()-5) | AB13: =CALCULO!CT13 | AC13: =CALCULO!CD13
A14: =IF(B14="","",ROW()-5) | AB14: =CALCULO!CT14 | AC14: =CALCULO!CD14
A15: =IF(B15="","",ROW()-5) | AB15: =CALCULO!CT15 | AC15: =CALCULO!CD15
A16: =IF(B16="","",ROW()-5) | AB16: =CALCULO!CT16 | AC16: =CALCULO!CD16
A17: =IF(B17="","",ROW()-5) | AB17: =CALCULO!CT17 | AC17: =CALCULO!CD17
A18: =IF(B18="","",ROW()-5) | AB18: =CALCULO!CT18 | AC18: =CALCULO!CD18
A19: =IF(B19="","",ROW()-5) | AB19: =CALCULO!CT19 | AC19: =CALCULO!CD19
A20: =IF(B20="","",ROW()-5) | AB20: =CALCULO!CT20 | AC20: =CALCULO!CD20
A21: =IF(B21="","",ROW()-5) | AB21: =CALCULO!CT21 | AC21: =CALCULO!CD21
... A305: =IF(B305="","",ROW()-5) | AB305: =CALCULO!CT305 | AC305: =CALCULO!CD305

Sheet PARAMETROS
A1: Parámetros generales, normas técnicas y tributos
A2: Valores estables del modelo. Los precios que cambian con el tiempo van en la hoja PRECIOS (con fecha de vigencia).
A4: Nombre (referencia) | B4: Concepto | C4: Valor | D4: Unidad | E4: Fuente / nota
A5: A. GENERALES
A6: Empresa | B6: Nombre de la empresa | C6: Empresa de Paquetería (editar) | D6: texto | E6: Aparece en los encabezados.
A7: Fecha_Inicio | B7: Primer mes del período de análisis | C7: 46266 | D7: fecha | E7: Primer mes que se registra. COSTOS_FIJOS y RESUMEN_MES abarcan 24 meses desde esta fecha.
A8: Metodo_Prorrateo | B8: Base de reparto de los costos fijos entre contenedores | C8: KG | D8: lista | E8: KG = proporcional al peso (recomendado: un contenedor más cargado absorbe más estructura). CONTENEDOR = partes iguales.
A9: Base_Comision | B9: Base del pago variable de comercialización | C9: % DEL INGRESO | D9: lista | E9: % DEL INGRESO: tasa sobre lo cobrado. USD POR KG: importe por kg entregado. Las tasas están en PRECIOS.
A10: Tolerancia_Comb | B10: Tolerancia del desvío de combustible frente a la norma | C10: 0.1 | D10: % | E10: Si el consumo real supera la norma en más de este %, se genera una alerta.
A11: Mes_Corte | B11: Último mes incluido en los resultados (opcional) | D11: fecha | E11: Vacío = último mes con contenedores registrados. Los meses posteriores no cargan costos fijos en RESUMEN_MES ni en DASHBOARD.
A12: B. NORMAS TÉCNICAS (se usan cuando no hay dato real)
A13: Std_Viajes_Puerto | B13: Viajes al puerto por contenedor | C13: 1 | D13: viajes | E13: Un contenedor = un viaje del camión propio.
A14: Litros_Puerto_Viaje | B14: Combustible por viaje al puerto | C14: 60 | D14: L / viaje | E14: Dato informado por la empresa.
A15: Km_Puerto_Viaje | B15: Km por viaje al puerto (ida y vuelta) | C15: 180 | D15: km / viaje | E15: ILUSTRATIVO: sustituir por el dato real. Medir con la hoja de ruta.
A16: Rend_Desagrupe | B16: Rendimiento del desagrupe en la transitaria | C16: 1000 | D16: kg / jornal | E16: ILUSTRATIVO: sustituir por el dato real. Jornales = kg ÷ rendimiento (redondeado hacia arriba).
A17: Rend_Desagrupe_CT | B17: Rendimiento del desagrupe en los centros transitorios (Centro y Oriente) | C17: 800 | D17: kg / jornal | E17: ILUSTRATIVO: sustituir por el dato real.
A18: Cap_Camion_OCC | B18: Capacidad útil del camión de distribución – Occidente | C18: 5000 | D18: kg / viaje | E18: ILUSTRATIVO: sustituir por el dato real. Viajes = kg ÷ capacidad (redondeado hacia arriba).
A19: Cap_Camion_CEN | B19: Capacidad útil del camión de traslado – Centro | C19: 5000 | D19: kg / viaje | E19: ILUSTRATIVO: sustituir por el dato real.
A20: Cap_Camion_ORI | B20: Capacidad útil del camión de traslado – Oriente | C20: 5000 | D20: kg / viaje | E20: ILUSTRATIVO: sustituir por el dato real.
A21: L_Dist_OCC | B21: Combustible de distribución en Occidente | C21: 120 | D21: L / viaje | E21: ILUSTRATIVO: sustituir por el dato real.
A22: L_Tras_CEN | B22: Combustible de traslado al centro transitorio – Centro | C22: 250 | D22: L / viaje | E22: ILUSTRATIVO: sustituir por el dato real.
A23: L_Dist_CEN | B23: Combustible de distribución en Centro | C23: 150 | D23: L / viaje | E23: ILUSTRATIVO: sustituir por el dato real.
A24: L_Tras_ORI | B24: Combustible de traslado al centro transitorio – Oriente | C24: 450 | D24: L / viaje | E24: ILUSTRATIVO: sustituir por el dato real.
A25: L_Dist_ORI | B25: Combustible de distribución en Oriente | C25: 180 | D25: L / viaje | E25: ILUSTRATIVO: sustituir por el dato real.
A26: C. OTROS COSTOS VARIABLES (sobre el ingreso)
A27: Pct_Reclamaciones | B27: Provisión para pérdidas, daños y reclamaciones | C27: 0.005 | D27: % ingreso | E27: Recomendado. ILUSTRATIVO: sustituir por el dato real. Use 0 si no aplica.
A28: Pct_Banco | B28: Comisiones bancarias y costo de cobro | C28: 0.01 | D28: % ingreso | E28: Recomendado. ILUSTRATIVO: sustituir por el dato real. Use 0 si no aplica.
A29: D. TRIBUTOS (régimen general MIPYME – confirmar con el contador / ONAT)
A30: Imp_Ventas_Serv | B30: Impuesto sobre las ventas y los servicios | C30: 0.1 | D30: % ingreso | E30: Ley 113 del Sistema Tributario; vigente en 2026 según la Ley del Presupuesto.
A31: Contrib_Territorial | B31: Contribución territorial para el desarrollo local | C31: 0.01 | D31: % ingreso | E31: Ley 113; vigente en 2026.
A32: Contrib_SS | B32: Contribución a la seguridad social (empleador) | C32: 0.14 | D32: % salarios | E32: Solo sobre salarios de trabajadores propios.
A33: Imp_Fuerza_Trabajo | B33: Impuesto por la utilización de la fuerza de trabajo | C33: 0.05 | D33: % salarios | E33: Solo sobre salarios de trabajadores propios. Confirmar si la empresa tiene alguna bonificación.
A34: Imp_Utilidades | B34: Impuesto sobre las utilidades | C34: 0.35 | D34: % utilidad | E34: Liquidación anual con pagos a cuenta. En el libro es una estimación.

Sheet PRECIOS
A1: Precios y tarifas con fecha de vigencia
A2: Cuando cambie un precio, AGREGUE una fila nueva con la fecha desde la que rige (en orden ascendente). No sobrescriba las anteriores: cada contenedor usa los precios vigentes en su fecha de arribo.
A5: Vigente desde | B5: Tarifa Occidente (USD/kg) | C5: Tarifa Centro (USD/kg) | D5: Tarifa Oriente (USD/kg) | E5: Precio diésel (USD/L) | F5: Cita del puerto (USD/viaje) | G5: Dieta del chofer (USD/viaje) | H5: Pago por jornal – transitaria (USD) | I5: Pago por jornal – centro transitorio (USD) | J5: Servicio ENCI (USD/contenedor) | K5: Servicio A.V (USD/contenedor) | L5: Comisión variable (% del ingreso) | M5: Comisión variable (USD/kg) | N5: Desgaste del vehículo propio (USD/km) | O5: Documento de soporte / nota
A6: 46023 | B6: 0.8 | C6: 0.8 | D6: 0.8 | E6: 2 | F6: 10 | G6: 10 | H6: 15 | I6: 15 | J6: 0 | K6: 0 | L6: 0.03 | M6: 0.03 | N6: 0.12 | O6: EJEMPLO. Cita 10 USD = dato de la empresa. Diésel 2,00 USD/L = referencia de CUPET 2026. Resto ILUSTRATIVO: sustituir.

Sheet ACTIVOS
A1: Activos fijos: depreciación, mantenimiento y seguros
A2: Método lineal. La depreciación se calcula desde el mes de alta hasta el fin de la vida útil o la fecha de baja. Confirme las tasas con la norma contable vigente.
A5: Nº | B5: Descripción / chapa | C5: Tipo | D5: Fecha de alta | E5: Valor de adquisición (USD) | F5: Valor residual (USD) | G5: Vida útil (años) | H5: Depreciación anual (USD) | I5: Depreciación mensual (USD) | J5: Fin de la depreciación | K5: Fecha de baja (si se vendió o retiró) | L5: Mantenimiento preventivo (USD/mes) | M5: Seguros, licencias e inspecciones (USD/año) | N5: Seguros y licencias (USD/mes) | O5: Observaciones
A6: 1 | B6: Camión porta-contenedor (recogida en el puerto) – EJEMPLO | C6: Vehículo propio | D6: 45658 | E6: 45000 | F6: 5000 | G6: 8 | H6: =IF(OR(D6="",N(G6)=0),0,(E6-F6)/G6) -> 5000 | I6: =H6/12 -> 416.66667 | J6: =IF(OR(D6="",N(G6)=0),0,EDATE(D6,G6*12)) -> 48580 | L6: 150 | M6: 1020 | N6: =N(M6)/12 -> 85 | O6: ILUSTRATIVO: sustituir por el valor contable real.
A7: 2 | B7: Computadoras y equipos de oficina – EJEMPLO | C7: Equipo | D7: 46023 | E7: 1500 | F7: 0 | G7: 5 | H7: =IF(OR(D7="",N(G7)=0),0,(E7-F7)/G7) -> 300 | I7: =H7/12 -> 25 | J7: =IF(OR(D7="",N(G7)=0),0,EDATE(D7,G7*12)) -> 47849 | L7: 0 | M7: 0 | N7: =N(M7)/12 -> 0 | O7: ILUSTRATIVO
A8: 3 | H8: =IF(OR(D8="",N(G8)=0),0,(E8-F8)/G8) -> 0 | I8: =H8/12 -> 0 | J8: =IF(OR(D8="",N(G8)=0),0,EDATE(D8,G8*12)) -> 00:00:00 | N8: =N(M8)/12 -> 0
A9: 4 | H9: =IF(OR(D9="",N(G9)=0),0,(E9-F9)/G9) -> 0 | I9: =H9/12 -> 0 | J9: =IF(OR(D9="",N(G9)=0),0,EDATE(D9,G9*12)) -> 00:00:00 | N9: =N(M9)/12 -> 0
A10: 5 | H10: =IF(OR(D10="",N(G10)=0),0,(E10-F10)/G10) -> 0 | I10: =H10/12 -> 0 | J10: =IF(OR(D10="",N(G10)=0),0,EDATE(D10,G10*12)) -> 00:00:00 | N10: =N(M10)/12 -> 0
A11: 6 | H11: =IF(OR(D11="",N(G11)=0),0,(E11-F11)/G11) -> 0 | I11: =H11/12 -> 0 | J11: =IF(OR(D11="",N(G11)=0),0,EDATE(D11,G11*12)) -> 00:00:00 | N11: =N(M11)/12 -> 0
A12: 7 | H12: =IF(OR(D12="",N(G12)=0),0,(E12-F12)/G12) -> 0 | I12: =H12/12 -> 0 | J12: =IF(OR(D12="",N(G12)=0),0,EDATE(D12,G12*12)) -> 00:00:00 | N12: =N(M12)/12 -> 0
A13: 8 | H13: =IF(OR(D13="",N(G13)=0),0,(E13-F13)/G13) -> 0 | I13: =H13/12 -> 0 | J13: =IF(OR(D13="",N(G13)=0),0,EDATE(D13,G13*12)) -> 00:00:00 | N13: =N(M13)/12 -> 0
A14: 9 | H14: =IF(OR(D14="",N(G14)=0),0,(E14-F14)/G14) -> 0 | I14: =H14/12 -> 0 | J14: =IF(OR(D14="",N(G14)=0),0,EDATE(D14,G14*12)) -> 00:00:00 | N14: =N(M14)/12 -> 0
A15: 10 | H15: =IF(OR(D15="",N(G15)=0),0,(E15-F15)/G15) -> 0 | I15: =H15/12 -> 0 | J15: =IF(OR(D15="",N(G15)=0),0,EDATE(D15,G15*12)) -> 00:00:00 | N15: =N(M15)/12 -> 0
B16: TOTAL | E16: =SUM(E6:E15) -> 46500 | F16: =SUM(F6:F15) -> 5000 | H16: =SUM(H6:H15) -> 5300 | I16: =SUM(I6:I15) -> 441.66667 | L16: =SUM(L6:L15) -> 150 | N16: =SUM(N6:N15) -> 85

Sheet COSTOS_FIJOS
A1: Costos fijos mensuales por centro de costo
A2: La columna «Valor base» se copia a cada mes. Si el gasto real de un mes fue distinto, escriba el valor real en la celda de ese mes. Las filas en negro se calculan solas.
A5: Código | B5: Concepto | C5: Centro de costo | D5: Elemento de gasto | E5: ¿Salario de trabajador propio? | F5: Valor base mensual (USD) | G5: =EDATE(Fecha_Inicio,0) -> 46266 | H5: =EDATE(Fecha_Inicio,1) -> 46296 | I5: =EDATE(Fecha_Inicio,2) -> 46327 | J5: =EDATE(Fecha_Inicio,3) -> 46357 | K5: =EDATE(Fecha_Inicio,4) -> 46388 | L5: =EDATE(Fecha_Inicio,5) -> 46419 | M5: =EDATE(Fecha_Inicio,6) -> 46447 | N5: =EDATE(Fecha_Inicio,7) -> 46478 | O5: =EDATE(Fecha_Inicio,8) -> 46508 | P5: =EDATE(Fecha_Inicio,9) -> 46539 | Q5: =EDATE(Fecha_Inicio,10) -> 46569 | R5: =EDATE(Fecha_Inicio,11) -> 46600 | S5: =EDATE(Fecha_Inicio,12) -> 46631 | T5: =EDATE(Fecha_Inicio,13) -> 46661 | U5: =EDATE(Fecha_Inicio,14) -> 46692 | V5: =EDATE(Fecha_Inicio,15) -> 46722 | W5: =EDATE(Fecha_Inicio,16) -> 46753 | X5: =EDATE(Fecha_Inicio,17) -> 46784 | Y5: =EDATE(Fecha_Inicio,18) -> 46813 | Z5: =EDATE(Fecha_Inicio,19) -> 46844 | AA5: =EDATE(Fecha_Inicio,20) -> 46874 | AB5: =EDATE(Fecha_Inicio,21) -> 46905 | AC5: =EDATE(Fecha_Inicio,22) -> 46935 | AD5: =EDATE(Fecha_Inicio,23) -> 46966 | AE5: Total período
A6: CF01 | B6: Salario del chofer del vehículo propio (puerto) | C6: GENERAL | D6: Gastos de fuerza de trabajo | E6: Sí | F6: 60 | G6: =$F6 -> 60 | H6: =$F6 -> 60 | I6: =$F6 -> 60 | J6: =$F6 -> 60 | K6: =$F6 -> 60 | L6: =$F6 -> 60 | M6: =$F6 -> 60 | N6: =$F6 -> 60 | ... AD6: =$F6 -> 60 | AE6: =SUM(G6:AD6) -> 1440
A7: CF02 | B7: Salarios de dirección, economía y contabilidad | C7: GENERAL | D7: Gastos de fuerza de trabajo | E7: Sí | F7: 250 | G7: =$F7 -> 250 | H7: =$F7 -> 250 | I7: =$F7 -> 250 | J7: =$F7 -> 250 | K7: =$F7 -> 250 | L7: =$F7 -> 250 | M7: =$F7 -> 250 | N7: =$F7 -> 250 | ... AD7: =$F7 -> 250 | AE7: =SUM(G7:AD7) -> 6000
A8: CF03 | B8: Comercialización – parte fija (21 gestores, desde COMERCIAL) | C8: GENERAL | D8: Gastos de fuerza de trabajo | E8: Sí | F8: =COMERCIAL!F33 -> 1050 | G8: =$F8 -> 1050 | H8: =$F8 -> 1050 | I8: =$F8 -> 1050 | J8: =$F8 -> 1050 | K8: =$F8 -> 1050 | L8: =$F8 -> 1050 | M8: =$F8 -> 1050 | N8: =$F8 -> 1050 | ... AD8: =$F8 -> 1050 | AE8: =SUM(G8:AD8) -> 25200
A9: CF04 | B9: Alquiler de local / almacén | C9: GENERAL | D9: Otros gastos monetarios | E9: No | F9: 200 | G9: =$F9 -> 200 | H9: =$F9 -> 200 | I9: =$F9 -> 200 | J9: =$F9 -> 200 | K9: =$F9 -> 200 | L9: =$F9 -> 200 | M9: =$F9 -> 200 | N9: =$F9 -> 200 | ... AD9: =$F9 -> 200 | AE9: =SUM(G9:AD9) -> 4800
A10: CF05 | B10: Electricidad y agua | C10: GENERAL | D10: Energía | E10: No | F10: 40 | G10: =$F10 -> 40 | H10: =$F10 -> 40 | I10: =$F10 -> 40 | J10: =$F10 -> 40 | K10: =$F10 -> 40 | L10: =$F10 -> 40 | M10: =$F10 -> 40 | N10: =$F10 -> 40 | ... AD10: =$F10 -> 40 | AE10: =SUM(G10:AD10) -> 960
A11: CF06 | B11: Comunicaciones (teléfono, internet) | C11: GENERAL | D11: Otros gastos monetarios | E11: No | F11: 30 | G11: =$F11 -> 30 | H11: =$F11 -> 30 | I11: =$F11 -> 30 | J11: =$F11 -> 30 | K11: =$F11 -> 30 | L11: =$F11 -> 30 | M11: =$F11 -> 30 | N11: =$F11 -> 30 | ... AD11: =$F11 -> 30 | AE11: =SUM(G11:AD11) -> 720
A12: CF07 | B12: Materiales de oficina y limpieza | C12: GENERAL | D12: Materias primas y materiales | E12: No | F12: 15 | G12: =$F12 -> 15 | H12: =$F12 -> 15 | I12: =$F12 -> 15 | J12: =$F12 -> 15 | K12: =$F12 -> 15 | L12: =$F12 -> 15 | M12: =$F12 -> 15 | N12: =$F12 -> 15 | ... AD12: =$F12 -> 15 | AE12: =SUM(G12:AD12) -> 360
A13: CF08 | B13: Servicios contables, legales y otros externos | C13: GENERAL | D13: Otros gastos monetarios | E13: No | F13: 50 | G13: =$F13 -> 50 | H13: =$F13 -> 50 | I13: =$F13 -> 50 | J13: =$F13 -> 50 | K13: =$F13 -> 50 | L13: =$F13 -> 50 | M13: =$F13 -> 50 | N13: =$F13 -> 50 | ... AD13: =$F13 -> 50 | AE13: =SUM(G13:AD13) -> 1200
A14: CF09 | B14: Gastos bancarios fijos (mantenimiento de cuenta) | C14: GENERAL | D14: Otros gastos monetarios | E14: No | F14: 10 | G14: =$F14 -> 10 | H14: =$F14 -> 10 | I14: =$F14 -> 10 | J14: =$F14 -> 10 | K14: =$F14 -> 10 | L14: =$F14 -> 10 | M14: =$F14 -> 10 | N14: =$F14 -> 10 | ... AD14: =$F14 -> 10 | AE14: =SUM(G14:AD14) -> 240
A15: CF10 | B15: Depreciación de activos fijos (desde ACTIVOS) | C15: GENERAL | D15: Depreciación y amortización | E15: No | F15: =ACTIVOS!I16 -> 441.66667 | G15: =SUMPRODUCT((ACTIVOS!$D$6:$D$15>0)*(ACTIVOS!$D$6:$D$15<=EOMONTH(G$5,0))*(((ACTIVOS!$K$6:$K$15=0)+(ACTIVOS!$K$6:$K$15>G$5))>0)*(ACTIVOS!$J$6:$J$15>G$5)*ACTIVOS!$I$6:$I$15) -> 441.66667 | H15: =SUMPRODUCT((ACTIVOS!$D$6:$D$15>0)*(ACTIVOS!$D$6:$D$15<=EOMONTH(H$5,0))*(((ACTIVOS!$K$6:$K$15=0)+(ACTIVOS!$K$6:$K$15>H$5))>0)*(ACTIVOS!$J$6:$J$15>H$5)*ACTIVOS!$I$6:$I$15) -> 441.66667 | I15: =SUMPRODUCT((ACTIVOS!$D$6:$D$15>0)*(ACTIVOS!$D$6:$D$15<=EOMONTH(I$5,0))*(((ACTIVOS!$K$6:$K$15=0)+(ACTIVOS!$K$6:$K$15>I$5))>0)*(ACTIVOS!$J$6:$J$15>I$5)*ACTIVOS!$I$6:$I$15) -> 441.66667 | J15: =SUMPRODUCT((ACTIVOS!$D$6:$D$15>0)*(ACTIVOS!$D$6:$D$15<=EOMONTH(J$5,0))*(((ACTIVOS!$K$6:$K$15=0)+(ACTIVOS!$K$6:$K$15>J$5))>0)*(ACTIVOS!$J$6:$J$15>J$5)*ACTIVOS!$I$6:$I$15) -> 441.66667 | K15: =SUMPRODUCT((ACTIVOS!$D$6:$D$15>0)*(ACTIVOS!$D$6:$D$15<=EOMONTH(K$5,0))*(((ACTIVOS!$K$6:$K$15=0)+(ACTIVOS!$K$6:$K$15>K$5))>0)*(ACTIVOS!$J$6:$J$15>K$5)*ACTIVOS!$I$6:$I$15) -> 441.66667 | L15: =SUMPRODUCT((ACTIVOS!$D$6:$D$15>0)*(ACTIVOS!$D$6:$D$15<=EOMONTH(L$5,0))*(((ACTIVOS!$K$6:$K$15=0)+(ACTIVOS!$K$6:$K$15>L$5))>0)*(ACTIVOS!$J$6:$J$15>L$5)*ACTIVOS!$I$6:$I$15) -> 441.66667 | M15: =SUMPRODUCT((ACTIVOS!$D$6:$D$15>0)*(ACTIVOS!$D$6:$D$15<=EOMONTH(M$5,0))*(((ACTIVOS!$K$6:$K$15=0)+(ACTIVOS!$K$6:$K$15>M$5))>0)*(ACTIVOS!$J$6:$J$15>M$5)*ACTIVOS!$I$6:$I$15) -> 441.66667 | N15: =SUMPRODUCT((ACTIVOS!$D$6:$D$15>0)*(ACTIVOS!$D$6:$D$15<=EOMONTH(N$5,0))*(((ACTIVOS!$K$6:$K$15=0)+(ACTIVOS!$K$6:$K$15>N$5))>0)*(ACTIVOS!$J$6:$J$15>N$5)*ACTIVOS!$I$6:$I$15) -> 441.66667 | ... AD15: =SUMPRODUCT((ACTIVOS!$D$6:$D$15>0)*(ACTIVOS!$D$6:$D$15<=EOMONTH(AD$5,0))*(((ACTIVOS!$K$6:$K$15=0)+(ACTIVOS!$K$6:$K$15>AD$5))>0)*(ACTIVOS!$J$6:$J$15>AD$5)*ACTIVOS!$I$6:$I$15) -> 441.66667 | AE15: =SUM(G15:AD15) -> 10600
A16: CF11 | B16: Mantenimiento preventivo de la flota propia (desde ACTIVOS) | C16: GENERAL | D16: Materias primas y materiales | E16: No | F16: =ACTIVOS!L16 -> 150 | G16: =SUMPRODUCT((ACTIVOS!$D$6:$D$15>0)*(ACTIVOS!$D$6:$D$15<=EOMONTH(G$5,0))*(((ACTIVOS!$K$6:$K$15=0)+(ACTIVOS!$K$6:$K$15>G$5))>0)*ACTIVOS!$L$6:$L$15) -> 150 | H16: =SUMPRODUCT((ACTIVOS!$D$6:$D$15>0)*(ACTIVOS!$D$6:$D$15<=EOMONTH(H$5,0))*(((ACTIVOS!$K$6:$K$15=0)+(ACTIVOS!$K$6:$K$15>H$5))>0)*ACTIVOS!$L$6:$L$15) -> 150 | I16: =SUMPRODUCT((ACTIVOS!$D$6:$D$15>0)*(ACTIVOS!$D$6:$D$15<=EOMONTH(I$5,0))*(((ACTIVOS!$K$6:$K$15=0)+(ACTIVOS!$K$6:$K$15>I$5))>0)*ACTIVOS!$L$6:$L$15) -> 150 | J16: =SUMPRODUCT((ACTIVOS!$D$6:$D$15>0)*(ACTIVOS!$D$6:$D$15<=EOMONTH(J$5,0))*(((ACTIVOS!$K$6:$K$15=0)+(ACTIVOS!$K$6:$K$15>J$5))>0)*ACTIVOS!$L$6:$L$15) -> 150 | K16: =SUMPRODUCT((ACTIVOS!$D$6:$D$15>0)*(ACTIVOS!$D$6:$D$15<=EOMONTH(K$5,0))*(((ACTIVOS!$K$6:$K$15=0)+(ACTIVOS!$K$6:$K$15>K$5))>0)*ACTIVOS!$L$6:$L$15) -> 150 | L16: =SUMPRODUCT((ACTIVOS!$D$6:$D$15>0)*(ACTIVOS!$D$6:$D$15<=EOMONTH(L$5,0))*(((ACTIVOS!$K$6:$K$15=0)+(ACTIVOS!$K$6:$K$15>L$5))>0)*ACTIVOS!$L$6:$L$15) -> 150 | M16: =SUMPRODUCT((ACTIVOS!$D$6:$D$15>0)*(ACTIVOS!$D$6:$D$15<=EOMONTH(M$5,0))*(((ACTIVOS!$K$6:$K$15=0)+(ACTIVOS!$K$6:$K$15>M$5))>0)*ACTIVOS!$L$6:$L$15) -> 150 | N16: =SUMPRODUCT((ACTIVOS!$D$6:$D$15>0)*(ACTIVOS!$D$6:$D$15<=EOMONTH(N$5,0))*(((ACTIVOS!$K$6:$K$15=0)+(ACTIVOS!$K$6:$K$15>N$5))>0)*ACTIVOS!$L$6:$L$15) -> 150 | ... AD16: =SUMPRODUCT((ACTIVOS!$D$6:$D$15>0)*(ACTIVOS!$D$6:$D$15<=EOMONTH(AD$5,0))*(((ACTIVOS!$K$6:$K$15=0)+(ACTIVOS!$K$6:$K$15>AD$5))>0)*ACTIVOS!$L$6:$L$15) -> 150 | AE16: =SUM(G16:AD16) -> 3600
A17: CF12 | B17: Seguros, licencias e inspecciones de la flota (desde ACTIVOS) | C17: GENERAL | D17: Otros gastos monetarios | E17: No | F17: =ACTIVOS!N16 -> 85 | G17: =SUMPRODUCT((ACTIVOS!$D$6:$D$15>0)*(ACTIVOS!$D$6:$D$15<=EOMONTH(G$5,0))*(((ACTIVOS!$K$6:$K$15=0)+(ACTIVOS!$K$6:$K$15>G$5))>0)*ACTIVOS!$N$6:$N$15) -> 85 | H17: =SUMPRODUCT((ACTIVOS!$D$6:$D$15>0)*(ACTIVOS!$D$6:$D$15<=EOMONTH(H$5,0))*(((ACTIVOS!$K$6:$K$15=0)+(ACTIVOS!$K$6:$K$15>H$5))>0)*ACTIVOS!$N$6:$N$15) -> 85 | I17: =SUMPRODUCT((ACTIVOS!$D$6:$D$15>0)*(ACTIVOS!$D$6:$D$15<=EOMONTH(I$5,0))*(((ACTIVOS!$K$6:$K$15=0)+(ACTIVOS!$K$6:$K$15>I$5))>0)*ACTIVOS!$N$6:$N$15) -> 85 | J17: =SUMPRODUCT((ACTIVOS!$D$6:$D$15>0)*(ACTIVOS!$D$6:$D$15<=EOMONTH(J$5,0))*(((ACTIVOS!$K$6:$K$15=0)+(ACTIVOS!$K$6:$K$15>J$5))>0)*ACTIVOS!$N$6:$N$15) -> 85 | K17: =SUMPRODUCT((ACTIVOS!$D$6:$D$15>0)*(ACTIVOS!$D$6:$D$15<=EOMONTH(K$5,0))*(((ACTIVOS!$K$6:$K$15=0)+(ACTIVOS!$K$6:$K$15>K$5))>0)*ACTIVOS!$N$6:$N$15) -> 85 | L17: =SUMPRODUCT((ACTIVOS!$D$6:$D$15>0)*(ACTIVOS!$D$6:$D$15<=EOMONTH(L$5,0))*(((ACTIVOS!$K$6:$K$15=0)+(ACTIVOS!$K$6:$K$15>L$5))>0)*ACTIVOS!$N$6:$N$15) -> 85 | M17: =SUMPRODUCT((ACTIVOS!$D$6:$D$15>0)*(ACTIVOS!$D$6:$D$15<=EOMONTH(M$5,0))*(((ACTIVOS!$K$6:$K$15=0)+(ACTIVOS!$K$6:$K$15>M$5))>0)*ACTIVOS!$N$6:$N$15) -> 85 | N17: =SUMPRODUCT((ACTIVOS!$D$6:$D$15>0)*(ACTIVOS!$D$6:$D$15<=EOMONTH(N$5,0))*(((ACTIVOS!$K$6:$K$15=0)+(ACTIVOS!$K$6:$K$15>N$5))>0)*ACTIVOS!$N$6:$N$15) -> 85 | ... AD17: =SUMPRODUCT((ACTIVOS!$D$6:$D$15>0)*(ACTIVOS!$D$6:$D$15<=EOMONTH(AD$5,0))*(((ACTIVOS!$K$6:$K$15=0)+(ACTIVOS!$K$6:$K$15>AD$5))>0)*ACTIVOS!$N$6:$N$15) -> 85 | AE17: =SUM(G17:AD17) -> 2040
A18: CF13 | B18: Otros gastos fijos generales | C18: GENERAL | D18: Otros gastos monetarios | E18: No | F18: 0 | G18: =$F18 -> 0 | H18: =$F18 -> 0 | I18: =$F18 -> 0 | J18: =$F18 -> 0 | K18: =$F18 -> 0 | L18: =$F18 -> 0 | M18: =$F18 -> 0 | N18: =$F18 -> 0 | ... AD18: =$F18 -> 0 | AE18: =SUM(G18:AD18) -> 0
A19: CF14 | B19: Occidente – chofer (servicio contratado) | C19: OCC | D19: Otros gastos monetarios | E19: No | F19: 120 | G19: =$F19 -> 120 | H19: =$F19 -> 120 | I19: =$F19 -> 120 | J19: =$F19 -> 120 | K19: =$F19 -> 120 | L19: =$F19 -> 120 | M19: =$F19 -> 120 | N19: =$F19 -> 120 | ... AD19: =$F19 -> 120 | AE19: =SUM(G19:AD19) -> 2880
A20: CF15 | B20: Occidente – ayudante (servicio contratado) | C20: OCC | D20: Otros gastos monetarios | E20: No | F20: 80 | G20: =$F20 -> 80 | H20: =$F20 -> 80 | I20: =$F20 -> 80 | J20: =$F20 -> 80 | K20: =$F20 -> 80 | L20: =$F20 -> 80 | M20: =$F20 -> 80 | N20: =$F20 -> 80 | ... AD20: =$F20 -> 80 | AE20: =SUM(G20:AD20) -> 1920
A21: CF16 | B21: Occidente – otros gastos fijos | C21: OCC | D21: Otros gastos monetarios | E21: No | F21: 0 | G21: =$F21 -> 0 | H21: =$F21 -> 0 | I21: =$F21 -> 0 | J21: =$F21 -> 0 | K21: =$F21 -> 0 | L21: =$F21 -> 0 | M21: =$F21 -> 0 | N21: =$F21 -> 0 | ... AD21: =$F21 -> 0 | AE21: =SUM(G21:AD21) -> 0
A22: CF17 | B22: Centro – chofer (servicio contratado) | C22: CEN | D22: Otros gastos monetarios | E22: No | F22: 120 | G22: =$F22 -> 120 | H22: =$F22 -> 120 | I22: =$F22 -> 120 | J22: =$F22 -> 120 | K22: =$F22 -> 120 | L22: =$F22 -> 120 | M22: =$F22 -> 120 | N22: =$F22 -> 120 | ... AD22: =$F22 -> 120 | AE22: =SUM(G22:AD22) -> 2880
A23: CF18 | B23: Centro – ayudante (servicio contratado) | C23: CEN | D23: Otros gastos monetarios | E23: No | F23: 80 | G23: =$F23 -> 80 | H23: =$F23 -> 80 | I23: =$F23 -> 80 | J23: =$F23 -> 80 | K23: =$F23 -> 80 | L23: =$F23 -> 80 | M23: =$F23 -> 80 | N23: =$F23 -> 80 | ... AD23: =$F23 -> 80 | AE23: =SUM(G23:AD23) -> 1920
A24: CF19 | B24: Centro – otros gastos fijos (centro transitorio) | C24: CEN | D24: Otros gastos monetarios | E24: No | F24: 0 | G24: =$F24 -> 0 | H24: =$F24 -> 0 | I24: =$F24 -> 0 | J24: =$F24 -> 0 | K24: =$F24 -> 0 | L24: =$F24 -> 0 | M24: =$F24 -> 0 | N24: =$F24 -> 0 | ... AD24: =$F24 -> 0 | AE24: =SUM(G24:AD24) -> 0
A25: CF20 | B25: Oriente – chofer (servicio contratado) | C25: ORI | D25: Otros gastos monetarios | E25: No | F25: 120 | G25: =$F25 -> 120 | H25: =$F25 -> 120 | I25: =$F25 -> 120 | J25: =$F25 -> 120 | K25: =$F25 -> 120 | L25: =$F25 -> 120 | M25: =$F25 -> 120 | N25: =$F25 -> 120 | ... AD25: =$F25 -> 120 | AE25: =SUM(G25:AD25) -> 2880
A26: CF21 | B26: Oriente – ayudante (servicio contratado) | C26: ORI | D26: Otros gastos monetarios | E26: No | F26: 80 | G26: =$F26 -> 80 | H26: =$F26 -> 80 | I26: =$F26 -> 80 | J26: =$F26 -> 80 | K26: =$F26 -> 80 | L26: =$F26 -> 80 | M26: =$F26 -> 80 | N26: =$F26 -> 80 | ... AD26: =$F26 -> 80 | AE26: =SUM(G26:AD26) -> 1920
A27: CF22 | B27: Oriente – otros gastos fijos (centro transitorio) | C27: ORI | D27: Otros gastos monetarios | E27: No | F27: 0 | G27: =$F27 -> 0 | H27: =$F27 -> 0 | I27: =$F27 -> 0 | J27: =$F27 -> 0 | K27: =$F27 -> 0 | L27: =$F27 -> 0 | M27: =$F27 -> 0 | N27: =$F27 -> 0 | ... AD27: =$F27 -> 0 | AE27: =SUM(G27:AD27) -> 0
B28: Tributos sobre salarios de trabajadores propios (calculados)
A29: SS-GENERAL | B29: Contribución a la seguridad social – GENERAL | C29: GENERAL | D29: Gastos de fuerza de trabajo | E29: — | F29: =Contrib_SS*SUMIFS($F$6:$F$27,$C$6:$C$27,$C29,$E$6:$E$27,"Sí") -> 190.4 | G29: =Contrib_SS*SUMIFS(G$6:G$27,$C$6:$C$27,$C29,$E$6:$E$27,"Sí") -> 190.4 | H29: =Contrib_SS*SUMIFS(H$6:H$27,$C$6:$C$27,$C29,$E$6:$E$27,"Sí") -> 190.4 | I29: =Contrib_SS*SUMIFS(I$6:I$27,$C$6:$C$27,$C29,$E$6:$E$27,"Sí") -> 190.4 | J29: =Contrib_SS*SUMIFS(J$6:J$27,$C$6:$C$27,$C29,$E$6:$E$27,"Sí") -> 190.4 | K29: =Contrib_SS*SUMIFS(K$6:K$27,$C$6:$C$27,$C29,$E$6:$E$27,"Sí") -> 190.4 | L29: =Contrib_SS*SUMIFS(L$6:L$27,$C$6:$C$27,$C29,$E$6:$E$27,"Sí") -> 190.4 | M29: =Contrib_SS*SUMIFS(M$6:M$27,$C$6:$C$27,$C29,$E$6:$E$27,"Sí") -> 190.4 | N29: =Contrib_SS*SUMIFS(N$6:N$27,$C$6:$C$27,$C29,$E$6:$E$27,"Sí") -> 190.4 | ... AD29: =Contrib_SS*SUMIFS(AD$6:AD$27,$C$6:$C$27,$C29,$E$6:$E$27,"Sí") -> 190.4 | AE29: =SUM(G29:AD29) -> 4569.6
A30: FT-GENERAL | B30: Impuesto por utilización de la fuerza de trabajo – GENERAL | C30: GENERAL | D30: Gastos de fuerza de trabajo | E30: — | F30: =Imp_Fuerza_Trabajo*SUMIFS($F$6:$F$27,$C$6:$C$27,$C30,$E$6:$E$27,"Sí") -> 68 | G30: =Imp_Fuerza_Trabajo*SUMIFS(G$6:G$27,$C$6:$C$27,$C30,$E$6:$E$27,"Sí") -> 68 | H30: =Imp_Fuerza_Trabajo*SUMIFS(H$6:H$27,$C$6:$C$27,$C30,$E$6:$E$27,"Sí") -> 68 | I30: =Imp_Fuerza_Trabajo*SUMIFS(I$6:I$27,$C$6:$C$27,$C30,$E$6:$E$27,"Sí") -> 68 | J30: =Imp_Fuerza_Trabajo*SUMIFS(J$6:J$27,$C$6:$C$27,$C30,$E$6:$E$27,"Sí") -> 68 | K30: =Imp_Fuerza_Trabajo*SUMIFS(K$6:K$27,$C$6:$C$27,$C30,$E$6:$E$27,"Sí") -> 68 | L30: =Imp_Fuerza_Trabajo*SUMIFS(L$6:L$27,$C$6:$C$27,$C30,$E$6:$E$27,"Sí") -> 68 | M30: =Imp_Fuerza_Trabajo*SUMIFS(M$6:M$27,$C$6:$C$27,$C30,$E$6:$E$27,"Sí") -> 68 | N30: =Imp_Fuerza_Trabajo*SUMIFS(N$6:N$27,$C$6:$C$27,$C30,$E$6:$E$27,"Sí") -> 68 | ... AD30: =Imp_Fuerza_Trabajo*SUMIFS(AD$6:AD$27,$C$6:$C$27,$C30,$E$6:$E$27,"Sí") -> 68 | AE30: =SUM(G30:AD30) -> 1632
A31: SS-OCC | B31: Contribución a la seguridad social – OCC | C31: OCC | D31: Gastos de fuerza de trabajo | E31: — | F31: =Contrib_SS*SUMIFS($F$6:$F$27,$C$6:$C$27,$C31,$E$6:$E$27,"Sí") -> 0 | G31: =Contrib_SS*SUMIFS(G$6:G$27,$C$6:$C$27,$C31,$E$6:$E$27,"Sí") -> 0 | H31: =Contrib_SS*SUMIFS(H$6:H$27,$C$6:$C$27,$C31,$E$6:$E$27,"Sí") -> 0 | I31: =Contrib_SS*SUMIFS(I$6:I$27,$C$6:$C$27,$C31,$E$6:$E$27,"Sí") -> 0 | J31: =Contrib_SS*SUMIFS(J$6:J$27,$C$6:$C$27,$C31,$E$6:$E$27,"Sí") -> 0 | K31: =Contrib_SS*SUMIFS(K$6:K$27,$C$6:$C$27,$C31,$E$6:$E$27,"Sí") -> 0 | L31: =Contrib_SS*SUMIFS(L$6:L$27,$C$6:$C$27,$C31,$E$6:$E$27,"Sí") -> 0 | M31: =Contrib_SS*SUMIFS(M$6:M$27,$C$6:$C$27,$C31,$E$6:$E$27,"Sí") -> 0 | N31: =Contrib_SS*SUMIFS(N$6:N$27,$C$6:$C$27,$C31,$E$6:$E$27,"Sí") -> 0 | ... AD31: =Contrib_SS*SUMIFS(AD$6:AD$27,$C$6:$C$27,$C31,$E$6:$E$27,"Sí") -> 0 | AE31: =SUM(G31:AD31) -> 0
A32: FT-OCC | B32: Impuesto por utilización de la fuerza de trabajo – OCC | C32: OCC | D32: Gastos de fuerza de trabajo | E32: — | F32: =Imp_Fuerza_Trabajo*SUMIFS($F$6:$F$27,$C$6:$C$27,$C32,$E$6:$E$27,"Sí") -> 0 | G32: =Imp_Fuerza_Trabajo*SUMIFS(G$6:G$27,$C$6:$C$27,$C32,$E$6:$E$27,"Sí") -> 0 | H32: =Imp_Fuerza_Trabajo*SUMIFS(H$6:H$27,$C$6:$C$27,$C32,$E$6:$E$27,"Sí") -> 0 | I32: =Imp_Fuerza_Trabajo*SUMIFS(I$6:I$27,$C$6:$C$27,$C32,$E$6:$E$27,"Sí") -> 0 | J32: =Imp_Fuerza_Trabajo*SUMIFS(J$6:J$27,$C$6:$C$27,$C32,$E$6:$E$27,"Sí") -> 0 | K32: =Imp_Fuerza_Trabajo*SUMIFS(K$6:K$27,$C$6:$C$27,$C32,$E$6:$E$27,"Sí") -> 0 | L32: =Imp_Fuerza_Trabajo*SUMIFS(L$6:L$27,$C$6:$C$27,$C32,$E$6:$E$27,"Sí") -> 0 | M32: =Imp_Fuerza_Trabajo*SUMIFS(M$6:M$27,$C$6:$C$27,$C32,$E$6:$E$27,"Sí") -> 0 | N32: =Imp_Fuerza_Trabajo*SUMIFS(N$6:N$27,$C$6:$C$27,$C32,$E$6:$E$27,"Sí") -> 0 | ... AD32: =Imp_Fuerza_Trabajo*SUMIFS(AD$6:AD$27,$C$6:$C$27,$C32,$E$6:$E$27,"Sí") -> 0 | AE32: =SUM(G32:AD32) -> 0
A33: SS-CEN | B33: Contribución a la seguridad social – CEN | C33: CEN | D33: Gastos de fuerza de trabajo | E33: — | F33: =Contrib_SS*SUMIFS($F$6:$F$27,$C$6:$C$27,$C33,$E$6:$E$27,"Sí") -> 0 | G33: =Contrib_SS*SUMIFS(G$6:G$27,$C$6:$C$27,$C33,$E$6:$E$27,"Sí") -> 0 | H33: =Contrib_SS*SUMIFS(H$6:H$27,$C$6:$C$27,$C33,$E$6:$E$27,"Sí") -> 0 | I33: =Contrib_SS*SUMIFS(I$6:I$27,$C$6:$C$27,$C33,$E$6:$E$27,"Sí") -> 0 | J33: =Contrib_SS*SUMIFS(J$6:J$27,$C$6:$C$27,$C33,$E$6:$E$27,"Sí") -> 0 | K33: =Contrib_SS*SUMIFS(K$6:K$27,$C$6:$C$27,$C33,$E$6:$E$27,"Sí") -> 0 | L33: =Contrib_SS*SUMIFS(L$6:L$27,$C$6:$C$27,$C33,$E$6:$E$27,"Sí") -> 0 | M33: =Contrib_SS*SUMIFS(M$6:M$27,$C$6:$C$27,$C33,$E$6:$E$27,"Sí") -> 0 | N33: =Contrib_SS*SUMIFS(N$6:N$27,$C$6:$C$27,$C33,$E$6:$E$27,"Sí") -> 0 | ... AD33: =Contrib_SS*SUMIFS(AD$6:AD$27,$C$6:$C$27,$C33,$E$6:$E$27,"Sí") -> 0 | AE33: =SUM(G33:AD33) -> 0
A34: FT-CEN | B34: Impuesto por utilización de la fuerza de trabajo – CEN | C34: CEN | D34: Gastos de fuerza de trabajo | E34: — | F34: =Imp_Fuerza_Trabajo*SUMIFS($F$6:$F$27,$C$6:$C$27,$C34,$E$6:$E$27,"Sí") -> 0 | G34: =Imp_Fuerza_Trabajo*SUMIFS(G$6:G$27,$C$6:$C$27,$C34,$E$6:$E$27,"Sí") -> 0 | H34: =Imp_Fuerza_Trabajo*SUMIFS(H$6:H$27,$C$6:$C$27,$C34,$E$6:$E$27,"Sí") -> 0 | I34: =Imp_Fuerza_Trabajo*SUMIFS(I$6:I$27,$C$6:$C$27,$C34,$E$6:$E$27,"Sí") -> 0 | J34: =Imp_Fuerza_Trabajo*SUMIFS(J$6:J$27,$C$6:$C$27,$C34,$E$6:$E$27,"Sí") -> 0 | K34: =Imp_Fuerza_Trabajo*SUMIFS(K$6:K$27,$C$6:$C$27,$C34,$E$6:$E$27,"Sí") -> 0 | L34: =Imp_Fuerza_Trabajo*SUMIFS(L$6:L$27,$C$6:$C$27,$C34,$E$6:$E$27,"Sí") -> 0 | M34: =Imp_Fuerza_Trabajo*SUMIFS(M$6:M$27,$C$6:$C$27,$C34,$E$6:$E$27,"Sí") -> 0 | N34: =Imp_Fuerza_Trabajo*SUMIFS(N$6:N$27,$C$6:$C$27,$C34,$E$6:$E$27,"Sí") -> 0 | ... AD34: =Imp_Fuerza_Trabajo*SUMIFS(AD$6:AD$27,$C$6:$C$27,$C34,$E$6:$E$27,"Sí") -> 0 | AE34: =SUM(G34:AD34) -> 0
A35: SS-ORI | B35: Contribución a la seguridad social – ORI | C35: ORI | D35: Gastos de fuerza de trabajo | E35: — | F35: =Contrib_SS*SUMIFS($F$6:$F$27,$C$6:$C$27,$C35,$E$6:$E$27,"Sí") -> 0 | G35: =Contrib_SS*SUMIFS(G$6:G$27,$C$6:$C$27,$C35,$E$6:$E$27,"Sí") -> 0 | H35: =Contrib_SS*SUMIFS(H$6:H$27,$C$6:$C$27,$C35,$E$6:$E$27,"Sí") -> 0 | I35: =Contrib_SS*SUMIFS(I$6:I$27,$C$6:$C$27,$C35,$E$6:$E$27,"Sí") -> 0 | J35: =Contrib_SS*SUMIFS(J$6:J$27,$C$6:$C$27,$C35,$E$6:$E$27,"Sí") -> 0 | K35: =Contrib_SS*SUMIFS(K$6:K$27,$C$6:$C$27,$C35,$E$6:$E$27,"Sí") -> 0 | L35: =Contrib_SS*SUMIFS(L$6:L$27,$C$6:$C$27,$C35,$E$6:$E$27,"Sí") -> 0 | M35: =Contrib_SS*SUMIFS(M$6:M$27,$C$6:$C$27,$C35,$E$6:$E$27,"Sí") -> 0 | N35: =Contrib_SS*SUMIFS(N$6:N$27,$C$6:$C$27,$C35,$E$6:$E$27,"Sí") -> 0 | ... AD35: =Contrib_SS*SUMIFS(AD$6:AD$27,$C$6:$C$27,$C35,$E$6:$E$27,"Sí") -> 0 | AE35: =SUM(G35:AD35) -> 0
A36: FT-ORI | B36: Impuesto por utilización de la fuerza de trabajo – ORI | C36: ORI | D36: Gastos de fuerza de trabajo | E36: — | F36: =Imp_Fuerza_Trabajo*SUMIFS($F$6:$F$27,$C$6:$C$27,$C36,$E$6:$E$27,"Sí") -> 0 | G36: =Imp_Fuerza_Trabajo*SUMIFS(G$6:G$27,$C$6:$C$27,$C36,$E$6:$E$27,"Sí") -> 0 | H36: =Imp_Fuerza_Trabajo*SUMIFS(H$6:H$27,$C$6:$C$27,$C36,$E$6:$E$27,"Sí") -> 0 | I36: =Imp_Fuerza_Trabajo*SUMIFS(I$6:I$27,$C$6:$C$27,$C36,$E$6:$E$27,"Sí") -> 0 | J36: =Imp_Fuerza_Trabajo*SUMIFS(J$6:J$27,$C$6:$C$27,$C36,$E$6:$E$27,"Sí") -> 0 | K36: =Imp_Fuerza_Trabajo*SUMIFS(K$6:K$27,$C$6:$C$27,$C36,$E$6:$E$27,"Sí") -> 0 | L36: =Imp_Fuerza_Trabajo*SUMIFS(L$6:L$27,$C$6:$C$27,$C36,$E$6:$E$27,"Sí") -> 0 | M36: =Imp_Fuerza_Trabajo*SUMIFS(M$6:M$27,$C$6:$C$27,$C36,$E$6:$E$27,"Sí") -> 0 | N36: =Imp_Fuerza_Trabajo*SUMIFS(N$6:N$27,$C$6:$C$27,$C36,$E$6:$E$27,"Sí") -> 0 | ... AD36: =Imp_Fuerza_Trabajo*SUMIFS(AD$6:AD$27,$C$6:$C$27,$C36,$E$6:$E$27,"Sí") -> 0 | AE36: =SUM(G36:AD36) -> 0
B38: TOTAL FIJOS GENERALES (se reparten entre todos los kg) | C38: GENERAL | F38: =SUMIF($C$6:$C$36,"GENERAL",$F$6:$F$36) -> 2640.0667 | G38: =SUMIF($C$6:$C$36,"GENERAL",G$6:G$36) -> 2640.0667 | H38: =SUMIF($C$6:$C$36,"GENERAL",H$6:H$36) -> 2640.0667 | I38: =SUMIF($C$6:$C$36,"GENERAL",I$6:I$36) -> 2640.0667 | J38: =SUMIF($C$6:$C$36,"GENERAL",J$6:J$36) -> 2640.0667 | K38: =SUMIF($C$6:$C$36,"GENERAL",K$6:K$36) -> 2640.0667 | L38: =SUMIF($C$6:$C$36,"GENERAL",L$6:L$36) -> 2640.0667 | M38: =SUMIF($C$6:$C$36,"GENERAL",M$6:M$36) -> 2640.0667 | N38: =SUMIF($C$6:$C$36,"GENERAL",N$6:N$36) -> 2640.0667 | ... AE38: =SUMIF($C$6:$C$36,"GENERAL",AE$6:AE$36) -> 63361.6
B39: TOTAL FIJOS OCCIDENTE | C39: OCC | F39: =SUMIF($C$6:$C$36,"OCC",$F$6:$F$36) -> 200 | G39: =SUMIF($C$6:$C$36,"OCC",G$6:G$36) -> 200 | H39: =SUMIF($C$6:$C$36,"OCC",H$6:H$36) -> 200 | I39: =SUMIF($C$6:$C$36,"OCC",I$6:I$36) -> 200 | J39: =SUMIF($C$6:$C$36,"OCC",J$6:J$36) -> 200 | K39: =SUMIF($C$6:$C$36,"OCC",K$6:K$36) -> 200 | L39: =SUMIF($C$6:$C$36,"OCC",L$6:L$36) -> 200 | M39: =SUMIF($C$6:$C$36,"OCC",M$6:M$36) -> 200 | N39: =SUMIF($C$6:$C$36,"OCC",N$6:N$36) -> 200 | ... AE39: =SUMIF($C$6:$C$36,"OCC",AE$6:AE$36) -> 4800
B40: TOTAL FIJOS CENTRO | C40: CEN | F40: =SUMIF($C$6:$C$36,"CEN",$F$6:$F$36) -> 200 | G40: =SUMIF($C$6:$C$36,"CEN",G$6:G$36) -> 200 | H40: =SUMIF($C$6:$C$36,"CEN",H$6:H$36) -> 200 | I40: =SUMIF($C$6:$C$36,"CEN",I$6:I$36) -> 200 | J40: =SUMIF($C$6:$C$36,"CEN",J$6:J$36) -> 200 | K40: =SUMIF($C$6:$C$36,"CEN",K$6:K$36) -> 200 | L40: =SUMIF($C$6:$C$36,"CEN",L$6:L$36) -> 200 | M40: =SUMIF($C$6:$C$36,"CEN",M$6:M$36) -> 200 | N40: =SUMIF($C$6:$C$36,"CEN",N$6:N$36) -> 200 | ... AE40: =SUMIF($C$6:$C$36,"CEN",AE$6:AE$36) -> 4800
B41: TOTAL FIJOS ORIENTE | C41: ORI | F41: =SUMIF($C$6:$C$36,"ORI",$F$6:$F$36) -> 200 | G41: =SUMIF($C$6:$C$36,"ORI",G$6:G$36) -> 200 | H41: =SUMIF($C$6:$C$36,"ORI",H$6:H$36) -> 200 | I41: =SUMIF($C$6:$C$36,"ORI",I$6:I$36) -> 200 | J41: =SUMIF($C$6:$C$36,"ORI",J$6:J$36) -> 200 | K41: =SUMIF($C$6:$C$36,"ORI",K$6:K$36) -> 200 | L41: =SUMIF($C$6:$C$36,"ORI",L$6:L$36) -> 200 | M41: =SUMIF($C$6:$C$36,"ORI",M$6:M$36) -> 200 | N41: =SUMIF($C$6:$C$36,"ORI",N$6:N$36) -> 200 | ... AE41: =SUMIF($C$6:$C$36,"ORI",AE$6:AE$36) -> 4800
B42: TOTAL COSTOS FIJOS DEL MES | F42: =SUM(F38:F41) -> 3240.0667 | G42: =SUM(G38:G41) -> 3240.0667 | H42: =SUM(H38:H41) -> 3240.0667 | I42: =SUM(I38:I41) -> 3240.0667 | J42: =SUM(J38:J41) -> 3240.0667 | K42: =SUM(K38:K41) -> 3240.0667 | L42: =SUM(L38:L41) -> 3240.0667 | M42: =SUM(M38:M41) -> 3240.0667 | ... AE42: =SUM(AE38:AE41) -> 77761.6

Sheet COMERCIAL
A1: Comercialización: 21 gestores y liquidación mensual
A2: El pago fijo de todos los gestores pasa a COSTOS_FIJOS. La parte variable se liquida cada mes y se concilia con los kg o ingresos reales del mes.
A4: Mes a liquidar | C4: 46296
A5: Vigencia de precios del mes | C5: =IFERROR(MATCH(SUMPRODUCT(MAX((PRECIOS!$A$6:$A$55<=EOMONTH(C4,0))*PRECIOS!$A$6:$A$55)),PRECIOS!$A$6:$A$55,0),1) -> 1
A6: Base de la comisión | C6: =Base_Comision -> % DEL INGRESO
A7: Tasa variable aplicable | C7: =IF(C6="% DEL INGRESO",INDEX(PRECIOS!$L$6:$L$55,C5),INDEX(PRECIOS!$M$6:$M$55,C5)) -> 0.03 | D7: =IF(C6="% DEL INGRESO","de lo cobrado (USD)","USD por kg entregado") -> de lo cobrado (USD)
A8: Pago fijo mensual por defecto (USD) | C8: 50 | D8: ILUSTRATIVO. Todos los gestores cobran lo mismo; se puede ajustar por persona en la columna F.
A11: Nº | B11: Nombre del gestor | C11: Grupo | D11: Territorio | E11: Región | F11: Pago fijo mensual (USD) | G11: Base variable del mes (USD cobrados o kg) | H11: Pago variable (USD) | I11: TOTAL A PAGAR (USD)
A12: 1 | B12: Gestor 01 (editar) | C12: Grupo central | D12: Oficina central | E12: =IFERROR(INDEX(L_TerrRegion,MATCH(D12,L_Territorio,0)),"") -> General | F12: =$C$8 -> 50 | G12: 0 | H12: =N(G12)*$C$7 -> 0 | I12: =N(F12)+H12 -> 50
A13: 2 | B13: Gestor 02 (editar) | C13: Grupo central | D13: Oficina central | E13: =IFERROR(INDEX(L_TerrRegion,MATCH(D13,L_Territorio,0)),"") -> General | F13: =$C$8 -> 50 | G13: 0 | H13: =N(G13)*$C$7 -> 0 | I13: =N(F13)+H13 -> 50
A14: 3 | B14: Gestor 03 (editar) | C14: Grupo central | D14: Oficina central | E14: =IFERROR(INDEX(L_TerrRegion,MATCH(D14,L_Territorio,0)),"") -> General | F14: =$C$8 -> 50 | G14: 0 | H14: =N(G14)*$C$7 -> 0 | I14: =N(F14)+H14 -> 50
A15: 4 | B15: Gestor 04 (editar) | C15: Grupo central | D15: Oficina central | E15: =IFERROR(INDEX(L_TerrRegion,MATCH(D15,L_Territorio,0)),"") -> General | F15: =$C$8 -> 50 | G15: 0 | H15: =N(G15)*$C$7 -> 0 | I15: =N(F15)+H15 -> 50
A16: 5 | B16: Gestor 05 (editar) | C16: Grupo central | D16: Oficina central | E16: =IFERROR(INDEX(L_TerrRegion,MATCH(D16,L_Territorio,0)),"") -> General | F16: =$C$8 -> 50 | G16: 0 | H16: =N(G16)*$C$7 -> 0 | I16: =N(F16)+H16 -> 50
A17: 6 | B17: Gestor 06 (editar) | C17: Provincial | D17: Pinar del Río | E17: =IFERROR(INDEX(L_TerrRegion,MATCH(D17,L_Territorio,0)),"") -> Occidente | F17: =$C$8 -> 50 | G17: 833.68 | H17: =N(G17)*$C$7 -> 25.0104 | I17: =N(F17)+H17 -> 75.0104
A18: 7 | B18: Gestor 07 (editar) | C18: Provincial | D18: Artemisa | E18: =IFERROR(INDEX(L_TerrRegion,MATCH(D18,L_Territorio,0)),"") -> Occidente | F18: =$C$8 -> 50 | G18: 833.68 | H18: =N(G18)*$C$7 -> 25.0104 | I18: =N(F18)+H18 -> 75.0104
A19: 8 | B19: Gestor 08 (editar) | C19: Provincial | D19: La Habana | E19: =IFERROR(INDEX(L_TerrRegion,MATCH(D19,L_Territorio,0)),"") -> Occidente | F19: =$C$8 -> 50 | G19: 3334.74 | H19: =N(G19)*$C$7 -> 100.0422 | I19: =N(F19)+H19 -> 150.0422
A20: 9 | B20: Gestor 09 (editar) | C20: Provincial | D20: Mayabeque | E20: =IFERROR(INDEX(L_TerrRegion,MATCH(D20,L_Territorio,0)),"") -> Occidente | F20: =$C$8 -> 50 | G20: 833.68 | H20: =N(G20)*$C$7 -> 25.0104 | I20: =N(F20)+H20 -> 75.0104
A21: 10 | B21: Gestor 10 (editar) | C21: Provincial | D21: Matanzas | E21: =IFERROR(INDEX(L_TerrRegion,MATCH(D21,L_Territorio,0)),"") -> Occidente | F21: =$C$8 -> 50 | G21: 1667.37 | H21: =N(G21)*$C$7 -> 50.0211 | I21: =N(F21)+H21 -> 100.0211
A22: 11 | B22: Gestor 11 (editar) | C22: Provincial | D22: Isla de la Juventud | E22: =IFERROR(INDEX(L_TerrRegion,MATCH(D22,L_Territorio,0)),"") -> Occidente | F22: =$C$8 -> 50 | G22: 416.85 | H22: =N(G22)*$C$7 -> 12.5055 | I22: =N(F22)+H22 -> 62.5055
A23: 12 | B23: Gestor 12 (editar) | C23: Provincial | D23: Cienfuegos | E23: =IFERROR(INDEX(L_TerrRegion,MATCH(D23,L_Territorio,0)),"") -> Centro | F23: =$C$8 -> 50 | G23: 502.86 | H23: =N(G23)*$C$7 -> 15.0858 | I23: =N(F23)+H23 -> 65.0858
... A32: 21 | B32: Gestor 21 (editar) | C32: Provincial | D32: Guantánamo | E32: =IFERROR(INDEX(L_TerrRegion,MATCH(D32,L_Territorio,0)),"") -> Oriente | F32: =$C$8 -> 50 | G32: 630 | H32: =N(G32)*$C$7 -> 18.9 | I32: =N(F32)+H32 -> 68.9
B33: TOTAL | F33: =SUM(F12:F32) -> 1050 | G33: =SUM(G12:G32) -> 16480 | H33: =SUM(H12:H32) -> 494.4 | I33: =SUM(I12:I32) -> 1544.4
A35: CONCILIACIÓN DEL MES
A36: Base variable declarada por los gestores | G36: =G33 -> 16480
A37: Base real del mes según las operaciones (CALCULO) | G37: =IF(C6="% DEL INGRESO",SUMIFS(CALCULO!$M$6:$M$305,CALCULO!$D$6:$D$305,C4)+SUMIFS(CALCULO!$N$6:$N$305,CALCULO!$D$6:$D$305,C4)+SUMIFS(CALCULO!$O$6:$O$305,CALCULO!$D$6:$D$305,C4),SUMIFS(CALCULO!$J$6:$J$305,CALCULO!$D$6:$D$305,C4)) -> 16480
A38: Diferencia | G38: =G36-G37 -> 0
A39: Estado de la conciliación | G39: =IF(ABS(G38)<0.01,"CUADRA","REVISAR: la base declarada no coincide con las operaciones") -> CUADRA
A40: Pago variable calculado en el modelo de costos (CALCULO) | G40: =SUMIFS(CALCULO!$BH$6:$BH$305,CALCULO!$D$6:$D$305,C4) -> 494.4
A42: Nota: los ingresos de la conciliación se calculan a la tarifa por kg. Si se liquida sobre lo efectivamente COBRADO (recomendado), la diferencia muestra lo pendiente de cobro.

Sheet CALCULO
A1: Cálculo de la rentabilidad por contenedor (automático – no escribir)
A2: Cada fila corresponde a la misma fila de ENTRADA. Importes en USD. Los costos fijos se reparten entre los contenedores del mes.
A4: IDENTIFICACIÓN | G4: VOLUMEN | K4: PRECIOS | M4: INGRESOS | R4: ETAPA 1 · PUERTO | Z4: ETAPA 2 · TRANSITARIA | AF4: OCCIDENTE | AJ4: CENTRO | AT4: ORIENTE | BE4: COMERCIALIZACIÓN VARIABLE | BI4: OTROS VARIABLES | BL4: MARGEN DE CONTRIBUCIÓN | BP4: COSTOS FIJOS ASIGNADOS | CB4: TRIBUTOS | CD4: RESULTADO | CK4: RESULTADO POR REGIÓN | CP4: CONTROL
A5: Nº | B5: ID contenedor | C5: Fecha de arribo | D5: Mes | E5: Transitaria | F5: Estado | G5: kg Occidente | H5: kg Centro | I5: kg Oriente | J5: kg total | K5: Fila de precios vigente | L5: Precios vigentes desde | M5: Ingreso Occidente | N5: Ingreso Centro | O5: Ingreso Oriente | P5: Otros ingresos | Q5: INGRESO TOTAL | R5: Viajes al puerto | S5: Cita del puerto | T5: Litros al puerto (norma) | U5: Litros al puerto (aplicados) | V5: Combustible al puerto | W5: Dieta del chofer | X5: Desgaste del vehículo propio | Y5: TOTAL PUERTO | Z5: Jornales de desagrupe (norma) | AA5: Jornales de desagrupe (aplicados) | AB5: Mano de obra del desagrupe | AC5: Servicio de la transitaria | AD5: Estadía / almacenaje | AE5: TOTAL TRANSITARIA | AF5: Viajes de distribución en Occidente | AG5: Litros de distribución (norma) | AH5: Litros de distribución (aplicados) | AI5: TOTAL OCCIDENTE (combustible) | AJ5: Viajes a Centro | AK5: Litros de traslado (norma) | AL5: Litros de traslado (aplicados) | AM5: Litros de distribución (norma) | AN5: Litros de distribución (aplicados) | AO5: Combustible de Centro | AP5: Jornales del centro transitorio (norma) | AQ5: Jornales del centro transitorio (aplicados) | AR5: Desagrupe en el centro transitorio | AS5: TOTAL CENTRO | AT5: Viajes a Oriente | AU5: Litros de traslado (norma) | AV5: Litros de traslado (aplicados) | AW5: Litros de distribución (norma) | AX5: Litros de distribución (aplicados) | AY5: Combustible de Oriente | AZ5: Jornales del centro transitorio (norma) | BA5: Jornales del centro transitorio (aplicados) | BB5: Desagrupe en el centro transitorio | BC5: TOTAL ORIENTE | BD5: TOTAL DISTRIBUCIÓN | BE5: Comisión Occidente | BF5: Comisión Centro | BG5: Comisión Oriente | BH5: TOTAL COMISIÓN VARIABLE | BI5: Provisión para reclamaciones | BJ5: Comisiones bancarias | BK5: Otros gastos directos | BL5: TOTAL COSTOS VARIABLES | BM5: MARGEN DE CONTRIBUCIÓN | BN5: MC % | BO5: MC por kg | BP5: Columna del mes en COSTOS_FIJOS | BQ5: Contenedores del mes | BR5: kg del mes | BS5: % de los fijos generales | BT5: Fijos generales asignados | BU5: % de los fijos OCC | BV5: Fijos OCC asignados | BW5: % de los fijos CEN | BX5: Fijos CEN asignados | BY5: % de los fijos ORI | BZ5: Fijos ORI asignados | CA5: TOTAL FIJOS ASIGNADOS | CB5: Impuesto sobre ventas y servicios | CC5: Contribución territorial | CD5: UTILIDAD ANTES DE IMPUESTO SOBRE UTILIDADES | CE5: Impuesto sobre utilidades (estimado) | CF5: UTILIDAD NETA ESTIMADA | CG5: Margen neto % | CH5: Costo total por kg | CI5: Ingreso por kg | CJ5: Utilidad antes de impuesto por kg | CK5: Costos compartidos (puerto + transitaria + otros directos + fijos generales) | CL5: Utilidad Occidente | CM5: Utilidad Centro | CN5: Utilidad Oriente | CO5: Control: diferencia de cuadre (debe ser 0) | CP5: Litros totales según norma | CQ5: Litros totales aplicados | CR5: Desvío del combustible frente a la norma | CS5: Días de ciclo (arribo → fin) | CT5: ALERTAS
A6: =IF(B6="","",ROW()-5) -> 1 | B6: =IF(ENTRADA!$B6="","",ENTRADA!$B6) -> CONT-EJEMPLO-01 | C6: =IF(B6="","",ENTRADA!$C6) -> 46273 | D6: =IF(B6="","",DATE(YEAR(C6),MONTH(C6),1)) -> 46266 | E6: =IF(B6="","",ENTRADA!$D6&"") -> ENCI | F6: =IF(B6="","",ENTRADA!$Z6&"") -> Cerrado | G6: =IF(B6="","",N(ENTRADA!$G6)) -> 5200 | H6: =IF(B6="","",N(ENTRADA!$H6)) -> 2600 | I6: =IF(B6="","",N(ENTRADA!$I6)) -> 2300 | J6: =IF(B6="","",G6+H6+I6) -> 10100 | K6: =IF(B6="","",IFERROR(MATCH(SUMPRODUCT(MAX((PRECIOS!$A$6:$A$55<=C6)*PRECIOS!$A$6:$A$55)),PRECIOS!$A$6:$A$55,0),1)) -> 1 | L6: =IF(B6="","",INDEX(PRECIOS!$A$6:$A$55,K6)) -> 46023 | M6: =IF(B6="","",G6*INDEX(PRECIOS!$B$6:$B$55,K6)) -> 4160 | N6: =IF(B6="","",H6*INDEX(PRECIOS!$C$6:$C$55,K6)) -> 2080 | O6: =IF(B6="","",I6*INDEX(PRECIOS!$D$6:$D$55,K6)) -> 1840 | P6: =IF(B6="","",N(ENTRADA!$X6)) -> 0 | Q6: =IF(B6="","",M6+N6+O6+P6) -> 8080 | R6: =IF(B6="","",IF(ENTRADA!$J6="",Std_Viajes_Puerto,ENTRADA!$J6)) -> 1 | S6: =IF(B6="","",R6*INDEX(PRECIOS!$F$6:$F$55,K6)) -> 10 | T6: =IF(B6="","",R6*Litros_Puerto_Viaje) -> 60 | U6: =IF(B6="","",IF(ENTRADA!$K6="",T6,ENTRADA!$K6)) -> 62 | V6: =IF(B6="","",U6*INDEX(PRECIOS!$E$6:$E$55,K6)) -> 124 | W6: =IF(B6="","",IF(ENTRADA!$L6="",R6*INDEX(PRECIOS!$G$6:$G$55,K6),ENTRADA!$L6)) -> 10 | X6: =IF(B6="","",R6*Km_Puerto_Viaje*INDEX(PRECIOS!$N$6:$N$55,K6)) -> 21.6 | Y6: =IF(B6="","",S6+V6+W6+X6) -> 165.6 | Z6: =IF(B6="","",IF(J6=0,0,ROUNDUP(J6/Rend_Desagrupe,0))) -> 11 | AA6: =IF(B6="","",IF(ENTRADA!$M6="",Z6,ENTRADA!$M6)) -> 11 | AB6: =IF(B6="","",AA6*INDEX(PRECIOS!$H$6:$H$55,K6)) -> 165 | AC6: =IF(B6="","",IF(E6="ENCI",INDEX(PRECIOS!$J$6:$J$55,K6),IF(E6="A.V",INDEX(PRECIOS!$K$6:$K$55,K6),0))) -> 0 | AD6: =IF(B6="","",N(ENTRADA!$N6)) -> 0 | AE6: =IF(B6="","",AB6+AC6+AD6) -> 165 | AF6: =IF(B6="","",IF(G6=0,0,ROUNDUP(G6/Cap_Camion_OCC,0))) -> 2 | AG6: =IF(B6="","",AF6*L_Dist_OCC) -> 240 | AH6: =IF(B6="","",IF(ENTRADA!$O6="",AG6,ENTRADA!$O6)) -> 240 | AI6: =IF(B6="","",AH6*INDEX(PRECIOS!$E$6:$E$55,K6)) -> 480 | AJ6: =IF(B6="","",IF(H6=0,0,ROUNDUP(H6/Cap_Camion_CEN,0))) -> 1 | AK6: =IF(B6="","",AJ6*L_Tras_CEN) -> 250 | AL6: =IF(B6="","",IF(ENTRADA!$P6="",AK6,ENTRADA!$P6)) -> 250 | AM6: =IF(B6="","",AJ6*L_Dist_CEN) -> 150 | AN6: =IF(B6="","",IF(ENTRADA!$Q6="",AM6,ENTRADA!$Q6)) -> 150 | AO6: =IF(B6="","",(AL6+AN6)*INDEX(PRECIOS!$E$6:$E$55,K6)) -> 800 | AP6: =IF(B6="","",IF(H6=0,0,ROUNDUP(H6/Rend_Desagrupe_CT,0))) -> 4 | AQ6: =IF(B6="","",IF(ENTRADA!$R6="",AP6,ENTRADA!$R6)) -> 4 | AR6: =IF(B6="","",AQ6*INDEX(PRECIOS!$I$6:$I$55,K6)) -> 60 | AS6: =IF(B6="","",AO6+AR6) -> 860 | AT6: =IF(B6="","",IF(I6=0,0,ROUNDUP(I6/Cap_Camion_ORI,0))) -> 1 | AU6: =IF(B6="","",AT6*L_Tras_ORI) -> 450 | AV6: =IF(B6="","",IF(ENTRADA!$S6="",AU6,ENTRADA!$S6)) -> 450 | AW6: =IF(B6="","",AT6*L_Dist_ORI) -> 180 | AX6: =IF(B6="","",IF(ENTRADA!$T6="",AW6,ENTRADA!$T6)) -> 180 | AY6: =IF(B6="","",(AV6+AX6)*INDEX(PRECIOS!$E$6:$E$55,K6)) -> 1260 | AZ6: =IF(B6="","",IF(I6=0,0,ROUNDUP(I6/Rend_Desagrupe_CT,0))) -> 3 | BA6: =IF(B6="","",IF(ENTRADA!$U6="",AZ6,ENTRADA!$U6)) -> 3 | BB6: =IF(B6="","",BA6*INDEX(PRECIOS!$I$6:$I$55,K6)) -> 45 | BC6: =IF(B6="","",AY6+BB6) -> 1305 | BD6: =IF(B6="","",AI6+AS6+BC6) -> 2645 | BE6: =IF(B6="","",IF(Base_Comision="% DEL INGRESO",M6*INDEX(PRECIOS!$L$6:$L$55,K6),G6*INDEX(PRECIOS!$M$6:$M$55,K6))) -> 124.8 | BF6: =IF(B6="","",IF(Base_Comision="% DEL INGRESO",N6*INDEX(PRECIOS!$L$6:$L$55,K6),H6*INDEX(PRECIOS!$M$6:$M$55,K6))) -> 62.4 | BG6: =IF(B6="","",IF(Base_Comision="% DEL INGRESO",O6*INDEX(PRECIOS!$L$6:$L$55,K6),I6*INDEX(PRECIOS!$M$6:$M$55,K6))) -> 55.2 | BH6: =IF(B6="","",BE6+BF6+BG6) -> 242.4 | BI6: =IF(B6="","",Q6*Pct_Reclamaciones) -> 40.4 | BJ6: =IF(B6="","",Q6*Pct_Banco) -> 80.8 | BK6: =IF(B6="","",N(ENTRADA!$V6)) -> 0 | BL6: =IF(B6="","",Y6+AE6+BD6+BH6+BI6+BJ6+BK6) -> 3339.2 | BM6: =IF(B6="","",Q6-BL6) -> 4740.8 | BN6: =IF(B6="","",IF(Q6=0,0,BM6/Q6)) -> 0.58673267 | BO6: =IF(B6="","",IF(J6=0,0,BM6/J6)) -> 0.46938614 | BP6: =IF(B6="","",IFERROR(MATCH(D6,COSTOS_FIJOS!$G$5:$AD$5,0),0)) -> 1 | BQ6: =IF(B6="","",COUNTIFS($D$6:$D$305,D6)) -> 2 | BR6: =IF(B6="","",SUMIFS($J$6:$J$305,$D$6:$D$305,D6)) -> 19500 | BS6: =IF(B6="","",IF(Metodo_Prorrateo="KG",IF(BR6=0,0,J6/BR6),1/BQ6)) -> 0.51794872 | BT6: =IF(B6="","",IF(BP6=0,0,INDEX(COSTOS_FIJOS!$G$38:$AD$38,BP6))*BS6) -> 1367.4191 | BU6: =IF(B6="","",IF(Metodo_Prorrateo="KG",IF(SUMIFS($G$6:$G$305,$D$6:$D$305,D6)=0,0,G6/SUMIFS($G$6:$G$305,$D$6:$D$305,D6)),IF(G6>0,1/COUNTIFS($D$6:$D$305,D6,$G$6:$G$305,">0"),0))) -> 0.53061224 | BV6: =IF(B6="","",IF(BP6=0,0,INDEX(COSTOS_FIJOS!$G$39:$AD$39,BP6))*BU6) -> 106.12245 | BW6: =IF(B6="","",IF(Metodo_Prorrateo="KG",IF(SUMIFS($H$6:$H$305,$D$6:$D$305,D6)=0,0,H6/SUMIFS($H$6:$H$305,$D$6:$D$305,D6)),IF(H6>0,1/COUNTIFS($D$6:$D$305,D6,$H$6:$H$305,">0"),0))) -> 0.55319149 | BX6: =IF(B6="","",IF(BP6=0,0,INDEX(COSTOS_FIJOS!$G$40:$AD$40,BP6))*BW6) -> 110.6383 | BY6: =IF(B6="","",IF(Metodo_Prorrateo="KG",IF(SUMIFS($I$6:$I$305,$D$6:$D$305,D6)=0,0,I6/SUMIFS($I$6:$I$305,$D$6:$D$305,D6)),IF(I6>0,1/COUNTIFS($D$6:$D$305,D6,$I$6:$I$305,">0"),0))) -> 0.46 | BZ6: =IF(B6="","",IF(BP6=0,0,INDEX(COSTOS_FIJOS!$G$41:$AD$41,BP6))*BY6) -> 92 | CA6: =IF(B6="","",BT6+BV6+BX6+BZ6) -> 1676.1799 | CB6: =IF(B6="","",Q6*Imp_Ventas_Serv) -> 808 | CC6: =IF(B6="","",Q6*Contrib_Territorial) -> 80.8 | CD6: =IF(B6="","",BM6-CA6-CB6-CC6) -> 2175.8201 | CE6: =IF(B6="","",MAX(0,CD6)*Imp_Utilidades) -> 761.53704 | CF6: =IF(B6="","",CD6-CE6) -> 1414.2831 | CG6: =IF(B6="","",IF(Q6=0,0,CF6/Q6)) -> 0.17503503 | CH6: =IF(B6="","",IF(J6=0,0,(BL6+CA6+CB6+CC6)/J6)) -> 0.58457227 | CI6: =IF(B6="","",IF(J6=0,0,Q6/J6)) -> 0.8 | CJ6: =IF(B6="","",IF(J6=0,0,CD6/J6)) -> 0.21542773 | CK6: =IF(B6="","",Y6+AE6+BK6+BT6) -> 1698.0191 | CL6: =IF(B6="","",IF(J6=0,0,(M6+P6*G6/J6)*(1-Pct_Reclamaciones-Pct_Banco-Imp_Ventas_Serv-Contrib_Territorial)-AI6-BE6-BV6-CK6*G6/J6)) -> 2054.8499 | CM6: =IF(B6="","",IF(J6=0,0,(N6+P6*H6/J6)*(1-Pct_Reclamaciones-Pct_Banco-Imp_Ventas_Serv-Contrib_Territorial)-AS6-BF6-BX6-CK6*H6/J6)) -> 349.84786 | CN6: =IF(B6="","",IF(J6=0,0,(O6+P6*I6/J6)*(1-Pct_Reclamaciones-Pct_Banco-Imp_Ventas_Serv-Contrib_Territorial)-BC6-BG6-BZ6-CK6*I6/J6)) -> -228.87763 | CO6: =IF(B6="","",IF(J6=0,0,ROUND(CD6-CL6-CM6-CN6,4))) -> 0 | CP6: =IF(B6="","",T6+AG6+AK6+AM6+AU6+AW6) -> 1330 | CQ6: =IF(B6="","",U6+AH6+AL6+AN6+AV6+AX6) -> 1332 | CR6: =IF(B6="","",IF(CP6=0,0,CQ6/CP6-1)) -> 0.0015037594 | CS6: =IF(B6="","",IF(ENTRADA!$Y6="","",ENTRADA!$Y6-C6)) -> 10 | CT6: =IF(B6="","",IF(ENTRADA!$C6="","Falta fecha. ","")&IF(BP6=0,"Mes fuera del rango de COSTOS_FIJOS. ","")&IF(J6=0,"Sin kg. ","")&IF(E6="","Falta transitaria. ","")&IF(AND(T6>0,U6/T6-1>Tolerancia_Comb),"Combustible al puerto "&TEXT(U6/T6-1,"+0%")&" sobre norma. ","")&IF(AND(AG6>0,AH6/AG6-1>Tolerancia_Comb),"Combustible distribución Occidente "&TEXT(AH6/AG6-1,"+0%")&" sobre norma. ","")&IF(AND(AK6>0,AL6/AK6-1>Tolerancia_Comb),"Combustible traslado Centro "&TEXT(AL6/AK6-1,"+0%")&" sobre norma. ","")&IF(AND(AM6>0,AN6/AM6-1>Tolerancia_Comb),"Combustible distribución Centro "&TEXT(AN6/AM6-1,"+0%")&" sobre norma. ","")&IF(AND(AU6>0,AV6/AU6-1>Tolerancia_Comb),"Combustible traslado Oriente "&TEXT(AV6/AU6-1,"+0%")&" sobre norma. ","")&IF(AND(AW6>0,AX6/AW6-1>Tolerancia_Comb),"Combustible distribución Oriente "&TEXT(AX6/AW6-1,"+0%")&" sobre norma. ","")&IF(AND(ENTRADA!$C6<>"",C6<PRECIOS!$A$6),"Fecha anterior a la 1ª vigencia de precios. ","")&IF(CD6<0,"Contenedor con pérdida. ",""))
A7: =IF(B7="","",ROW()-5) -> 2 | B7: =IF(ENTRADA!$B7="","",ENTRADA!$B7) -> CONT-EJEMPLO-02 | C7: =IF(B7="","",ENTRADA!$C7) -> 46287 | D7: =IF(B7="","",DATE(YEAR(C7),MONTH(C7),1)) -> 46266 | E7: =IF(B7="","",ENTRADA!$D7&"") -> A.V | F7: =IF(B7="","",ENTRADA!$Z7&"") -> Cerrado | G7: =IF(B7="","",N(ENTRADA!$G7)) -> 4600 | H7: =IF(B7="","",N(ENTRADA!$H7)) -> 2100 | I7: =IF(B7="","",N(ENTRADA!$I7)) -> 2700 | J7: =IF(B7="","",G7+H7+I7) -> 9400 | K7: =IF(B7="","",IFERROR(MATCH(SUMPRODUCT(MAX((PRECIOS!$A$6:$A$55<=C7)*PRECIOS!$A$6:$A$55)),PRECIOS!$A$6:$A$55,0),1)) -> 1 | L7: =IF(B7="","",INDEX(PRECIOS!$A$6:$A$55,K7)) -> 46023 | M7: =IF(B7="","",G7*INDEX(PRECIOS!$B$6:$B$55,K7)) -> 3680 | N7: =IF(B7="","",H7*INDEX(PRECIOS!$C$6:$C$55,K7)) -> 1680 | O7: =IF(B7="","",I7*INDEX(PRECIOS!$D$6:$D$55,K7)) -> 2160 | P7: =IF(B7="","",N(ENTRADA!$X7)) -> 0 | Q7: =IF(B7="","",M7+N7+O7+P7) -> 7520 | R7: =IF(B7="","",IF(ENTRADA!$J7="",Std_Viajes_Puerto,ENTRADA!$J7)) -> 1 | S7: =IF(B7="","",R7*INDEX(PRECIOS!$F$6:$F$55,K7)) -> 10 | T7: =IF(B7="","",R7*Litros_Puerto_Viaje) -> 60 | U7: =IF(B7="","",IF(ENTRADA!$K7="",T7,ENTRADA!$K7)) -> 60 | V7: =IF(B7="","",U7*INDEX(PRECIOS!$E$6:$E$55,K7)) -> 120 | W7: =IF(B7="","",IF(ENTRADA!$L7="",R7*INDEX(PRECIOS!$G$6:$G$55,K7),ENTRADA!$L7)) -> 10 | X7: =IF(B7="","",R7*Km_Puerto_Viaje*INDEX(PRECIOS!$N$6:$N$55,K7)) -> 21.6 | Y7: =IF(B7="","",S7+V7+W7+X7) -> 161.6 | Z7: =IF(B7="","",IF(J7=0,0,ROUNDUP(J7/Rend_Desagrupe,0))) -> 10 | AA7: =IF(B7="","",IF(ENTRADA!$M7="",Z7,ENTRADA!$M7)) -> 10 | AB7: =IF(B7="","",AA7*INDEX(PRECIOS!$H$6:$H$55,K7)) -> 150 | AC7: =IF(B7="","",IF(E7="ENCI",INDEX(PRECIOS!$J$6:$J$55,K7),IF(E7="A.V",INDEX(PRECIOS!$K$6:$K$55,K7),0))) -> 0 | AD7: =IF(B7="","",N(ENTRADA!$N7)) -> 120 | AE7: =IF(B7="","",AB7+AC7+AD7) -> 270 | AF7: =IF(B7="","",IF(G7=0,0,ROUNDUP(G7/Cap_Camion_OCC,0))) -> 1 | AG7: =IF(B7="","",AF7*L_Dist_OCC) -> 120 | AH7: =IF(B7="","",IF(ENTRADA!$O7="",AG7,ENTRADA!$O7)) -> 120 | AI7: =IF(B7="","",AH7*INDEX(PRECIOS!$E$6:$E$55,K7)) -> 240 | AJ7: =IF(B7="","",IF(H7=0,0,ROUNDUP(H7/Cap_Camion_CEN,0))) -> 1 | AK7: =IF(B7="","",AJ7*L_Tras_CEN) -> 250 | AL7: =IF(B7="","",IF(ENTRADA!$P7="",AK7,ENTRADA!$P7)) -> 250 | AM7: =IF(B7="","",AJ7*L_Dist_CEN) -> 150 | AN7: =IF(B7="","",IF(ENTRADA!$Q7="",AM7,ENTRADA!$Q7)) -> 150 | AO7: =IF(B7="","",(AL7+AN7)*INDEX(PRECIOS!$E$6:$E$55,K7)) -> 800 | AP7: =IF(B7="","",IF(H7=0,0,ROUNDUP(H7/Rend_Desagrupe_CT,0))) -> 3 | AQ7: =IF(B7="","",IF(ENTRADA!$R7="",AP7,ENTRADA!$R7)) -> 3 | AR7: =IF(B7="","",AQ7*INDEX(PRECIOS!$I$6:$I$55,K7)) -> 45 | AS7: =IF(B7="","",AO7+AR7) -> 845 | AT7: =IF(B7="","",IF(I7=0,0,ROUNDUP(I7/Cap_Camion_ORI,0))) -> 1 | AU7: =IF(B7="","",AT7*L_Tras_ORI) -> 450 | AV7: =IF(B7="","",IF(ENTRADA!$S7="",AU7,ENTRADA!$S7)) -> 480 | AW7: =IF(B7="","",AT7*L_Dist_ORI) -> 180 | AX7: =IF(B7="","",IF(ENTRADA!$T7="",AW7,ENTRADA!$T7)) -> 180 | AY7: =IF(B7="","",(AV7+AX7)*INDEX(PRECIOS!$E$6:$E$55,K7)) -> 1320 | AZ7: =IF(B7="","",IF(I7=0,0,ROUNDUP(I7/Rend_Desagrupe_CT,0))) -> 4 | BA7: =IF(B7="","",IF(ENTRADA!$U7="",AZ7,ENTRADA!$U7)) -> 4 | BB7: =IF(B7="","",BA7*INDEX(PRECIOS!$I$6:$I$55,K7)) -> 60 | BC7: =IF(B7="","",AY7+BB7) -> 1380 | BD7: =IF(B7="","",AI7+AS7+BC7) -> 2465 | BE7: =IF(B7="","",IF(Base_Comision="% DEL INGRESO",M7*INDEX(PRECIOS!$L$6:$L$55,K7),G7*INDEX(PRECIOS!$M$6:$M$55,K7))) -> 110.4 | BF7: =IF(B7="","",IF(Base_Comision="% DEL INGRESO",N7*INDEX(PRECIOS!$L$6:$L$55,K7),H7*INDEX(PRECIOS!$M$6:$M$55,K7))) -> 50.4 | BG7: =IF(B7="","",IF(Base_Comision="% DEL INGRESO",O7*INDEX(PRECIOS!$L$6:$L$55,K7),I7*INDEX(PRECIOS!$M$6:$M$55,K7))) -> 64.8 | BH7: =IF(B7="","",BE7+BF7+BG7) -> 225.6 | BI7: =IF(B7="","",Q7*Pct_Reclamaciones) -> 37.6 | BJ7: =IF(B7="","",Q7*Pct_Banco) -> 75.2 | BK7: =IF(B7="","",N(ENTRADA!$V7)) -> 0 | BL7: =IF(B7="","",Y7+AE7+BD7+BH7+BI7+BJ7+BK7) -> 3235 | BM7: =IF(B7="","",Q7-BL7) -> 4285 | BN7: =IF(B7="","",IF(Q7=0,0,BM7/Q7)) -> 0.56981383 | BO7: =IF(B7="","",IF(J7=0,0,BM7/J7)) -> 0.45585106 | BP7: =IF(B7="","",IFERROR(MATCH(D7,COSTOS_FIJOS!$G$5:$AD$5,0),0)) -> 1 | BQ7: =IF(B7="","",COUNTIFS($D$6:$D$305,D7)) -> 2 | BR7: =IF(B7="","",SUMIFS($J$6:$J$305,$D$6:$D$305,D7)) -> 19500 | BS7: =IF(B7="","",IF(Metodo_Prorrateo="KG",IF(BR7=0,0,J7/BR7),1/BQ7)) -> 0.48205128 | BT7: =IF(B7="","",IF(BP7=0,0,INDEX(COSTOS_FIJOS!$G$38:$AD$38,BP7))*BS7) -> 1272.6475 | BU7: =IF(B7="","",IF(Metodo_Prorrateo="KG",IF(SUMIFS($G$6:$G$305,$D$6:$D$305,D7)=0,0,G7/SUMIFS($G$6:$G$305,$D$6:$D$305,D7)),IF(G7>0,1/COUNTIFS($D$6:$D$305,D7,$G$6:$G$305,">0"),0))) -> 0.46938776 | BV7: =IF(B7="","",IF(BP7=0,0,INDEX(COSTOS_FIJOS!$G$39:$AD$39,BP7))*BU7) -> 93.877551 | BW7: =IF(B7="","",IF(Metodo_Prorrateo="KG",IF(SUMIFS($H$6:$H$305,$D$6:$D$305,D7)=0,0,H7/SUMIFS($H$6:$H$305,$D$6:$D$305,D7)),IF(H7>0,1/COUNTIFS($D$6:$D$305,D7,$H$6:$H$305,">0"),0))) -> 0.44680851 | BX7: =IF(B7="","",IF(BP7=0,0,INDEX(COSTOS_FIJOS!$G$40:$AD$40,BP7))*BW7) -> 89.361702 | BY7: =IF(B7="","",IF(Metodo_Prorrateo="KG",IF(SUMIFS($I$6:$I$305,$D$6:$D$305,D7)=0,0,I7/SUMIFS($I$6:$I$305,$D$6:$D$305,D7)),IF(I7>0,1/COUNTIFS($D$6:$D$305,D7,$I$6:$I$305,">0"),0))) -> 0.54 | BZ7: =IF(B7="","",IF(BP7=0,0,INDEX(COSTOS_FIJOS!$G$41:$AD$41,BP7))*BY7) -> 108 | CA7: =IF(B7="","",BT7+BV7+BX7+BZ7) -> 1563.8868 | CB7: =IF(B7="","",Q7*Imp_Ventas_Serv) -> 752 | CC7: =IF(B7="","",Q7*Contrib_Territorial) -> 75.2 | CD7: =IF(B7="","",BM7-CA7-CB7-CC7) -> 1893.9132 | CE7: =IF(B7="","",MAX(0,CD7)*Imp_Utilidades) -> 662.86963 | CF7: =IF(B7="","",CD7-CE7) -> 1231.0436 | CG7: =IF(B7="","",IF(Q7=0,0,CF7/Q7)) -> 0.16370261 | CH7: =IF(B7="","",IF(J7=0,0,(BL7+CA7+CB7+CC7)/J7)) -> 0.59851987 | CI7: =IF(B7="","",IF(J7=0,0,Q7/J7)) -> 0.8 | CJ7: =IF(B7="","",IF(J7=0,0,CD7/J7)) -> 0.20148013 | CK7: =IF(B7="","",Y7+AE7+BK7+BT7) -> 1704.2475 | CL7: =IF(B7="","",IF(J7=0,0,(M7+P7*G7/J7)*(1-Pct_Reclamaciones-Pct_Banco-Imp_Ventas_Serv-Contrib_Territorial)-AI7-BE7-BV7-CK7*G7/J7)) -> 1941.729 | CM7: =IF(B7="","",IF(J7=0,0,(N7+P7*H7/J7)*(1-Pct_Reclamaciones-Pct_Banco-Imp_Ventas_Serv-Contrib_Territorial)-AS7-BF7-BX7-CK7*H7/J7)) -> 104.50215 | CN7: =IF(B7="","",IF(J7=0,0,(O7+P7*I7/J7)*(1-Pct_Reclamaciones-Pct_Banco-Imp_Ventas_Serv-Contrib_Territorial)-BC7-BG7-BZ7-CK7*I7/J7)) -> -152.31791 | CO7: =IF(B7="","",IF(J7=0,0,ROUND(CD7-CL7-CM7-CN7,4))) -> 0 | CP7: =IF(B7="","",T7+AG7+AK7+AM7+AU7+AW7) -> 1210 | CQ7: =IF(B7="","",U7+AH7+AL7+AN7+AV7+AX7) -> 1240 | CR7: =IF(B7="","",IF(CP7=0,0,CQ7/CP7-1)) -> 0.024793388 | CS7: =IF(B7="","",IF(ENTRADA!$Y7="","",ENTRADA!$Y7-C7)) -> 11 | CT7: =IF(B7="","",IF(ENTRADA!$C7="","Falta fecha. ","")&IF(BP7=0,"Mes fuera del rango de COSTOS_FIJOS. ","")&IF(J7=0,"Sin kg. ","")&IF(E7="","Falta transitaria. ","")&IF(AND(T7>0,U7/T7-1>Tolerancia_Comb),"Combustible al puerto "&TEXT(U7/T7-1,"+0%")&" sobre norma. ","")&IF(AND(AG7>0,AH7/AG7-1>Tolerancia_Comb),"Combustible distribución Occidente "&TEXT(AH7/AG7-1,"+0%")&" sobre norma. ","")&IF(AND(AK7>0,AL7/AK7-1>Tolerancia_Comb),"Combustible traslado Centro "&TEXT(AL7/AK7-1,"+0%")&" sobre norma. ","")&IF(AND(AM7>0,AN7/AM7-1>Tolerancia_Comb),"Combustible distribución Centro "&TEXT(AN7/AM7-1,"+0%")&" sobre norma. ","")&IF(AND(AU7>0,AV7/AU7-1>Tolerancia_Comb),"Combustible traslado Oriente "&TEXT(AV7/AU7-1,"+0%")&" sobre norma. ","")&IF(AND(AW7>0,AX7/AW7-1>Tolerancia_Comb),"Combustible distribución Oriente "&TEXT(AX7/AW7-1,"+0%")&" sobre norma. ","")&IF(AND(ENTRADA!$C7<>"",C7<PRECIOS!$A$6),"Fecha anterior a la 1ª vigencia de precios. ","")&IF(CD7<0,"Contenedor con pérdida. ",""))
A8: =IF(B8="","",ROW()-5) -> 3 | B8: =IF(ENTRADA!$B8="","",ENTRADA!$B8) -> CONT-EJEMPLO-03 | C8: =IF(B8="","",ENTRADA!$C8) -> 46301 | D8: =IF(B8="","",DATE(YEAR(C8),MONTH(C8),1)) -> 46296 | E8: =IF(B8="","",ENTRADA!$D8&"") -> ENCI | F8: =IF(B8="","",ENTRADA!$Z8&"") -> Cerrado | G8: =IF(B8="","",N(ENTRADA!$G8)) -> 6100 | H8: =IF(B8="","",N(ENTRADA!$H8)) -> 2900 | I8: =IF(B8="","",N(ENTRADA!$I8)) -> 2400 | J8: =IF(B8="","",G8+H8+I8) -> 11400 | K8: =IF(B8="","",IFERROR(MATCH(SUMPRODUCT(MAX((PRECIOS!$A$6:$A$55<=C8)*PRECIOS!$A$6:$A$55)),PRECIOS!$A$6:$A$55,0),1)) -> 1 | L8: =IF(B8="","",INDEX(PRECIOS!$A$6:$A$55,K8)) -> 46023 | M8: =IF(B8="","",G8*INDEX(PRECIOS!$B$6:$B$55,K8)) -> 4880 | N8: =IF(B8="","",H8*INDEX(PRECIOS!$C$6:$C$55,K8)) -> 2320 | O8: =IF(B8="","",I8*INDEX(PRECIOS!$D$6:$D$55,K8)) -> 1920 | P8: =IF(B8="","",N(ENTRADA!$X8)) -> 150 | Q8: =IF(B8="","",M8+N8+O8+P8) -> 9270 | R8: =IF(B8="","",IF(ENTRADA!$J8="",Std_Viajes_Puerto,ENTRADA!$J8)) -> 1 | S8: =IF(B8="","",R8*INDEX(PRECIOS!$F$6:$F$55,K8)) -> 10 | T8: =IF(B8="","",R8*Litros_Puerto_Viaje) -> 60 | U8: =IF(B8="","",IF(ENTRADA!$K8="",T8,ENTRADA!$K8)) -> 60 | V8: =IF(B8="","",U8*INDEX(PRECIOS!$E$6:$E$55,K8)) -> 120 | W8: =IF(B8="","",IF(ENTRADA!$L8="",R8*INDEX(PRECIOS!$G$6:$G$55,K8),ENTRADA!$L8)) -> 10 | X8: =IF(B8="","",R8*Km_Puerto_Viaje*INDEX(PRECIOS!$N$6:$N$55,K8)) -> 21.6 | Y8: =IF(B8="","",S8+V8+W8+X8) -> 161.6 | Z8: =IF(B8="","",IF(J8=0,0,ROUNDUP(J8/Rend_Desagrupe,0))) -> 12 | AA8: =IF(B8="","",IF(ENTRADA!$M8="",Z8,ENTRADA!$M8)) -> 12 | AB8: =IF(B8="","",AA8*INDEX(PRECIOS!$H$6:$H$55,K8)) -> 180 | AC8: =IF(B8="","",IF(E8="ENCI",INDEX(PRECIOS!$J$6:$J$55,K8),IF(E8="A.V",INDEX(PRECIOS!$K$6:$K$55,K8),0))) -> 0 | AD8: =IF(B8="","",N(ENTRADA!$N8)) -> 0 | AE8: =IF(B8="","",AB8+AC8+AD8) -> 180 | AF8: =IF(B8="","",IF(G8=0,0,ROUNDUP(G8/Cap_Camion_OCC,0))) -> 2 | AG8: =IF(B8="","",AF8*L_Dist_OCC) -> 240 | AH8: =IF(B8="","",IF(ENTRADA!$O8="",AG8,ENTRADA!$O8)) -> 150 | AI8: =IF(B8="","",AH8*INDEX(PRECIOS!$E$6:$E$55,K8)) -> 300 | AJ8: =IF(B8="","",IF(H8=0,0,ROUNDUP(H8/Cap_Camion_CEN,0))) -> 1 | AK8: =IF(B8="","",AJ8*L_Tras_CEN) -> 250 | AL8: =IF(B8="","",IF(ENTRADA!$P8="",AK8,ENTRADA!$P8)) -> 250 | AM8: =IF(B8="","",AJ8*L_Dist_CEN) -> 150 | AN8: =IF(B8="","",IF(ENTRADA!$Q8="",AM8,ENTRADA!$Q8)) -> 150 | AO8: =IF(B8="","",(AL8+AN8)*INDEX(PRECIOS!$E$6:$E$55,K8)) -> 800 | AP8: =IF(B8="","",IF(H8=0,0,ROUNDUP(H8/Rend_Desagrupe_CT,0))) -> 4 | AQ8: =IF(B8="","",IF(ENTRADA!$R8="",AP8,ENTRADA!$R8)) -> 4 | AR8: =IF(B8="","",AQ8*INDEX(PRECIOS!$I$6:$I$55,K8)) -> 60 | AS8: =IF(B8="","",AO8+AR8) -> 860 | AT8: =IF(B8="","",IF(I8=0,0,ROUNDUP(I8/Cap_Camion_ORI,0))) -> 1 | AU8: =IF(B8="","",AT8*L_Tras_ORI) -> 450 | AV8: =IF(B8="","",IF(ENTRADA!$S8="",AU8,ENTRADA!$S8)) -> 450 | AW8: =IF(B8="","",AT8*L_Dist_ORI) -> 180 | AX8: =IF(B8="","",IF(ENTRADA!$T8="",AW8,ENTRADA!$T8)) -> 260 | AY8: =IF(B8="","",(AV8+AX8)*INDEX(PRECIOS!$E$6:$E$55,K8)) -> 1420 | AZ8: =IF(B8="","",IF(I8=0,0,ROUNDUP(I8/Rend_Desagrupe_CT,0))) -> 3 | BA8: =IF(B8="","",IF(ENTRADA!$U8="",AZ8,ENTRADA!$U8)) -> 3 | BB8: =IF(B8="","",BA8*INDEX(PRECIOS!$I$6:$I$55,K8)) -> 45 | BC8: =IF(B8="","",AY8+BB8) -> 1465 | BD8: =IF(B8="","",AI8+AS8+BC8) -> 2625 | BE8: =IF(B8="","",IF(Base_Comision="% DEL INGRESO",M8*INDEX(PRECIOS!$L$6:$L$55,K8),G8*INDEX(PRECIOS!$M$6:$M$55,K8))) -> 146.4 | BF8: =IF(B8="","",IF(Base_Comision="% DEL INGRESO",N8*INDEX(PRECIOS!$L$6:$L$55,K8),H8*INDEX(PRECIOS!$M$6:$M$55,K8))) -> 69.6 | BG8: =IF(B8="","",IF(Base_Comision="% DEL INGRESO",O8*INDEX(PRECIOS!$L$6:$L$55,K8),I8*INDEX(PRECIOS!$M$6:$M$55,K8))) -> 57.6 | BH8: =IF(B8="","",BE8+BF8+BG8) -> 273.6 | BI8: =IF(B8="","",Q8*Pct_Reclamaciones) -> 46.35 | BJ8: =IF(B8="","",Q8*Pct_Banco) -> 92.7 | BK8: =IF(B8="","",N(ENTRADA!$V8)) -> 35 | BL8: =IF(B8="","",Y8+AE8+BD8+BH8+BI8+BJ8+BK8) -> 3414.25 | BM8: =IF(B8="","",Q8-BL8) -> 5855.75 | BN8: =IF(B8="","",IF(Q8=0,0,BM8/Q8)) -> 0.63168824 | BO8: =IF(B8="","",IF(J8=0,0,BM8/J8)) -> 0.51366228 | BP8: =IF(B8="","",IFERROR(MATCH(D8,COSTOS_FIJOS!$G$5:$AD$5,0),0)) -> 2 | BQ8: =IF(B8="","",COUNTIFS($D$6:$D$305,D8)) -> 2 | BR8: =IF(B8="","",SUMIFS($J$6:$J$305,$D$6:$D$305,D8)) -> 20600 | BS8: =IF(B8="","",IF(Metodo_Prorrateo="KG",IF(BR8=0,0,J8/BR8),1/BQ8)) -> 0.55339806 | BT8: =IF(B8="","",IF(BP8=0,0,INDEX(COSTOS_FIJOS!$G$38:$AD$38,BP8))*BS8) -> 1461.0078 | BU8: =IF(B8="","",IF(Metodo_Prorrateo="KG",IF(SUMIFS($G$6:$G$305,$D$6:$D$305,D8)=0,0,G8/SUMIFS($G$6:$G$305,$D$6:$D$305,D8)),IF(G8>0,1/COUNTIFS($D$6:$D$305,D8,$G$6:$G$305,">0"),0))) -> 0.61616162 | BV8: =IF(B8="","",IF(BP8=0,0,INDEX(COSTOS_FIJOS!$G$39:$AD$39,BP8))*BU8) -> 123.23232 | BW8: =IF(B8="","",IF(Metodo_Prorrateo="KG",IF(SUMIFS($H$6:$H$305,$D$6:$D$305,D8)=0,0,H8/SUMIFS($H$6:$H$305,$D$6:$D$305,D8)),IF(H8>0,1/COUNTIFS($D$6:$D$305,D8,$H$6:$H$305,">0"),0))) -> 0.65909091 | BX8: =IF(B8="","",IF(BP8=0,0,INDEX(COSTOS_FIJOS!$G$40:$AD$40,BP8))*BW8) -> 131.81818 | BY8: =IF(B8="","",IF(Metodo_Prorrateo="KG",IF(SUMIFS($I$6:$I$305,$D$6:$D$305,D8)=0,0,I8/SUMIFS($I$6:$I$305,$D$6:$D$305,D8)),IF(I8>0,1/COUNTIFS($D$6:$D$305,D8,$I$6:$I$305,">0"),0))) -> 0.38095238 | BZ8: =IF(B8="","",IF(BP8=0,0,INDEX(COSTOS_FIJOS!$G$41:$AD$41,BP8))*BY8) -> 76.190476 | CA8: =IF(B8="","",BT8+BV8+BX8+BZ8) -> 1792.2487 | CB8: =IF(B8="","",Q8*Imp_Ventas_Serv) -> 927 | CC8: =IF(B8="","",Q8*Contrib_Territorial) -> 92.7 | CD8: =IF(B8="","",BM8-CA8-CB8-CC8) -> 3043.8013 | CE8: =IF(B8="","",MAX(0,CD8)*Imp_Utilidades) -> 1065.3304 | CF8: =IF(B8="","",CD8-CE8) -> 1978.4708 | CG8: =IF(B8="","",IF(Q8=0,0,CF8/Q8)) -> 0.21342727 | CH8: =IF(B8="","",IF(J8=0,0,(BL8+CA8+CB8+CC8)/J8)) -> 0.54615778 | CI8: =IF(B8="","",IF(J8=0,0,Q8/J8)) -> 0.81315789 | CJ8: =IF(B8="","",IF(J8=0,0,CD8/J8)) -> 0.26700011 | CK8: =IF(B8="","",Y8+AE8+BK8+BT8) -> 1837.6078 | CL8: =IF(B8="","",IF(J8=0,0,(M8+P8*G8/J8)*(1-Pct_Reclamaciones-Pct_Banco-Imp_Ventas_Serv-Contrib_Territorial)-AI8-BE8-BV8-CK8*G8/J8)) -> 2787.3166 | CM8: =IF(B8="","",IF(J8=0,0,(N8+P8*H8/J8)*(1-Pct_Reclamaciones-Pct_Banco-Imp_Ventas_Serv-Contrib_Territorial)-AS8-BF8-BX8-CK8*H8/J8)) -> 534.50835 | CN8: =IF(B8="","",IF(J8=0,0,(O8+P8*I8/J8)*(1-Pct_Reclamaciones-Pct_Banco-Imp_Ventas_Serv-Contrib_Territorial)-BC8-BG8-BZ8-CK8*I8/J8)) -> -278.02369 | CO8: =IF(B8="","",IF(J8=0,0,ROUND(CD8-CL8-CM8-CN8,4))) -> 0 | CP8: =IF(B8="","",T8+AG8+AK8+AM8+AU8+AW8) -> 1330 | CQ8: =IF(B8="","",U8+AH8+AL8+AN8+AV8+AX8) -> 1320 | CR8: =IF(B8="","",IF(CP8=0,0,CQ8/CP8-1)) -> -0.007518797 | CS8: =IF(B8="","",IF(ENTRADA!$Y8="","",ENTRADA!$Y8-C8)) -> 10 | CT8: =IF(B8="","",IF(ENTRADA!$C8="","Falta fecha. ","")&IF(BP8=0,"Mes fuera del rango de COSTOS_FIJOS. ","")&IF(J8=0,"Sin kg. ","")&IF(E8="","Falta transitaria. ","")&IF(AND(T8>0,U8/T8-1>Tolerancia_Comb),"Combustible al puerto "&TEXT(U8/T8-1,"+0%")&" sobre norma. ","")&IF(AND(AG8>0,AH8/AG8-1>Tolerancia_Comb),"Combustible distribución Occidente "&TEXT(AH8/AG8-1,"+0%")&" sobre norma. ","")&IF(AND(AK8>0,AL8/AK8-1>Tolerancia_Comb),"Combustible traslado Centro "&TEXT(AL8/AK8-1,"+0%")&" sobre norma. ","")&IF(AND(AM8>0,AN8/AM8-1>Tolerancia_Comb),"Combustible distribución Centro "&TEXT(AN8/AM8-1,"+0%")&" sobre norma. ","")&IF(AND(AU8>0,AV8/AU8-1>Tolerancia_Comb),"Combustible traslado Oriente "&TEXT(AV8/AU8-1,"+0%")&" sobre norma. ","")&IF(AND(AW8>0,AX8/AW8-1>Tolerancia_Comb),"Combustible distribución Oriente "&TEXT(AX8/AW8-1,"+0%")&" sobre norma. ","")&IF(AND(ENTRADA!$C8<>"",C8<PRECIOS!$A$6),"Fecha anterior a la 1ª vigencia de precios. ","")&IF(CD8<0,"Contenedor con pérdida. ","")) -> Combustible distribución Oriente +44% sobre norma.
A9: =IF(B9="","",ROW()-5) -> 4 | B9: =IF(ENTRADA!$B9="","",ENTRADA!$B9) -> CONT-EJEMPLO-04 | C9: =IF(B9="","",ENTRADA!$C9) -> 46315 | D9: =IF(B9="","",DATE(YEAR(C9),MONTH(C9),1)) -> 46296 | E9: =IF(B9="","",ENTRADA!$D9&"") -> A.V | F9: =IF(B9="","",ENTRADA!$Z9&"") -> Abierto | G9: =IF(B9="","",N(ENTRADA!$G9)) -> 3800 | H9: =IF(B9="","",N(ENTRADA!$H9)) -> 1500 | I9: =IF(B9="","",N(ENTRADA!$I9)) -> 3900 | J9: =IF(B9="","",G9+H9+I9) -> 9200 | K9: =IF(B9="","",IFERROR(MATCH(SUMPRODUCT(MAX((PRECIOS!$A$6:$A$55<=C9)*PRECIOS!$A$6:$A$55)),PRECIOS!$A$6:$A$55,0),1)) -> 1 | L9: =IF(B9="","",INDEX(PRECIOS!$A$6:$A$55,K9)) -> 46023 | M9: =IF(B9="","",G9*INDEX(PRECIOS!$B$6:$B$55,K9)) -> 3040 | N9: =IF(B9="","",H9*INDEX(PRECIOS!$C$6:$C$55,K9)) -> 1200 | O9: =IF(B9="","",I9*INDEX(PRECIOS!$D$6:$D$55,K9)) -> 3120 | P9: =IF(B9="","",N(ENTRADA!$X9)) -> 0 | Q9: =IF(B9="","",M9+N9+O9+P9) -> 7360 | R9: =IF(B9="","",IF(ENTRADA!$J9="",Std_Viajes_Puerto,ENTRADA!$J9)) -> 1 | S9: =IF(B9="","",R9*INDEX(PRECIOS!$F$6:$F$55,K9)) -> 10 | T9: =IF(B9="","",R9*Litros_Puerto_Viaje) -> 60 | U9: =IF(B9="","",IF(ENTRADA!$K9="",T9,ENTRADA!$K9)) -> 60 | V9: =IF(B9="","",U9*INDEX(PRECIOS!$E$6:$E$55,K9)) -> 120 | W9: =IF(B9="","",IF(ENTRADA!$L9="",R9*INDEX(PRECIOS!$G$6:$G$55,K9),ENTRADA!$L9)) -> 10 | X9: =IF(B9="","",R9*Km_Puerto_Viaje*INDEX(PRECIOS!$N$6:$N$55,K9)) -> 21.6 | Y9: =IF(B9="","",S9+V9+W9+X9) -> 161.6 | Z9: =IF(B9="","",IF(J9=0,0,ROUNDUP(J9/Rend_Desagrupe,0))) -> 10 | AA9: =IF(B9="","",IF(ENTRADA!$M9="",Z9,ENTRADA!$M9)) -> 10 | AB9: =IF(B9="","",AA9*INDEX(PRECIOS!$H$6:$H$55,K9)) -> 150 | AC9: =IF(B9="","",IF(E9="ENCI",INDEX(PRECIOS!$J$6:$J$55,K9),IF(E9="A.V",INDEX(PRECIOS!$K$6:$K$55,K9),0))) -> 0 | AD9: =IF(B9="","",N(ENTRADA!$N9)) -> 0 | AE9: =IF(B9="","",AB9+AC9+AD9) -> 150 | AF9: =IF(B9="","",IF(G9=0,0,ROUNDUP(G9/Cap_Camion_OCC,0))) -> 1 | AG9: =IF(B9="","",AF9*L_Dist_OCC) -> 120 | AH9: =IF(B9="","",IF(ENTRADA!$O9="",AG9,ENTRADA!$O9)) -> 120 | AI9: =IF(B9="","",AH9*INDEX(PRECIOS!$E$6:$E$55,K9)) -> 240 | AJ9: =IF(B9="","",IF(H9=0,0,ROUNDUP(H9/Cap_Camion_CEN,0))) -> 1 | AK9: =IF(B9="","",AJ9*L_Tras_CEN) -> 250 | AL9: =IF(B9="","",IF(ENTRADA!$P9="",AK9,ENTRADA!$P9)) -> 250 | AM9: =IF(B9="","",AJ9*L_Dist_CEN) -> 150 | AN9: =IF(B9="","",IF(ENTRADA!$Q9="",AM9,ENTRADA!$Q9)) -> 150 | AO9: =IF(B9="","",(AL9+AN9)*INDEX(PRECIOS!$E$6:$E$55,K9)) -> 800 | AP9: =IF(B9="","",IF(H9=0,0,ROUNDUP(H9/Rend_Desagrupe_CT,0))) -> 2 | AQ9: =IF(B9="","",IF(ENTRADA!$R9="",AP9,ENTRADA!$R9)) -> 2 | AR9: =IF(B9="","",AQ9*INDEX(PRECIOS!$I$6:$I$55,K9)) -> 30 | AS9: =IF(B9="","",AO9+AR9) -> 830 | AT9: =IF(B9="","",IF(I9=0,0,ROUNDUP(I9/Cap_Camion_ORI,0))) -> 1 | AU9: =IF(B9="","",AT9*L_Tras_ORI) -> 450 | AV9: =IF(B9="","",IF(ENTRADA!$S9="",AU9,ENTRADA!$S9)) -> 450 | AW9: =IF(B9="","",AT9*L_Dist_ORI) -> 180 | AX9: =IF(B9="","",IF(ENTRADA!$T9="",AW9,ENTRADA!$T9)) -> 180 | AY9: =IF(B9="","",(AV9+AX9)*INDEX(PRECIOS!$E$6:$E$55,K9)) -> 1260 | AZ9: =IF(B9="","",IF(I9=0,0,ROUNDUP(I9/Rend_Desagrupe_CT,0))) -> 5 | BA9: =IF(B9="","",IF(ENTRADA!$U9="",AZ9,ENTRADA!$U9)) -> 5 | BB9: =IF(B9="","",BA9*INDEX(PRECIOS!$I$6:$I$55,K9)) -> 75 | BC9: =IF(B9="","",AY9+BB9) -> 1335 | BD9: =IF(B9="","",AI9+AS9+BC9) -> 2405 | BE9: =IF(B9="","",IF(Base_Comision="% DEL INGRESO",M9*INDEX(PRECIOS!$L$6:$L$55,K9),G9*INDEX(PRECIOS!$M$6:$M$55,K9))) -> 91.2 | BF9: =IF(B9="","",IF(Base_Comision="% DEL INGRESO",N9*INDEX(PRECIOS!$L$6:$L$55,K9),H9*INDEX(PRECIOS!$M$6:$M$55,K9))) -> 36 | BG9: =IF(B9="","",IF(Base_Comision="% DEL INGRESO",O9*INDEX(PRECIOS!$L$6:$L$55,K9),I9*INDEX(PRECIOS!$M$6:$M$55,K9))) -> 93.6 | BH9: =IF(B9="","",BE9+BF9+BG9) -> 220.8 | BI9: =IF(B9="","",Q9*Pct_Reclamaciones) -> 36.8 | BJ9: =IF(B9="","",Q9*Pct_Banco) -> 73.6 | BK9: =IF(B9="","",N(ENTRADA!$V9)) -> 0 | BL9: =IF(B9="","",Y9+AE9+BD9+BH9+BI9+BJ9+BK9) -> 3047.8 | BM9: =IF(B9="","",Q9-BL9) -> 4312.2 | BN9: =IF(B9="","",IF(Q9=0,0,BM9/Q9)) -> 0.58589674 | BO9: =IF(B9="","",IF(J9=0,0,BM9/J9)) -> 0.46871739 | BP9: =IF(B9="","",IFERROR(MATCH(D9,COSTOS_FIJOS!$G$5:$AD$5,0),0)) -> 2 | BQ9: =IF(B9="","",COUNTIFS($D$6:$D$305,D9)) -> 2 | BR9: =IF(B9="","",SUMIFS($J$6:$J$305,$D$6:$D$305,D9)) -> 20600 | BS9: =IF(B9="","",IF(Metodo_Prorrateo="KG",IF(BR9=0,0,J9/BR9),1/BQ9)) -> 0.44660194 | BT9: =IF(B9="","",IF(BP9=0,0,INDEX(COSTOS_FIJOS!$G$38:$AD$38,BP9))*BS9) -> 1179.0589 | BU9: =IF(B9="","",IF(Metodo_Prorrateo="KG",IF(SUMIFS($G$6:$G$305,$D$6:$D$305,D9)=0,0,G9/SUMIFS($G$6:$G$305,$D$6:$D$305,D9)),IF(G9>0,1/COUNTIFS($D$6:$D$305,D9,$G$6:$G$305,">0"),0))) -> 0.38383838 | BV9: =IF(B9="","",IF(BP9=0,0,INDEX(COSTOS_FIJOS!$G$39:$AD$39,BP9))*BU9) -> 76.767677 | BW9: =IF(B9="","",IF(Metodo_Prorrateo="KG",IF(SUMIFS($H$6:$H$305,$D$6:$D$305,D9)=0,0,H9/SUMIFS($H$6:$H$305,$D$6:$D$305,D9)),IF(H9>0,1/COUNTIFS($D$6:$D$305,D9,$H$6:$H$305,">0"),0))) -> 0.34090909 | BX9: =IF(B9="","",IF(BP9=0,0,INDEX(COSTOS_FIJOS!$G$40:$AD$40,BP9))*BW9) -> 68.181818 | BY9: =IF(B9="","",IF(Metodo_Prorrateo="KG",IF(SUMIFS($I$6:$I$305,$D$6:$D$305,D9)=0,0,I9/SUMIFS($I$6:$I$305,$D$6:$D$305,D9)),IF(I9>0,1/COUNTIFS($D$6:$D$305,D9,$I$6:$I$305,">0"),0))) -> 0.61904762 | BZ9: =IF(B9="","",IF(BP9=0,0,INDEX(COSTOS_FIJOS!$G$41:$AD$41,BP9))*BY9) -> 123.80952 | CA9: =IF(B9="","",BT9+BV9+BX9+BZ9) -> 1447.8179 | CB9: =IF(B9="","",Q9*Imp_Ventas_Serv) -> 736 | CC9: =IF(B9="","",Q9*Contrib_Territorial) -> 73.6 | CD9: =IF(B9="","",BM9-CA9-CB9-CC9) -> 2054.7821 | CE9: =IF(B9="","",MAX(0,CD9)*Imp_Utilidades) -> 719.17373 | CF9: =IF(B9="","",CD9-CE9) -> 1335.6084 | CG9: =IF(B9="","",IF(Q9=0,0,CF9/Q9)) -> 0.18146853 | CH9: =IF(B9="","",IF(J9=0,0,(BL9+CA9+CB9+CC9)/J9)) -> 0.57665412 | CI9: =IF(B9="","",IF(J9=0,0,Q9/J9)) -> 0.8 | CJ9: =IF(B9="","",IF(J9=0,0,CD9/J9)) -> 0.22334588 | CK9: =IF(B9="","",Y9+AE9+BK9+BT9) -> 1490.6589 | CL9: =IF(B9="","",IF(J9=0,0,(M9+P9*G9/J9)*(1-Pct_Reclamaciones-Pct_Banco-Imp_Ventas_Serv-Contrib_Territorial)-AI9-BE9-BV9-CK9*G9/J9)) -> 1636.3254 | CM9: =IF(B9="","",IF(J9=0,0,(N9+P9*H9/J9)*(1-Pct_Reclamaciones-Pct_Banco-Imp_Ventas_Serv-Contrib_Territorial)-AS9-BF9-BX9-CK9*H9/J9)) -> -127.22403 | CN9: =IF(B9="","",IF(J9=0,0,(O9+P9*I9/J9)*(1-Pct_Reclamaciones-Pct_Banco-Imp_Ventas_Serv-Contrib_Territorial)-BC9-BG9-BZ9-CK9*I9/J9)) -> 545.68073 | CO9: =IF(B9="","",IF(J9=0,0,ROUND(CD9-CL9-CM9-CN9,4))) -> 0 | CP9: =IF(B9="","",T9+AG9+AK9+AM9+AU9+AW9) -> 1210 | CQ9: =IF(B9="","",U9+AH9+AL9+AN9+AV9+AX9) -> 1210 | CR9: =IF(B9="","",IF(CP9=0,0,CQ9/CP9-1)) -> 0 | CS9: =IF(B9="","",IF(ENTRADA!$Y9="","",ENTRADA!$Y9-C9)) | CT9: =IF(B9="","",IF(ENTRADA!$C9="","Falta fecha. ","")&IF(BP9=0,"Mes fuera del rango de COSTOS_FIJOS. ","")&IF(J9=0,"Sin kg. ","")&IF(E9="","Falta transitaria. ","")&IF(AND(T9>0,U9/T9-1>Tolerancia_Comb),"Combustible al puerto "&TEXT(U9/T9-1,"+0%")&" sobre norma. ","")&IF(AND(AG9>0,AH9/AG9-1>Tolerancia_Comb),"Combustible distribución Occidente "&TEXT(AH9/AG9-1,"+0%")&" sobre norma. ","")&IF(AND(AK9>0,AL9/AK9-1>Tolerancia_Comb),"Combustible traslado Centro "&TEXT(AL9/AK9-1,"+0%")&" sobre norma. ","")&IF(AND(AM9>0,AN9/AM9-1>Tolerancia_Comb),"Combustible distribución Centro "&TEXT(AN9/AM9-1,"+0%")&" sobre norma. ","")&IF(AND(AU9>0,AV9/AU9-1>Tolerancia_Comb),"Combustible traslado Oriente "&TEXT(AV9/AU9-1,"+0%")&" sobre norma. ","")&IF(AND(AW9>0,AX9/AW9-1>Tolerancia_Comb),"Combustible distribución Oriente "&TEXT(AX9/AW9-1,"+0%")&" sobre norma. ","")&IF(AND(ENTRADA!$C9<>"",C9<PRECIOS!$A$6),"Fecha anterior a la 1ª vigencia de precios. ","")&IF(CD9<0,"Contenedor con pérdida. ",""))
A10: =IF(B10="","",ROW()-5) | B10: =IF(ENTRADA!$B10="","",ENTRADA!$B10) | C10: =IF(B10="","",ENTRADA!$C10) | D10: =IF(B10="","",DATE(YEAR(C10),MONTH(C10),1)) | E10: =IF(B10="","",ENTRADA!$D10&"") | F10: =IF(B10="","",ENTRADA!$Z10&"") | G10: =IF(B10="","",N(ENTRADA!$G10)) | H10: =IF(B10="","",N(ENTRADA!$H10)) | I10: =IF(B10="","",N(ENTRADA!$I10)) | J10: =IF(B10="","",G10+H10+I10) | K10: =IF(B10="","",IFERROR(MATCH(SUMPRODUCT(MAX((PRECIOS!$A$6:$A$55<=C10)*PRECIOS!$A$6:$A$55)),PRECIOS!$A$6:$A$55,0),1)) | L10: =IF(B10="","",INDEX(PRECIOS!$A$6:$A$55,K10)) | M10: =IF(B10="","",G10*INDEX(PRECIOS!$B$6:$B$55,K10)) | N10: =IF(B10="","",H10*INDEX(PRECIOS!$C$6:$C$55,K10)) | O10: =IF(B10="","",I10*INDEX(PRECIOS!$D$6:$D$55,K10)) | P10: =IF(B10="","",N(ENTRADA!$X10)) | Q10: =IF(B10="","",M10+N10+O10+P10) | R10: =IF(B10="","",IF(ENTRADA!$J10="",Std_Viajes_Puerto,ENTRADA!$J10)) | S10: =IF(B10="","",R10*INDEX(PRECIOS!$F$6:$F$55,K10)) | T10: =IF(B10="","",R10*Litros_Puerto_Viaje) | U10: =IF(B10="","",IF(ENTRADA!$K10="",T10,ENTRADA!$K10)) | V10: =IF(B10="","",U10*INDEX(PRECIOS!$E$6:$E$55,K10)) | W10: =IF(B10="","",IF(ENTRADA!$L10="",R10*INDEX(PRECIOS!$G$6:$G$55,K10),ENTRADA!$L10)) | X10: =IF(B10="","",R10*Km_Puerto_Viaje*INDEX(PRECIOS!$N$6:$N$55,K10)) | Y10: =IF(B10="","",S10+V10+W10+X10) | Z10: =IF(B10="","",IF(J10=0,0,ROUNDUP(J10/Rend_Desagrupe,0))) | AA10: =IF(B10="","",IF(ENTRADA!$M10="",Z10,ENTRADA!$M10)) | AB10: =IF(B10="","",AA10*INDEX(PRECIOS!$H$6:$H$55,K10)) | AC10: =IF(B10="","",IF(E10="ENCI",INDEX(PRECIOS!$J$6:$J$55,K10),IF(E10="A.V",INDEX(PRECIOS!$K$6:$K$55,K10),0))) | AD10: =IF(B10="","",N(ENTRADA!$N10)) | AE10: =IF(B10="","",AB10+AC10+AD10) | AF10: =IF(B10="","",IF(G10=0,0,ROUNDUP(G10/Cap_Camion_OCC,0))) | AG10: =IF(B10="","",AF10*L_Dist_OCC) | AH10: =IF(B10="","",IF(ENTRADA!$O10="",AG10,ENTRADA!$O10)) | AI10: =IF(B10="","",AH10*INDEX(PRECIOS!$E$6:$E$55,K10)) | AJ10: =IF(B10="","",IF(H10=0,0,ROUNDUP(H10/Cap_Camion_CEN,0))) | AK10: =IF(B10="","",AJ10*L_Tras_CEN) | AL10: =IF(B10="","",IF(ENTRADA!$P10="",AK10,ENTRADA!$P10)) | AM10: =IF(B10="","",AJ10*L_Dist_CEN) | AN10: =IF(B10="","",IF(ENTRADA!$Q10="",AM10,ENTRADA!$Q10)) | AO10: =IF(B10="","",(AL10+AN10)*INDEX(PRECIOS!$E$6:$E$55,K10)) | AP10: =IF(B10="","",IF(H10=0,0,ROUNDUP(H10/Rend_Desagrupe_CT,0))) | AQ10: =IF(B10="","",IF(ENTRADA!$R10="",AP10,ENTRADA!$R10)) | AR10: =IF(B10="","",AQ10*INDEX(PRECIOS!$I$6:$I$55,K10)) | AS10: =IF(B10="","",AO10+AR10) | AT10: =IF(B10="","",IF(I10=0,0,ROUNDUP(I10/Cap_Camion_ORI,0))) | AU10: =IF(B10="","",AT10*L_Tras_ORI) | AV10: =IF(B10="","",IF(ENTRADA!$S10="",AU10,ENTRADA!$S10)) | AW10: =IF(B10="","",AT10*L_Dist_ORI) | AX10: =IF(B10="","",IF(ENTRADA!$T10="",AW10,ENTRADA!$T10)) | AY10: =IF(B10="","",(AV10+AX10)*INDEX(PRECIOS!$E$6:$E$55,K10)) | AZ10: =IF(B10="","",IF(I10=0,0,ROUNDUP(I10/Rend_Desagrupe_CT,0))) | BA10: =IF(B10="","",IF(ENTRADA!$U10="",AZ10,ENTRADA!$U10)) | BB10: =IF(B10="","",BA10*INDEX(PRECIOS!$I$6:$I$55,K10)) | BC10: =IF(B10="","",AY10+BB10) | BD10: =IF(B10="","",AI10+AS10+BC10) | BE10: =IF(B10="","",IF(Base_Comision="% DEL INGRESO",M10*INDEX(PRECIOS!$L$6:$L$55,K10),G10*INDEX(PRECIOS!$M$6:$M$55,K10))) | BF10: =IF(B10="","",IF(Base_Comision="% DEL INGRESO",N10*INDEX(PRECIOS!$L$6:$L$55,K10),H10*INDEX(PRECIOS!$M$6:$M$55,K10))) | BG10: =IF(B10="","",IF(Base_Comision="% DEL INGRESO",O10*INDEX(PRECIOS!$L$6:$L$55,K10),I10*INDEX(PRECIOS!$M$6:$M$55,K10))) | BH10: =IF(B10="","",BE10+BF10+BG10) | BI10: =IF(B10="","",Q10*Pct_Reclamaciones) | BJ10: =IF(B10="","",Q10*Pct_Banco) | BK10: =IF(B10="","",N(ENTRADA!$V10)) | BL10: =IF(B10="","",Y10+AE10+BD10+BH10+BI10+BJ10+BK10) | BM10: =IF(B10="","",Q10-BL10) | BN10: =IF(B10="","",IF(Q10=0,0,BM10/Q10)) | BO10: =IF(B10="","",IF(J10=0,0,BM10/J10)) | BP10: =IF(B10="","",IFERROR(MATCH(D10,COSTOS_FIJOS!$G$5:$AD$5,0),0)) | BQ10: =IF(B10="","",COUNTIFS($D$6:$D$305,D10)) | BR10: =IF(B10="","",SUMIFS($J$6:$J$305,$D$6:$D$305,D10)) | BS10: =IF(B10="","",IF(Metodo_Prorrateo="KG",IF(BR10=0,0,J10/BR10),1/BQ10)) | BT10: =IF(B10="","",IF(BP10=0,0,INDEX(COSTOS_FIJOS!$G$38:$AD$38,BP10))*BS10) | BU10: =IF(B10="","",IF(Metodo_Prorrateo="KG",IF(SUMIFS($G$6:$G$305,$D$6:$D$305,D10)=0,0,G10/SUMIFS($G$6:$G$305,$D$6:$D$305,D10)),IF(G10>0,1/COUNTIFS($D$6:$D$305,D10,$G$6:$G$305,">0"),0))) | BV10: =IF(B10="","",IF(BP10=0,0,INDEX(COSTOS_FIJOS!$G$39:$AD$39,BP10))*BU10) | BW10: =IF(B10="","",IF(Metodo_Prorrateo="KG",IF(SUMIFS($H$6:$H$305,$D$6:$D$305,D10)=0,0,H10/SUMIFS($H$6:$H$305,$D$6:$D$305,D10)),IF(H10>0,1/COUNTIFS($D$6:$D$305,D10,$H$6:$H$305,">0"),0))) | BX10: =IF(B10="","",IF(BP10=0,0,INDEX(COSTOS_FIJOS!$G$40:$AD$40,BP10))*BW10) | BY10: =IF(B10="","",IF(Metodo_Prorrateo="KG",IF(SUMIFS($I$6:$I$305,$D$6:$D$305,D10)=0,0,I10/SUMIFS($I$6:$I$305,$D$6:$D$305,D10)),IF(I10>0,1/COUNTIFS($D$6:$D$305,D10,$I$6:$I$305,">0"),0))) | BZ10: =IF(B10="","",IF(BP10=0,0,INDEX(COSTOS_FIJOS!$G$41:$AD$41,BP10))*BY10) | CA10: =IF(B10="","",BT10+BV10+BX10+BZ10) | CB10: =IF(B10="","",Q10*Imp_Ventas_Serv) | CC10: =IF(B10="","",Q10*Contrib_Territorial) | CD10: =IF(B10="","",BM10-CA10-CB10-CC10) | CE10: =IF(B10="","",MAX(0,CD10)*Imp_Utilidades) | CF10: =IF(B10="","",CD10-CE10) | CG10: =IF(B10="","",IF(Q10=0,0,CF10/Q10)) | CH10: =IF(B10="","",IF(J10=0,0,(BL10+CA10+CB10+CC10)/J10)) | CI10: =IF(B10="","",IF(J10=0,0,Q10/J10)) | CJ10: =IF(B10="","",IF(J10=0,0,CD10/J10)) | CK10: =IF(B10="","",Y10+AE10+BK10+BT10) | CL10: =IF(B10="","",IF(J10=0,0,(M10+P10*G10/J10)*(1-Pct_Reclamaciones-Pct_Banco-Imp_Ventas_Serv-Contrib_Territorial)-AI10-BE10-BV10-CK10*G10/J10)) | CM10: =IF(B10="","",IF(J10=0,0,(N10+P10*H10/J10)*(1-Pct_Reclamaciones-Pct_Banco-Imp_Ventas_Serv-Contrib_Territorial)-AS10-BF10-BX10-CK10*H10/J10)) | CN10: =IF(B10="","",IF(J10=0,0,(O10+P10*I10/J10)*(1-Pct_Reclamaciones-Pct_Banco-Imp_Ventas_Serv-Contrib_Territorial)-BC10-BG10-BZ10-CK10*I10/J10)) | CO10: =IF(B10="","",IF(J10=0,0,ROUND(CD10-CL10-CM10-CN10,4))) | CP10: =IF(B10="","",T10+AG10+AK10+AM10+AU10+AW10) | CQ10: =IF(B10="","",U10+AH10+AL10+AN10+AV10+AX10) | CR10: =IF(B10="","",IF(CP10=0,0,CQ10/CP10-1)) | CS10: =IF(B10="","",IF(ENTRADA!$Y10="","",ENTRADA!$Y10-C10)) | CT10: =IF(B10="","",IF(ENTRADA!$C10="","Falta fecha. ","")&IF(BP10=0,"Mes fuera del rango de COSTOS_FIJOS. ","")&IF(J10=0,"Sin kg. ","")&IF(E10="","Falta transitaria. ","")&IF(AND(T10>0,U10/T10-1>Tolerancia_Comb),"Combustible al puerto "&TEXT(U10/T10-1,"+0%")&" sobre norma. ","")&IF(AND(AG10>0,AH10/AG10-1>Tolerancia_Comb),"Combustible distribución Occidente "&TEXT(AH10/AG10-1,"+0%")&" sobre norma. ","")&IF(AND(AK10>0,AL10/AK10-1>Tolerancia_Comb),"Combustible traslado Centro "&TEXT(AL10/AK10-1,"+0%")&" sobre norma. ","")&IF(AND(AM10>0,AN10/AM10-1>Tolerancia_Comb),"Combustible distribución Centro "&TEXT(AN10/AM10-1,"+0%")&" sobre norma. ","")&IF(AND(AU10>0,AV10/AU10-1>Tolerancia_Comb),"Combustible traslado Oriente "&TEXT(AV10/AU10-1,"+0%")&" sobre norma. ","")&IF(AND(AW10>0,AX10/AW10-1>Tolerancia_Comb),"Combustible distribución Oriente "&TEXT(AX10/AW10-1,"+0%")&" sobre norma. ","")&IF(AND(ENTRADA!$C10<>"",C10<PRECIOS!$A$6),"Fecha anterior a la 1ª vigencia de precios. ","")&IF(CD10<0,"Contenedor con pérdida. ",""))
A11: =IF(B11="","",ROW()-5) | B11: =IF(ENTRADA!$B11="","",ENTRADA!$B11) | C11: =IF(B11="","",ENTRADA!$C11) | D11: =IF(B11="","",DATE(YEAR(C11),MONTH(C11),1)) | E11: =IF(B11="","",ENTRADA!$D11&"") | F11: =IF(B11="","",ENTRADA!$Z11&"") | G11: =IF(B11="","",N(ENTRADA!$G11)) | H11: =IF(B11="","",N(ENTRADA!$H11)) | I11: =IF(B11="","",N(ENTRADA!$I11)) | J11: =IF(B11="","",G11+H11+I11) | K11: =IF(B11="","",IFERROR(MATCH(SUMPRODUCT(MAX((PRECIOS!$A$6:$A$55<=C11)*PRECIOS!$A$6:$A$55)),PRECIOS!$A$6:$A$55,0),1)) | L11: =IF(B11="","",INDEX(PRECIOS!$A$6:$A$55,K11)) | M11: =IF(B11="","",G11*INDEX(PRECIOS!$B$6:$B$55,K11)) | N11: =IF(B11="","",H11*INDEX(PRECIOS!$C$6:$C$55,K11)) | O11: =IF(B11="","",I11*INDEX(PRECIOS!$D$6:$D$55,K11)) | P11: =IF(B11="","",N(ENTRADA!$X11)) | Q11: =IF(B11="","",M11+N11+O11+P11) | R11: =IF(B11="","",IF(ENTRADA!$J11="",Std_Viajes_Puerto,ENTRADA!$J11)) | S11: =IF(B11="","",R11*INDEX(PRECIOS!$F$6:$F$55,K11)) | T11: =IF(B11="","",R11*Litros_Puerto_Viaje) | U11: =IF(B11="","",IF(ENTRADA!$K11="",T11,ENTRADA!$K11)) | V11: =IF(B11="","",U11*INDEX(PRECIOS!$E$6:$E$55,K11)) | W11: =IF(B11="","",IF(ENTRADA!$L11="",R11*INDEX(PRECIOS!$G$6:$G$55,K11),ENTRADA!$L11)) | X11: =IF(B11="","",R11*Km_Puerto_Viaje*INDEX(PRECIOS!$N$6:$N$55,K11)) | Y11: =IF(B11="","",S11+V11+W11+X11) | Z11: =IF(B11="","",IF(J11=0,0,ROUNDUP(J11/Rend_Desagrupe,0))) | AA11: =IF(B11="","",IF(ENTRADA!$M11="",Z11,ENTRADA!$M11)) | AB11: =IF(B11="","",AA11*INDEX(PRECIOS!$H$6:$H$55,K11)) | AC11: =IF(B11="","",IF(E11="ENCI",INDEX(PRECIOS!$J$6:$J$55,K11),IF(E11="A.V",INDEX(PRECIOS!$K$6:$K$55,K11),0))) | AD11: =IF(B11="","",N(ENTRADA!$N11)) | AE11: =IF(B11="","",AB11+AC11+AD11) | AF11: =IF(B11="","",IF(G11=0,0,ROUNDUP(G11/Cap_Camion_OCC,0))) | AG11: =IF(B11="","",AF11*L_Dist_OCC) | AH11: =IF(B11="","",IF(ENTRADA!$O11="",AG11,ENTRADA!$O11)) | AI11: =IF(B11="","",AH11*INDEX(PRECIOS!$E$6:$E$55,K11)) | AJ11: =IF(B11="","",IF(H11=0,0,ROUNDUP(H11/Cap_Camion_CEN,0))) | AK11: =IF(B11="","",AJ11*L_Tras_CEN) | AL11: =IF(B11="","",IF(ENTRADA!$P11="",AK11,ENTRADA!$P11)) | AM11: =IF(B11="","",AJ11*L_Dist_CEN) | AN11: =IF(B11="","",IF(ENTRADA!$Q11="",AM11,ENTRADA!$Q11)) | AO11: =IF(B11="","",(AL11+AN11)*INDEX(PRECIOS!$E$6:$E$55,K11)) | AP11: =IF(B11="","",IF(H11=0,0,ROUNDUP(H11/Rend_Desagrupe_CT,0))) | AQ11: =IF(B11="","",IF(ENTRADA!$R11="",AP11,ENTRADA!$R11)) | AR11: =IF(B11="","",AQ11*INDEX(PRECIOS!$I$6:$I$55,K11)) | AS11: =IF(B11="","",AO11+AR11) | AT11: =IF(B11="","",IF(I11=0,0,ROUNDUP(I11/Cap_Camion_ORI,0))) | AU11: =IF(B11="","",AT11*L_Tras_ORI) | AV11: =IF(B11="","",IF(ENTRADA!$S11="",AU11,ENTRADA!$S11)) | AW11: =IF(B11="","",AT11*L_Dist_ORI) | AX11: =IF(B11="","",IF(ENTRADA!$T11="",AW11,ENTRADA!$T11)) | AY11: =IF(B11="","",(AV11+AX11)*INDEX(PRECIOS!$E$6:$E$55,K11)) | AZ11: =IF(B11="","",IF(I11=0,0,ROUNDUP(I11/Rend_Desagrupe_CT,0))) | BA11: =IF(B11="","",IF(ENTRADA!$U11="",AZ11,ENTRADA!$U11)) | BB11: =IF(B11="","",BA11*INDEX(PRECIOS!$I$6:$I$55,K11)) | BC11: =IF(B11="","",AY11+BB11) | BD11: =IF(B11="","",AI11+AS11+BC11) | BE11: =IF(B11="","",IF(Base_Comision="% DEL INGRESO",M11*INDEX(PRECIOS!$L$6:$L$55,K11),G11*INDEX(PRECIOS!$M$6:$M$55,K11))) | BF11: =IF(B11="","",IF(Base_Comision="% DEL INGRESO",N11*INDEX(PRECIOS!$L$6:$L$55,K11),H11*INDEX(PRECIOS!$M$6:$M$55,K11))) | BG11: =IF(B11="","",IF(Base_Comision="% DEL INGRESO",O11*INDEX(PRECIOS!$L$6:$L$55,K11),I11*INDEX(PRECIOS!$M$6:$M$55,K11))) | BH11: =IF(B11="","",BE11+BF11+BG11) | BI11: =IF(B11="","",Q11*Pct_Reclamaciones) | BJ11: =IF(B11="","",Q11*Pct_Banco) | BK11: =IF(B11="","",N(ENTRADA!$V11)) | BL11: =IF(B11="","",Y11+AE11+BD11+BH11+BI11+BJ11+BK11) | BM11: =IF(B11="","",Q11-BL11) | BN11: =IF(B11="","",IF(Q11=0,0,BM11/Q11)) | BO11: =IF(B11="","",IF(J11=0,0,BM11/J11)) | BP11: =IF(B11="","",IFERROR(MATCH(D11,COSTOS_FIJOS!$G$5:$AD$5,0),0)) | BQ11: =IF(B11="","",COUNTIFS($D$6:$D$305,D11)) | BR11: =IF(B11="","",SUMIFS($J$6:$J$305,$D$6:$D$305,D11)) | BS11: =IF(B11="","",IF(Metodo_Prorrateo="KG",IF(BR11=0,0,J11/BR11),1/BQ11)) | BT11: =IF(B11="","",IF(BP11=0,0,INDEX(COSTOS_FIJOS!$G$38:$AD$38,BP11))*BS11) | BU11: =IF(B11="","",IF(Metodo_Prorrateo="KG",IF(SUMIFS($G$6:$G$305,$D$6:$D$305,D11)=0,0,G11/SUMIFS($G$6:$G$305,$D$6:$D$305,D11)),IF(G11>0,1/COUNTIFS($D$6:$D$305,D11,$G$6:$G$305,">0"),0))) | BV11: =IF(B11="","",IF(BP11=0,0,INDEX(COSTOS_FIJOS!$G$39:$AD$39,BP11))*BU11) | BW11: =IF(B11="","",IF(Metodo_Prorrateo="KG",IF(SUMIFS($H$6:$H$305,$D$6:$D$305,D11)=0,0,H11/SUMIFS($H$6:$H$305,$D$6:$D$305,D11)),IF(H11>0,1/COUNTIFS($D$6:$D$305,D11,$H$6:$H$305,">0"),0))) | BX11: =IF(B11="","",IF(BP11=0,0,INDEX(COSTOS_FIJOS!$G$40:$AD$40,BP11))*BW11) | BY11: =IF(B11="","",IF(Metodo_Prorrateo="KG",IF(SUMIFS($I$6:$I$305,$D$6:$D$305,D11)=0,0,I11/SUMIFS($I$6:$I$305,$D$6:$D$305,D11)),IF(I11>0,1/COUNTIFS($D$6:$D$305,D11,$I$6:$I$305,">0"),0))) | BZ11: =IF(B11="","",IF(BP11=0,0,INDEX(COSTOS_FIJOS!$G$41:$AD$41,BP11))*BY11) | CA11: =IF(B11="","",BT11+BV11+BX11+BZ11) | CB11: =IF(B11="","",Q11*Imp_Ventas_Serv) | CC11: =IF(B11="","",Q11*Contrib_Territorial) | CD11: =IF(B11="","",BM11-CA11-CB11-CC11) | CE11: =IF(B11="","",MAX(0,CD11)*Imp_Utilidades) | CF11: =IF(B11="","",CD11-CE11) | CG11: =IF(B11="","",IF(Q11=0,0,CF11/Q11)) | CH11: =IF(B11="","",IF(J11=0,0,(BL11+CA11+CB11+CC11)/J11)) | CI11: =IF(B11="","",IF(J11=0,0,Q11/J11)) | CJ11: =IF(B11="","",IF(J11=0,0,CD11/J11)) | CK11: =IF(B11="","",Y11+AE11+BK11+BT11) | CL11: =IF(B11="","",IF(J11=0,0,(M11+P11*G11/J11)*(1-Pct_Reclamaciones-Pct_Banco-Imp_Ventas_Serv-Contrib_Territorial)-AI11-BE11-BV11-CK11*G11/J11)) | CM11: =IF(B11="","",IF(J11=0,0,(N11+P11*H11/J11)*(1-Pct_Reclamaciones-Pct_Banco-Imp_Ventas_Serv-Contrib_Territorial)-AS11-BF11-BX11-CK11*H11/J11)) | CN11: =IF(B11="","",IF(J11=0,0,(O11+P11*I11/J11)*(1-Pct_Reclamaciones-Pct_Banco-Imp_Ventas_Serv-Contrib_Territorial)-BC11-BG11-BZ11-CK11*I11/J11)) | CO11: =IF(B11="","",IF(J11=0,0,ROUND(CD11-CL11-CM11-CN11,4))) | CP11: =IF(B11="","",T11+AG11+AK11+AM11+AU11+AW11) | CQ11: =IF(B11="","",U11+AH11+AL11+AN11+AV11+AX11) | CR11: =IF(B11="","",IF(CP11=0,0,CQ11/CP11-1)) | CS11: =IF(B11="","",IF(ENTRADA!$Y11="","",ENTRADA!$Y11-C11)) | CT11: =IF(B11="","",IF(ENTRADA!$C11="","Falta fecha. ","")&IF(BP11=0,"Mes fuera del rango de COSTOS_FIJOS. ","")&IF(J11=0,"Sin kg. ","")&IF(E11="","Falta transitaria. ","")&IF(AND(T11>0,U11/T11-1>Tolerancia_Comb),"Combustible al puerto "&TEXT(U11/T11-1,"+0%")&" sobre norma. ","")&IF(AND(AG11>0,AH11/AG11-1>Tolerancia_Comb),"Combustible distribución Occidente "&TEXT(AH11/AG11-1,"+0%")&" sobre norma. ","")&IF(AND(AK11>0,AL11/AK11-1>Tolerancia_Comb),"Combustible traslado Centro "&TEXT(AL11/AK11-1,"+0%")&" sobre norma. ","")&IF(AND(AM11>0,AN11/AM11-1>Tolerancia_Comb),"Combustible distribución Centro "&TEXT(AN11/AM11-1,"+0%")&" sobre norma. ","")&IF(AND(AU11>0,AV11/AU11-1>Tolerancia_Comb),"Combustible traslado Oriente "&TEXT(AV11/AU11-1,"+0%")&" sobre norma. ","")&IF(AND(AW11>0,AX11/AW11-1>Tolerancia_Comb),"Combustible distribución Oriente "&TEXT(AX11/AW11-1,"+0%")&" sobre norma. ","")&IF(AND(ENTRADA!$C11<>"",C11<PRECIOS!$A$6),"Fecha anterior a la 1ª vigencia de precios. ","")&IF(CD11<0,"Contenedor con pérdida. ",""))
A12: =IF(B12="","",ROW()-5) | B12: =IF(ENTRADA!$B12="","",ENTRADA!$B12) | C12: =IF(B12="","",ENTRADA!$C12) | D12: =IF(B12="","",DATE(YEAR(C12),MONTH(C12),1)) | E12: =IF(B12="","",ENTRADA!$D12&"") | F12: =IF(B12="","",ENTRADA!$Z12&"") | G12: =IF(B12="","",N(ENTRADA!$G12)) | H12: =IF(B12="","",N(ENTRADA!$H12)) | I12: =IF(B12="","",N(ENTRADA!$I12)) | J12: =IF(B12="","",G12+H12+I12) | K12: =IF(B12="","",IFERROR(MATCH(SUMPRODUCT(MAX((PRECIOS!$A$6:$A$55<=C12)*PRECIOS!$A$6:$A$55)),PRECIOS!$A$6:$A$55,0),1)) | L12: =IF(B12="","",INDEX(PRECIOS!$A$6:$A$55,K12)) | M12: =IF(B12="","",G12*INDEX(PRECIOS!$B$6:$B$55,K12)) | N12: =IF(B12="","",H12*INDEX(PRECIOS!$C$6:$C$55,K12)) | O12: =IF(B12="","",I12*INDEX(PRECIOS!$D$6:$D$55,K12)) | P12: =IF(B12="","",N(ENTRADA!$X12)) | Q12: =IF(B12="","",M12+N12+O12+P12) | R12: =IF(B12="","",IF(ENTRADA!$J12="",Std_Viajes_Puerto,ENTRADA!$J12)) | S12: =IF(B12="","",R12*INDEX(PRECIOS!$F$6:$F$55,K12)) | T12: =IF(B12="","",R12*Litros_Puerto_Viaje) | U12: =IF(B12="","",IF(ENTRADA!$K12="",T12,ENTRADA!$K12)) | V12: =IF(B12="","",U12*INDEX(PRECIOS!$E$6:$E$55,K12)) | W12: =IF(B12="","",IF(ENTRADA!$L12="",R12*INDEX(PRECIOS!$G$6:$G$55,K12),ENTRADA!$L12)) | X12: =IF(B12="","",R12*Km_Puerto_Viaje*INDEX(PRECIOS!$N$6:$N$55,K12)) | Y12: =IF(B12="","",S12+V12+W12+X12) | Z12: =IF(B12="","",IF(J12=0,0,ROUNDUP(J12/Rend_Desagrupe,0))) | AA12: =IF(B12="","",IF(ENTRADA!$M12="",Z12,ENTRADA!$M12)) | AB12: =IF(B12="","",AA12*INDEX(PRECIOS!$H$6:$H$55,K12)) | AC12: =IF(B12="","",IF(E12="ENCI",INDEX(PRECIOS!$J$6:$J$55,K12),IF(E12="A.V",INDEX(PRECIOS!$K$6:$K$55,K12),0))) | AD12: =IF(B12="","",N(ENTRADA!$N12)) | AE12: =IF(B12="","",AB12+AC12+AD12) | AF12: =IF(B12="","",IF(G12=0,0,ROUNDUP(G12/Cap_Camion_OCC,0))) | AG12: =IF(B12="","",AF12*L_Dist_OCC) | AH12: =IF(B12="","",IF(ENTRADA!$O12="",AG12,ENTRADA!$O12)) | AI12: =IF(B12="","",AH12*INDEX(PRECIOS!$E$6:$E$55,K12)) | AJ12: =IF(B12="","",IF(H12=0,0,ROUNDUP(H12/Cap_Camion_CEN,0))) | AK12: =IF(B12="","",AJ12*L_Tras_CEN) | AL12: =IF(B12="","",IF(ENTRADA!$P12="",AK12,ENTRADA!$P12)) | AM12: =IF(B12="","",AJ12*L_Dist_CEN) | AN12: =IF(B12="","",IF(ENTRADA!$Q12="",AM12,ENTRADA!$Q12)) | AO12: =IF(B12="","",(AL12+AN12)*INDEX(PRECIOS!$E$6:$E$55,K12)) | AP12: =IF(B12="","",IF(H12=0,0,ROUNDUP(H12/Rend_Desagrupe_CT,0))) | AQ12: =IF(B12="","",IF(ENTRADA!$R12="",AP12,ENTRADA!$R12)) | AR12: =IF(B12="","",AQ12*INDEX(PRECIOS!$I$6:$I$55,K12)) | AS12: =IF(B12="","",AO12+AR12) | AT12: =IF(B12="","",IF(I12=0,0,ROUNDUP(I12/Cap_Camion_ORI,0))) | AU12: =IF(B12="","",AT12*L_Tras_ORI) | AV12: =IF(B12="","",IF(ENTRADA!$S12="",AU12,ENTRADA!$S12)) | AW12: =IF(B12="","",AT12*L_Dist_ORI) | AX12: =IF(B12="","",IF(ENTRADA!$T12="",AW12,ENTRADA!$T12)) | AY12: =IF(B12="","",(AV12+AX12)*INDEX(PRECIOS!$E$6:$E$55,K12)) | AZ12: =IF(B12="","",IF(I12=0,0,ROUNDUP(I12/Rend_Desagrupe_CT,0))) | BA12: =IF(B12="","",IF(ENTRADA!$U12="",AZ12,ENTRADA!$U12)) | BB12: =IF(B12="","",BA12*INDEX(PRECIOS!$I$6:$I$55,K12)) | BC12: =IF(B12="","",AY12+BB12) | BD12: =IF(B12="","",AI12+AS12+BC12) | BE12: =IF(B12="","",IF(Base_Comision="% DEL INGRESO",M12*INDEX(PRECIOS!$L$6:$L$55,K12),G12*INDEX(PRECIOS!$M$6:$M$55,K12))) | BF12: =IF(B12="","",IF(Base_Comision="% DEL INGRESO",N12*INDEX(PRECIOS!$L$6:$L$55,K12),H12*INDEX(PRECIOS!$M$6:$M$55,K12))) | BG12: =IF(B12="","",IF(Base_Comision="% DEL INGRESO",O12*INDEX(PRECIOS!$L$6:$L$55,K12),I12*INDEX(PRECIOS!$M$6:$M$55,K12))) | BH12: =IF(B12="","",BE12+BF12+BG12) | BI12: =IF(B12="","",Q12*Pct_Reclamaciones) | BJ12: =IF(B12="","",Q12*Pct_Banco) | BK12: =IF(B12="","",N(ENTRADA!$V12)) | BL12: =IF(B12="","",Y12+AE12+BD12+BH12+BI12+BJ12+BK12) | BM12: =IF(B12="","",Q12-BL12) | BN12: =IF(B12="","",IF(Q12=0,0,BM12/Q12)) | BO12: =IF(B12="","",IF(J12=0,0,BM12/J12)) | BP12: =IF(B12="","",IFERROR(MATCH(D12,COSTOS_FIJOS!$G$5:$AD$5,0),0)) | BQ12: =IF(B12="","",COUNTIFS($D$6:$D$305,D12)) | BR12: =IF(B12="","",SUMIFS($J$6:$J$305,$D$6:$D$305,D12)) | BS12: =IF(B12="","",IF(Metodo_Prorrateo="KG",IF(BR12=0,0,J12/BR12),1/BQ12)) | BT12: =IF(B12="","",IF(BP12=0,0,INDEX(COSTOS_FIJOS!$G$38:$AD$38,BP12))*BS12) | BU12: =IF(B12="","",IF(Metodo_Prorrateo="KG",IF(SUMIFS($G$6:$G$305,$D$6:$D$305,D12)=0,0,G12/SUMIFS($G$6:$G$305,$D$6:$D$305,D12)),IF(G12>0,1/COUNTIFS($D$6:$D$305,D12,$G$6:$G$305,">0"),0))) | BV12: =IF(B12="","",IF(BP12=0,0,INDEX(COSTOS_FIJOS!$G$39:$AD$39,BP12))*BU12) | BW12: =IF(B12="","",IF(Metodo_Prorrateo="KG",IF(SUMIFS($H$6:$H$305,$D$6:$D$305,D12)=0,0,H12/SUMIFS($H$6:$H$305,$D$6:$D$305,D12)),IF(H12>0,1/COUNTIFS($D$6:$D$305,D12,$H$6:$H$305,">0"),0))) | BX12: =IF(B12="","",IF(BP12=0,0,INDEX(COSTOS_FIJOS!$G$40:$AD$40,BP12))*BW12) | BY12: =IF(B12="","",IF(Metodo_Prorrateo="KG",IF(SUMIFS($I$6:$I$305,$D$6:$D$305,D12)=0,0,I12/SUMIFS($I$6:$I$305,$D$6:$D$305,D12)),IF(I12>0,1/COUNTIFS($D$6:$D$305,D12,$I$6:$I$305,">0"),0))) | BZ12: =IF(B12="","",IF(BP12=0,0,INDEX(COSTOS_FIJOS!$G$41:$AD$41,BP12))*BY12) | CA12: =IF(B12="","",BT12+BV12+BX12+BZ12) | CB12: =IF(B12="","",Q12*Imp_Ventas_Serv) | CC12: =IF(B12="","",Q12*Contrib_Territorial) | CD12: =IF(B12="","",BM12-CA12-CB12-CC12) | CE12: =IF(B12="","",MAX(0,CD12)*Imp_Utilidades) | CF12: =IF(B12="","",CD12-CE12) | CG12: =IF(B12="","",IF(Q12=0,0,CF12/Q12)) | CH12: =IF(B12="","",IF(J12=0,0,(BL12+CA12+CB12+CC12)/J12)) | CI12: =IF(B12="","",IF(J12=0,0,Q12/J12)) | CJ12: =IF(B12="","",IF(J12=0,0,CD12/J12)) | CK12: =IF(B12="","",Y12+AE12+BK12+BT12) | CL12: =IF(B12="","",IF(J12=0,0,(M12+P12*G12/J12)*(1-Pct_Reclamaciones-Pct_Banco-Imp_Ventas_Serv-Contrib_Territorial)-AI12-BE12-BV12-CK12*G12/J12)) | CM12: =IF(B12="","",IF(J12=0,0,(N12+P12*H12/J12)*(1-Pct_Reclamaciones-Pct_Banco-Imp_Ventas_Serv-Contrib_Territorial)-AS12-BF12-BX12-CK12*H12/J12)) | CN12: =IF(B12="","",IF(J12=0,0,(O12+P12*I12/J12)*(1-Pct_Reclamaciones-Pct_Banco-Imp_Ventas_Serv-Contrib_Territorial)-BC12-BG12-BZ12-CK12*I12/J12)) | CO12: =IF(B12="","",IF(J12=0,0,ROUND(CD12-CL12-CM12-CN12,4))) | CP12: =IF(B12="","",T12+AG12+AK12+AM12+AU12+AW12) | CQ12: =IF(B12="","",U12+AH12+AL12+AN12+AV12+AX12) | CR12: =IF(B12="","",IF(CP12=0,0,CQ12/CP12-1)) | CS12: =IF(B12="","",IF(ENTRADA!$Y12="","",ENTRADA!$Y12-C12)) | CT12: =IF(B12="","",IF(ENTRADA!$C12="","Falta fecha. ","")&IF(BP12=0,"Mes fuera del rango de COSTOS_FIJOS. ","")&IF(J12=0,"Sin kg. ","")&IF(E12="","Falta transitaria. ","")&IF(AND(T12>0,U12/T12-1>Tolerancia_Comb),"Combustible al puerto "&TEXT(U12/T12-1,"+0%")&" sobre norma. ","")&IF(AND(AG12>0,AH12/AG12-1>Tolerancia_Comb),"Combustible distribución Occidente "&TEXT(AH12/AG12-1,"+0%")&" sobre norma. ","")&IF(AND(AK12>0,AL12/AK12-1>Tolerancia_Comb),"Combustible traslado Centro "&TEXT(AL12/AK12-1,"+0%")&" sobre norma. ","")&IF(AND(AM12>0,AN12/AM12-1>Tolerancia_Comb),"Combustible distribución Centro "&TEXT(AN12/AM12-1,"+0%")&" sobre norma. ","")&IF(AND(AU12>0,AV12/AU12-1>Tolerancia_Comb),"Combustible traslado Oriente "&TEXT(AV12/AU12-1,"+0%")&" sobre norma. ","")&IF(AND(AW12>0,AX12/AW12-1>Tolerancia_Comb),"Combustible distribución Oriente "&TEXT(AX12/AW12-1,"+0%")&" sobre norma. ","")&IF(AND(ENTRADA!$C12<>"",C12<PRECIOS!$A$6),"Fecha anterior a la 1ª vigencia de precios. ","")&IF(CD12<0,"Contenedor con pérdida. ",""))
A13: =IF(B13="","",ROW()-5) | B13: =IF(ENTRADA!$B13="","",ENTRADA!$B13) | C13: =IF(B13="","",ENTRADA!$C13) | D13: =IF(B13="","",DATE(YEAR(C13),MONTH(C13),1)) | E13: =IF(B13="","",ENTRADA!$D13&"") | F13: =IF(B13="","",ENTRADA!$Z13&"") | G13: =IF(B13="","",N(ENTRADA!$G13)) | H13: =IF(B13="","",N(ENTRADA!$H13)) | I13: =IF(B13="","",N(ENTRADA!$I13)) | J13: =IF(B13="","",G13+H13+I13) | K13: =IF(B13="","",IFERROR(MATCH(SUMPRODUCT(MAX((PRECIOS!$A$6:$A$55<=C13)*PRECIOS!$A$6:$A$55)),PRECIOS!$A$6:$A$55,0),1)) | L13: =IF(B13="","",INDEX(PRECIOS!$A$6:$A$55,K13)) | M13: =IF(B13="","",G13*INDEX(PRECIOS!$B$6:$B$55,K13)) | N13: =IF(B13="","",H13*INDEX(PRECIOS!$C$6:$C$55,K13)) | O13: =IF(B13="","",I13*INDEX(PRECIOS!$D$6:$D$55,K13)) | P13: =IF(B13="","",N(ENTRADA!$X13)) | Q13: =IF(B13="","",M13+N13+O13+P13) | R13: =IF(B13="","",IF(ENTRADA!$J13="",Std_Viajes_Puerto,ENTRADA!$J13)) | S13: =IF(B13="","",R13*INDEX(PRECIOS!$F$6:$F$55,K13)) | T13: =IF(B13="","",R13*Litros_Puerto_Viaje) | U13: =IF(B13="","",IF(ENTRADA!$K13="",T13,ENTRADA!$K13)) | V13: =IF(B13="","",U13*INDEX(PRECIOS!$E$6:$E$55,K13)) | W13: =IF(B13="","",IF(ENTRADA!$L13="",R13*INDEX(PRECIOS!$G$6:$G$55,K13),ENTRADA!$L13)) | X13: =IF(B13="","",R13*Km_Puerto_Viaje*INDEX(PRECIOS!$N$6:$N$55,K13)) | Y13: =IF(B13="","",S13+V13+W13+X13) | Z13: =IF(B13="","",IF(J13=0,0,ROUNDUP(J13/Rend_Desagrupe,0))) | AA13: =IF(B13="","",IF(ENTRADA!$M13="",Z13,ENTRADA!$M13)) | AB13: =IF(B13="","",AA13*INDEX(PRECIOS!$H$6:$H$55,K13)) | AC13: =IF(B13="","",IF(E13="ENCI",INDEX(PRECIOS!$J$6:$J$55,K13),IF(E13="A.V",INDEX(PRECIOS!$K$6:$K$55,K13),0))) | AD13: =IF(B13="","",N(ENTRADA!$N13)) | AE13: =IF(B13="","",AB13+AC13+AD13) | AF13: =IF(B13="","",IF(G13=0,0,ROUNDUP(G13/Cap_Camion_OCC,0))) | AG13: =IF(B13="","",AF13*L_Dist_OCC) | AH13: =IF(B13="","",IF(ENTRADA!$O13="",AG13,ENTRADA!$O13)) | AI13: =IF(B13="","",AH13*INDEX(PRECIOS!$E$6:$E$55,K13)) | AJ13: =IF(B13="","",IF(H13=0,0,ROUNDUP(H13/Cap_Camion_CEN,0))) | AK13: =IF(B13="","",AJ13*L_Tras_CEN) | AL13: =IF(B13="","",IF(ENTRADA!$P13="",AK13,ENTRADA!$P13)) | AM13: =IF(B13="","",AJ13*L_Dist_CEN) | AN13: =IF(B13="","",IF(ENTRADA!$Q13="",AM13,ENTRADA!$Q13)) | AO13: =IF(B13="","",(AL13+AN13)*INDEX(PRECIOS!$E$6:$E$55,K13)) | AP13: =IF(B13="","",IF(H13=0,0,ROUNDUP(H13/Rend_Desagrupe_CT,0))) | AQ13: =IF(B13="","",IF(ENTRADA!$R13="",AP13,ENTRADA!$R13)) | AR13: =IF(B13="","",AQ13*INDEX(PRECIOS!$I$6:$I$55,K13)) | AS13: =IF(B13="","",AO13+AR13) | AT13: =IF(B13="","",IF(I13=0,0,ROUNDUP(I13/Cap_Camion_ORI,0))) | AU13: =IF(B13="","",AT13*L_Tras_ORI) | AV13: =IF(B13="","",IF(ENTRADA!$S13="",AU13,ENTRADA!$S13)) | AW13: =IF(B13="","",AT13*L_Dist_ORI) | AX13: =IF(B13="","",IF(ENTRADA!$T13="",AW13,ENTRADA!$T13)) | AY13: =IF(B13="","",(AV13+AX13)*INDEX(PRECIOS!$E$6:$E$55,K13)) | AZ13: =IF(B13="","",IF(I13=0,0,ROUNDUP(I13/Rend_Desagrupe_CT,0))) | BA13: =IF(B13="","",IF(ENTRADA!$U13="",AZ13,ENTRADA!$U13)) | BB13: =IF(B13="","",BA13*INDEX(PRECIOS!$I$6:$I$55,K13)) | BC13: =IF(B13="","",AY13+BB13) | BD13: =IF(B13="","",AI13+AS13+BC13) | BE13: =IF(B13="","",IF(Base_Comision="% DEL INGRESO",M13*INDEX(PRECIOS!$L$6:$L$55,K13),G13*INDEX(PRECIOS!$M$6:$M$55,K13))) | BF13: =IF(B13="","",IF(Base_Comision="% DEL INGRESO",N13*INDEX(PRECIOS!$L$6:$L$55,K13),H13*INDEX(PRECIOS!$M$6:$M$55,K13))) | BG13: =IF(B13="","",IF(Base_Comision="% DEL INGRESO",O13*INDEX(PRECIOS!$L$6:$L$55,K13),I13*INDEX(PRECIOS!$M$6:$M$55,K13))) | BH13: =IF(B13="","",BE13+BF13+BG13) | BI13: =IF(B13="","",Q13*Pct_Reclamaciones) | BJ13: =IF(B13="","",Q13*Pct_Banco) | BK13: =IF(B13="","",N(ENTRADA!$V13)) | BL13: =IF(B13="","",Y13+AE13+BD13+BH13+BI13+BJ13+BK13) | BM13: =IF(B13="","",Q13-BL13) | BN13: =IF(B13="","",IF(Q13=0,0,BM13/Q13)) | BO13: =IF(B13="","",IF(J13=0,0,BM13/J13)) | BP13: =IF(B13="","",IFERROR(MATCH(D13,COSTOS_FIJOS!$G$5:$AD$5,0),0)) | BQ13: =IF(B13="","",COUNTIFS($D$6:$D$305,D13)) | BR13: =IF(B13="","",SUMIFS($J$6:$J$305,$D$6:$D$305,D13)) | BS13: =IF(B13="","",IF(Metodo_Prorrateo="KG",IF(BR13=0,0,J13/BR13),1/BQ13)) | BT13: =IF(B13="","",IF(BP13=0,0,INDEX(COSTOS_FIJOS!$G$38:$AD$38,BP13))*BS13) | BU13: =IF(B13="","",IF(Metodo_Prorrateo="KG",IF(SUMIFS($G$6:$G$305,$D$6:$D$305,D13)=0,0,G13/SUMIFS($G$6:$G$305,$D$6:$D$305,D13)),IF(G13>0,1/COUNTIFS($D$6:$D$305,D13,$G$6:$G$305,">0"),0))) | BV13: =IF(B13="","",IF(BP13=0,0,INDEX(COSTOS_FIJOS!$G$39:$AD$39,BP13))*BU13) | BW13: =IF(B13="","",IF(Metodo_Prorrateo="KG",IF(SUMIFS($H$6:$H$305,$D$6:$D$305,D13)=0,0,H13/SUMIFS($H$6:$H$305,$D$6:$D$305,D13)),IF(H13>0,1/COUNTIFS($D$6:$D$305,D13,$H$6:$H$305,">0"),0))) | BX13: =IF(B13="","",IF(BP13=0,0,INDEX(COSTOS_FIJOS!$G$40:$AD$40,BP13))*BW13) | BY13: =IF(B13="","",IF(Metodo_Prorrateo="KG",IF(SUMIFS($I$6:$I$305,$D$6:$D$305,D13)=0,0,I13/SUMIFS($I$6:$I$305,$D$6:$D$305,D13)),IF(I13>0,1/COUNTIFS($D$6:$D$305,D13,$I$6:$I$305,">0"),0))) | BZ13: =IF(B13="","",IF(BP13=0,0,INDEX(COSTOS_FIJOS!$G$41:$AD$41,BP13))*BY13) | CA13: =IF(B13="","",BT13+BV13+BX13+BZ13) | CB13: =IF(B13="","",Q13*Imp_Ventas_Serv) | CC13: =IF(B13="","",Q13*Contrib_Territorial) | CD13: =IF(B13="","",BM13-CA13-CB13-CC13) | CE13: =IF(B13="","",MAX(0,CD13)*Imp_Utilidades) | CF13: =IF(B13="","",CD13-CE13) | CG13: =IF(B13="","",IF(Q13=0,0,CF13/Q13)) | CH13: =IF(B13="","",IF(J13=0,0,(BL13+CA13+CB13+CC13)/J13)) | CI13: =IF(B13="","",IF(J13=0,0,Q13/J13)) | CJ13: =IF(B13="","",IF(J13=0,0,CD13/J13)) | CK13: =IF(B13="","",Y13+AE13+BK13+BT13) | CL13: =IF(B13="","",IF(J13=0,0,(M13+P13*G13/J13)*(1-Pct_Reclamaciones-Pct_Banco-Imp_Ventas_Serv-Contrib_Territorial)-AI13-BE13-BV13-CK13*G13/J13)) | CM13: =IF(B13="","",IF(J13=0,0,(N13+P13*H13/J13)*(1-Pct_Reclamaciones-Pct_Banco-Imp_Ventas_Serv-Contrib_Territorial)-AS13-BF13-BX13-CK13*H13/J13)) | CN13: =IF(B13="","",IF(J13=0,0,(O13+P13*I13/J13)*(1-Pct_Reclamaciones-Pct_Banco-Imp_Ventas_Serv-Contrib_Territorial)-BC13-BG13-BZ13-CK13*I13/J13)) | CO13: =IF(B13="","",IF(J13=0,0,ROUND(CD13-CL13-CM13-CN13,4))) | CP13: =IF(B13="","",T13+AG13+AK13+AM13+AU13+AW13) | CQ13: =IF(B13="","",U13+AH13+AL13+AN13+AV13+AX13) | CR13: =IF(B13="","",IF(CP13=0,0,CQ13/CP13-1)) | CS13: =IF(B13="","",IF(ENTRADA!$Y13="","",ENTRADA!$Y13-C13)) | CT13: =IF(B13="","",IF(ENTRADA!$C13="","Falta fecha. ","")&IF(BP13=0,"Mes fuera del rango de COSTOS_FIJOS. ","")&IF(J13=0,"Sin kg. ","")&IF(E13="","Falta transitaria. ","")&IF(AND(T13>0,U13/T13-1>Tolerancia_Comb),"Combustible al puerto "&TEXT(U13/T13-1,"+0%")&" sobre norma. ","")&IF(AND(AG13>0,AH13/AG13-1>Tolerancia_Comb),"Combustible distribución Occidente "&TEXT(AH13/AG13-1,"+0%")&" sobre norma. ","")&IF(AND(AK13>0,AL13/AK13-1>Tolerancia_Comb),"Combustible traslado Centro "&TEXT(AL13/AK13-1,"+0%")&" sobre norma. ","")&IF(AND(AM13>0,AN13/AM13-1>Tolerancia_Comb),"Combustible distribución Centro "&TEXT(AN13/AM13-1,"+0%")&" sobre norma. ","")&IF(AND(AU13>0,AV13/AU13-1>Tolerancia_Comb),"Combustible traslado Oriente "&TEXT(AV13/AU13-1,"+0%")&" sobre norma. ","")&IF(AND(AW13>0,AX13/AW13-1>Tolerancia_Comb),"Combustible distribución Oriente "&TEXT(AX13/AW13-1,"+0%")&" sobre norma. ","")&IF(AND(ENTRADA!$C13<>"",C13<PRECIOS!$A$6),"Fecha anterior a la 1ª vigencia de precios. ","")&IF(CD13<0,"Contenedor con pérdida. ",""))
A14: =IF(B14="","",ROW()-5) | B14: =IF(ENTRADA!$B14="","",ENTRADA!$B14) | C14: =IF(B14="","",ENTRADA!$C14) | D14: =IF(B14="","",DATE(YEAR(C14),MONTH(C14),1)) | E14: =IF(B14="","",ENTRADA!$D14&"") | F14: =IF(B14="","",ENTRADA!$Z14&"") | G14: =IF(B14="","",N(ENTRADA!$G14)) | H14: =IF(B14="","",N(ENTRADA!$H14)) | I14: =IF(B14="","",N(ENTRADA!$I14)) | J14: =IF(B14="","",G14+H14+I14) | K14: =IF(B14="","",IFERROR(MATCH(SUMPRODUCT(MAX((PRECIOS!$A$6:$A$55<=C14)*PRECIOS!$A$6:$A$55)),PRECIOS!$A$6:$A$55,0),1)) | L14: =IF(B14="","",INDEX(PRECIOS!$A$6:$A$55,K14)) | M14: =IF(B14="","",G14*INDEX(PRECIOS!$B$6:$B$55,K14)) | N14: =IF(B14="","",H14*INDEX(PRECIOS!$C$6:$C$55,K14)) | O14: =IF(B14="","",I14*INDEX(PRECIOS!$D$6:$D$55,K14)) | P14: =IF(B14="","",N(ENTRADA!$X14)) | Q14: =IF(B14="","",M14+N14+O14+P14) | R14: =IF(B14="","",IF(ENTRADA!$J14="",Std_Viajes_Puerto,ENTRADA!$J14)) | S14: =IF(B14="","",R14*INDEX(PRECIOS!$F$6:$F$55,K14)) | T14: =IF(B14="","",R14*Litros_Puerto_Viaje) | U14: =IF(B14="","",IF(ENTRADA!$K14="",T14,ENTRADA!$K14)) | V14: =IF(B14="","",U14*INDEX(PRECIOS!$E$6:$E$55,K14)) | W14: =IF(B14="","",IF(ENTRADA!$L14="",R14*INDEX(PRECIOS!$G$6:$G$55,K14),ENTRADA!$L14)) | X14: =IF(B14="","",R14*Km_Puerto_Viaje*INDEX(PRECIOS!$N$6:$N$55,K14)) | Y14: =IF(B14="","",S14+V14+W14+X14) | Z14: =IF(B14="","",IF(J14=0,0,ROUNDUP(J14/Rend_Desagrupe,0))) | AA14: =IF(B14="","",IF(ENTRADA!$M14="",Z14,ENTRADA!$M14)) | AB14: =IF(B14="","",AA14*INDEX(PRECIOS!$H$6:$H$55,K14)) | AC14: =IF(B14="","",IF(E14="ENCI",INDEX(PRECIOS!$J$6:$J$55,K14),IF(E14="A.V",INDEX(PRECIOS!$K$6:$K$55,K14),0))) | AD14: =IF(B14="","",N(ENTRADA!$N14)) | AE14: =IF(B14="","",AB14+AC14+AD14) | AF14: =IF(B14="","",IF(G14=0,0,ROUNDUP(G14/Cap_Camion_OCC,0))) | AG14: =IF(B14="","",AF14*L_Dist_OCC) | AH14: =IF(B14="","",IF(ENTRADA!$O14="",AG14,ENTRADA!$O14)) | AI14: =IF(B14="","",AH14*INDEX(PRECIOS!$E$6:$E$55,K14)) | AJ14: =IF(B14="","",IF(H14=0,0,ROUNDUP(H14/Cap_Camion_CEN,0))) | AK14: =IF(B14="","",AJ14*L_Tras_CEN) | AL14: =IF(B14="","",IF(ENTRADA!$P14="",AK14,ENTRADA!$P14)) | AM14: =IF(B14="","",AJ14*L_Dist_CEN) | AN14: =IF(B14="","",IF(ENTRADA!$Q14="",AM14,ENTRADA!$Q14)) | AO14: =IF(B14="","",(AL14+AN14)*INDEX(PRECIOS!$E$6:$E$55,K14)) | AP14: =IF(B14="","",IF(H14=0,0,ROUNDUP(H14/Rend_Desagrupe_CT,0))) | AQ14: =IF(B14="","",IF(ENTRADA!$R14="",AP14,ENTRADA!$R14)) | AR14: =IF(B14="","",AQ14*INDEX(PRECIOS!$I$6:$I$55,K14)) | AS14: =IF(B14="","",AO14+AR14) | AT14: =IF(B14="","",IF(I14=0,0,ROUNDUP(I14/Cap_Camion_ORI,0))) | AU14: =IF(B14="","",AT14*L_Tras_ORI) | AV14: =IF(B14="","",IF(ENTRADA!$S14="",AU14,ENTRADA!$S14)) | AW14: =IF(B14="","",AT14*L_Dist_ORI) | AX14: =IF(B14="","",IF(ENTRADA!$T14="",AW14,ENTRADA!$T14)) | AY14: =IF(B14="","",(AV14+AX14)*INDEX(PRECIOS!$E$6:$E$55,K14)) | AZ14: =IF(B14="","",IF(I14=0,0,ROUNDUP(I14/Rend_Desagrupe_CT,0))) | BA14: =IF(B14="","",IF(ENTRADA!$U14="",AZ14,ENTRADA!$U14)) | BB14: =IF(B14="","",BA14*INDEX(PRECIOS!$I$6:$I$55,K14)) | BC14: =IF(B14="","",AY14+BB14) | BD14: =IF(B14="","",AI14+AS14+BC14) | BE14: =IF(B14="","",IF(Base_Comision="% DEL INGRESO",M14*INDEX(PRECIOS!$L$6:$L$55,K14),G14*INDEX(PRECIOS!$M$6:$M$55,K14))) | BF14: =IF(B14="","",IF(Base_Comision="% DEL INGRESO",N14*INDEX(PRECIOS!$L$6:$L$55,K14),H14*INDEX(PRECIOS!$M$6:$M$55,K14))) | BG14: =IF(B14="","",IF(Base_Comision="% DEL INGRESO",O14*INDEX(PRECIOS!$L$6:$L$55,K14),I14*INDEX(PRECIOS!$M$6:$M$55,K14))) | BH14: =IF(B14="","",BE14+BF14+BG14) | BI14: =IF(B14="","",Q14*Pct_Reclamaciones) | BJ14: =IF(B14="","",Q14*Pct_Banco) | BK14: =IF(B14="","",N(ENTRADA!$V14)) | BL14: =IF(B14="","",Y14+AE14+BD14+BH14+BI14+BJ14+BK14) | BM14: =IF(B14="","",Q14-BL14) | BN14: =IF(B14="","",IF(Q14=0,0,BM14/Q14)) | BO14: =IF(B14="","",IF(J14=0,0,BM14/J14)) | BP14: =IF(B14="","",IFERROR(MATCH(D14,COSTOS_FIJOS!$G$5:$AD$5,0),0)) | BQ14: =IF(B14="","",COUNTIFS($D$6:$D$305,D14)) | BR14: =IF(B14="","",SUMIFS($J$6:$J$305,$D$6:$D$305,D14)) | BS14: =IF(B14="","",IF(Metodo_Prorrateo="KG",IF(BR14=0,0,J14/BR14),1/BQ14)) | BT14: =IF(B14="","",IF(BP14=0,0,INDEX(COSTOS_FIJOS!$G$38:$AD$38,BP14))*BS14) | BU14: =IF(B14="","",IF(Metodo_Prorrateo="KG",IF(SUMIFS($G$6:$G$305,$D$6:$D$305,D14)=0,0,G14/SUMIFS($G$6:$G$305,$D$6:$D$305,D14)),IF(G14>0,1/COUNTIFS($D$6:$D$305,D14,$G$6:$G$305,">0"),0))) | BV14: =IF(B14="","",IF(BP14=0,0,INDEX(COSTOS_FIJOS!$G$39:$AD$39,BP14))*BU14) | BW14: =IF(B14="","",IF(Metodo_Prorrateo="KG",IF(SUMIFS($H$6:$H$305,$D$6:$D$305,D14)=0,0,H14/SUMIFS($H$6:$H$305,$D$6:$D$305,D14)),IF(H14>0,1/COUNTIFS($D$6:$D$305,D14,$H$6:$H$305,">0"),0))) | BX14: =IF(B14="","",IF(BP14=0,0,INDEX(COSTOS_FIJOS!$G$40:$AD$40,BP14))*BW14) | BY14: =IF(B14="","",IF(Metodo_Prorrateo="KG",IF(SUMIFS($I$6:$I$305,$D$6:$D$305,D14)=0,0,I14/SUMIFS($I$6:$I$305,$D$6:$D$305,D14)),IF(I14>0,1/COUNTIFS($D$6:$D$305,D14,$I$6:$I$305,">0"),0))) | BZ14: =IF(B14="","",IF(BP14=0,0,INDEX(COSTOS_FIJOS!$G$41:$AD$41,BP14))*BY14) | CA14: =IF(B14="","",BT14+BV14+BX14+BZ14) | CB14: =IF(B14="","",Q14*Imp_Ventas_Serv) | CC14: =IF(B14="","",Q14*Contrib_Territorial) | CD14: =IF(B14="","",BM14-CA14-CB14-CC14) | CE14: =IF(B14="","",MAX(0,CD14)*Imp_Utilidades) | CF14: =IF(B14="","",CD14-CE14) | CG14: =IF(B14="","",IF(Q14=0,0,CF14/Q14)) | CH14: =IF(B14="","",IF(J14=0,0,(BL14+CA14+CB14+CC14)/J14)) | CI14: =IF(B14="","",IF(J14=0,0,Q14/J14)) | CJ14: =IF(B14="","",IF(J14=0,0,CD14/J14)) | CK14: =IF(B14="","",Y14+AE14+BK14+BT14) | CL14: =IF(B14="","",IF(J14=0,0,(M14+P14*G14/J14)*(1-Pct_Reclamaciones-Pct_Banco-Imp_Ventas_Serv-Contrib_Territorial)-AI14-BE14-BV14-CK14*G14/J14)) | CM14: =IF(B14="","",IF(J14=0,0,(N14+P14*H14/J14)*(1-Pct_Reclamaciones-Pct_Banco-Imp_Ventas_Serv-Contrib_Territorial)-AS14-BF14-BX14-CK14*H14/J14)) | CN14: =IF(B14="","",IF(J14=0,0,(O14+P14*I14/J14)*(1-Pct_Reclamaciones-Pct_Banco-Imp_Ventas_Serv-Contrib_Territorial)-BC14-BG14-BZ14-CK14*I14/J14)) | CO14: =IF(B14="","",IF(J14=0,0,ROUND(CD14-CL14-CM14-CN14,4))) | CP14: =IF(B14="","",T14+AG14+AK14+AM14+AU14+AW14) | CQ14: =IF(B14="","",U14+AH14+AL14+AN14+AV14+AX14) | CR14: =IF(B14="","",IF(CP14=0,0,CQ14/CP14-1)) | CS14: =IF(B14="","",IF(ENTRADA!$Y14="","",ENTRADA!$Y14-C14)) | CT14: =IF(B14="","",IF(ENTRADA!$C14="","Falta fecha. ","")&IF(BP14=0,"Mes fuera del rango de COSTOS_FIJOS. ","")&IF(J14=0,"Sin kg. ","")&IF(E14="","Falta transitaria. ","")&IF(AND(T14>0,U14/T14-1>Tolerancia_Comb),"Combustible al puerto "&TEXT(U14/T14-1,"+0%")&" sobre norma. ","")&IF(AND(AG14>0,AH14/AG14-1>Tolerancia_Comb),"Combustible distribución Occidente "&TEXT(AH14/AG14-1,"+0%")&" sobre norma. ","")&IF(AND(AK14>0,AL14/AK14-1>Tolerancia_Comb),"Combustible traslado Centro "&TEXT(AL14/AK14-1,"+0%")&" sobre norma. ","")&IF(AND(AM14>0,AN14/AM14-1>Tolerancia_Comb),"Combustible distribución Centro "&TEXT(AN14/AM14-1,"+0%")&" sobre norma. ","")&IF(AND(AU14>0,AV14/AU14-1>Tolerancia_Comb),"Combustible traslado Oriente "&TEXT(AV14/AU14-1,"+0%")&" sobre norma. ","")&IF(AND(AW14>0,AX14/AW14-1>Tolerancia_Comb),"Combustible distribución Oriente "&TEXT(AX14/AW14-1,"+0%")&" sobre norma. ","")&IF(AND(ENTRADA!$C14<>"",C14<PRECIOS!$A$6),"Fecha anterior a la 1ª vigencia de precios. ","")&IF(CD14<0,"Contenedor con pérdida. ",""))
A15: =IF(B15="","",ROW()-5) | B15: =IF(ENTRADA!$B15="","",ENTRADA!$B15) | C15: =IF(B15="","",ENTRADA!$C15) | D15: =IF(B15="","",DATE(YEAR(C15),MONTH(C15),1)) | E15: =IF(B15="","",ENTRADA!$D15&"") | F15: =IF(B15="","",ENTRADA!$Z15&"") | G15: =IF(B15="","",N(ENTRADA!$G15)) | H15: =IF(B15="","",N(ENTRADA!$H15)) | I15: =IF(B15="","",N(ENTRADA!$I15)) | J15: =IF(B15="","",G15+H15+I15) | K15: =IF(B15="","",IFERROR(MATCH(SUMPRODUCT(MAX((PRECIOS!$A$6:$A$55<=C15)*PRECIOS!$A$6:$A$55)),PRECIOS!$A$6:$A$55,0),1)) | L15: =IF(B15="","",INDEX(PRECIOS!$A$6:$A$55,K15)) | M15: =IF(B15="","",G15*INDEX(PRECIOS!$B$6:$B$55,K15)) | N15: =IF(B15="","",H15*INDEX(PRECIOS!$C$6:$C$55,K15)) | O15: =IF(B15="","",I15*INDEX(PRECIOS!$D$6:$D$55,K15)) | P15: =IF(B15="","",N(ENTRADA!$X15)) | Q15: =IF(B15="","",M15+N15+O15+P15) | R15: =IF(B15="","",IF(ENTRADA!$J15="",Std_Viajes_Puerto,ENTRADA!$J15)) | S15: =IF(B15="","",R15*INDEX(PRECIOS!$F$6:$F$55,K15)) | T15: =IF(B15="","",R15*Litros_Puerto_Viaje) | U15: =IF(B15="","",IF(ENTRADA!$K15="",T15,ENTRADA!$K15)) | V15: =IF(B15="","",U15*INDEX(PRECIOS!$E$6:$E$55,K15)) | W15: =IF(B15="","",IF(ENTRADA!$L15="",R15*INDEX(PRECIOS!$G$6:$G$55,K15),ENTRADA!$L15)) | X15: =IF(B15="","",R15*Km_Puerto_Viaje*INDEX(PRECIOS!$N$6:$N$55,K15)) | Y15: =IF(B15="","",S15+V15+W15+X15) | Z15: =IF(B15="","",IF(J15=0,0,ROUNDUP(J15/Rend_Desagrupe,0))) | AA15: =IF(B15="","",IF(ENTRADA!$M15="",Z15,ENTRADA!$M15)) | AB15: =IF(B15="","",AA15*INDEX(PRECIOS!$H$6:$H$55,K15)) | AC15: =IF(B15="","",IF(E15="ENCI",INDEX(PRECIOS!$J$6:$J$55,K15),IF(E15="A.V",INDEX(PRECIOS!$K$6:$K$55,K15),0))) | AD15: =IF(B15="","",N(ENTRADA!$N15)) | AE15: =IF(B15="","",AB15+AC15+AD15) | AF15: =IF(B15="","",IF(G15=0,0,ROUNDUP(G15/Cap_Camion_OCC,0))) | AG15: =IF(B15="","",AF15*L_Dist_OCC) | AH15: =IF(B15="","",IF(ENTRADA!$O15="",AG15,ENTRADA!$O15)) | AI15: =IF(B15="","",AH15*INDEX(PRECIOS!$E$6:$E$55,K15)) | AJ15: =IF(B15="","",IF(H15=0,0,ROUNDUP(H15/Cap_Camion_CEN,0))) | AK15: =IF(B15="","",AJ15*L_Tras_CEN) | AL15: =IF(B15="","",IF(ENTRADA!$P15="",AK15,ENTRADA!$P15)) | AM15: =IF(B15="","",AJ15*L_Dist_CEN) | AN15: =IF(B15="","",IF(ENTRADA!$Q15="",AM15,ENTRADA!$Q15)) | AO15: =IF(B15="","",(AL15+AN15)*INDEX(PRECIOS!$E$6:$E$55,K15)) | AP15: =IF(B15="","",IF(H15=0,0,ROUNDUP(H15/Rend_Desagrupe_CT,0))) | AQ15: =IF(B15="","",IF(ENTRADA!$R15="",AP15,ENTRADA!$R15)) | AR15: =IF(B15="","",AQ15*INDEX(PRECIOS!$I$6:$I$55,K15)) | AS15: =IF(B15="","",AO15+AR15) | AT15: =IF(B15="","",IF(I15=0,0,ROUNDUP(I15/Cap_Camion_ORI,0))) | AU15: =IF(B15="","",AT15*L_Tras_ORI) | AV15: =IF(B15="","",IF(ENTRADA!$S15="",AU15,ENTRADA!$S15)) | AW15: =IF(B15="","",AT15*L_Dist_ORI) | AX15: =IF(B15="","",IF(ENTRADA!$T15="",AW15,ENTRADA!$T15)) | AY15: =IF(B15="","",(AV15+AX15)*INDEX(PRECIOS!$E$6:$E$55,K15)) | AZ15: =IF(B15="","",IF(I15=0,0,ROUNDUP(I15/Rend_Desagrupe_CT,0))) | BA15: =IF(B15="","",IF(ENTRADA!$U15="",AZ15,ENTRADA!$U15)) | BB15: =IF(B15="","",BA15*INDEX(PRECIOS!$I$6:$I$55,K15)) | BC15: =IF(B15="","",AY15+BB15) | BD15: =IF(B15="","",AI15+AS15+BC15) | BE15: =IF(B15="","",IF(Base_Comision="% DEL INGRESO",M15*INDEX(PRECIOS!$L$6:$L$55,K15),G15*INDEX(PRECIOS!$M$6:$M$55,K15))) | BF15: =IF(B15="","",IF(Base_Comision="% DEL INGRESO",N15*INDEX(PRECIOS!$L$6:$L$55,K15),H15*INDEX(PRECIOS!$M$6:$M$55,K15))) | BG15: =IF(B15="","",IF(Base_Comision="% DEL INGRESO",O15*INDEX(PRECIOS!$L$6:$L$55,K15),I15*INDEX(PRECIOS!$M$6:$M$55,K15))) | BH15: =IF(B15="","",BE15+BF15+BG15) | BI15: =IF(B15="","",Q15*Pct_Reclamaciones) | BJ15: =IF(B15="","",Q15*Pct_Banco) | BK15: =IF(B15="","",N(ENTRADA!$V15)) | BL15: =IF(B15="","",Y15+AE15+BD15+BH15+BI15+BJ15+BK15) | BM15: =IF(B15="","",Q15-BL15) | BN15: =IF(B15="","",IF(Q15=0,0,BM15/Q15)) | BO15: =IF(B15="","",IF(J15=0,0,BM15/J15)) | BP15: =IF(B15="","",IFERROR(MATCH(D15,COSTOS_FIJOS!$G$5:$AD$5,0),0)) | BQ15: =IF(B15="","",COUNTIFS($D$6:$D$305,D15)) | BR15: =IF(B15="","",SUMIFS($J$6:$J$305,$D$6:$D$305,D15)) | BS15: =IF(B15="","",IF(Metodo_Prorrateo="KG",IF(BR15=0,0,J15/BR15),1/BQ15)) | BT15: =IF(B15="","",IF(BP15=0,0,INDEX(COSTOS_FIJOS!$G$38:$AD$38,BP15))*BS15) | BU15: =IF(B15="","",IF(Metodo_Prorrateo="KG",IF(SUMIFS($G$6:$G$305,$D$6:$D$305,D15)=0,0,G15/SUMIFS($G$6:$G$305,$D$6:$D$305,D15)),IF(G15>0,1/COUNTIFS($D$6:$D$305,D15,$G$6:$G$305,">0"),0))) | BV15: =IF(B15="","",IF(BP15=0,0,INDEX(COSTOS_FIJOS!$G$39:$AD$39,BP15))*BU15) | BW15: =IF(B15="","",IF(Metodo_Prorrateo="KG",IF(SUMIFS($H$6:$H$305,$D$6:$D$305,D15)=0,0,H15/SUMIFS($H$6:$H$305,$D$6:$D$305,D15)),IF(H15>0,1/COUNTIFS($D$6:$D$305,D15,$H$6:$H$305,">0"),0))) | BX15: =IF(B15="","",IF(BP15=0,0,INDEX(COSTOS_FIJOS!$G$40:$AD$40,BP15))*BW15) | BY15: =IF(B15="","",IF(Metodo_Prorrateo="KG",IF(SUMIFS($I$6:$I$305,$D$6:$D$305,D15)=0,0,I15/SUMIFS($I$6:$I$305,$D$6:$D$305,D15)),IF(I15>0,1/COUNTIFS($D$6:$D$305,D15,$I$6:$I$305,">0"),0))) | BZ15: =IF(B15="","",IF(BP15=0,0,INDEX(COSTOS_FIJOS!$G$41:$AD$41,BP15))*BY15) | CA15: =IF(B15="","",BT15+BV15+BX15+BZ15) | CB15: =IF(B15="","",Q15*Imp_Ventas_Serv) | CC15: =IF(B15="","",Q15*Contrib_Territorial) | CD15: =IF(B15="","",BM15-CA15-CB15-CC15) | CE15: =IF(B15="","",MAX(0,CD15)*Imp_Utilidades) | CF15: =IF(B15="","",CD15-CE15) | CG15: =IF(B15="","",IF(Q15=0,0,CF15/Q15)) | CH15: =IF(B15="","",IF(J15=0,0,(BL15+CA15+CB15+CC15)/J15)) | CI15: =IF(B15="","",IF(J15=0,0,Q15/J15)) | CJ15: =IF(B15="","",IF(J15=0,0,CD15/J15)) | CK15: =IF(B15="","",Y15+AE15+BK15+BT15) | CL15: =IF(B15="","",IF(J15=0,0,(M15+P15*G15/J15)*(1-Pct_Reclamaciones-Pct_Banco-Imp_Ventas_Serv-Contrib_Territorial)-AI15-BE15-BV15-CK15*G15/J15)) | CM15: =IF(B15="","",IF(J15=0,0,(N15+P15*H15/J15)*(1-Pct_Reclamaciones-Pct_Banco-Imp_Ventas_Serv-Contrib_Territorial)-AS15-BF15-BX15-CK15*H15/J15)) | CN15: =IF(B15="","",IF(J15=0,0,(O15+P15*I15/J15)*(1-Pct_Reclamaciones-Pct_Banco-Imp_Ventas_Serv-Contrib_Territorial)-BC15-BG15-BZ15-CK15*I15/J15)) | CO15: =IF(B15="","",IF(J15=0,0,ROUND(CD15-CL15-CM15-CN15,4))) | CP15: =IF(B15="","",T15+AG15+AK15+AM15+AU15+AW15) | CQ15: =IF(B15="","",U15+AH15+AL15+AN15+AV15+AX15) | CR15: =IF(B15="","",IF(CP15=0,0,CQ15/CP15-1)) | CS15: =IF(B15="","",IF(ENTRADA!$Y15="","",ENTRADA!$Y15-C15)) | CT15: =IF(B15="","",IF(ENTRADA!$C15="","Falta fecha. ","")&IF(BP15=0,"Mes fuera del rango de COSTOS_FIJOS. ","")&IF(J15=0,"Sin kg. ","")&IF(E15="","Falta transitaria. ","")&IF(AND(T15>0,U15/T15-1>Tolerancia_Comb),"Combustible al puerto "&TEXT(U15/T15-1,"+0%")&" sobre norma. ","")&IF(AND(AG15>0,AH15/AG15-1>Tolerancia_Comb),"Combustible distribución Occidente "&TEXT(AH15/AG15-1,"+0%")&" sobre norma. ","")&IF(AND(AK15>0,AL15/AK15-1>Tolerancia_Comb),"Combustible traslado Centro "&TEXT(AL15/AK15-1,"+0%")&" sobre norma. ","")&IF(AND(AM15>0,AN15/AM15-1>Tolerancia_Comb),"Combustible distribución Centro "&TEXT(AN15/AM15-1,"+0%")&" sobre norma. ","")&IF(AND(AU15>0,AV15/AU15-1>Tolerancia_Comb),"Combustible traslado Oriente "&TEXT(AV15/AU15-1,"+0%")&" sobre norma. ","")&IF(AND(AW15>0,AX15/AW15-1>Tolerancia_Comb),"Combustible distribución Oriente "&TEXT(AX15/AW15-1,"+0%")&" sobre norma. ","")&IF(AND(ENTRADA!$C15<>"",C15<PRECIOS!$A$6),"Fecha anterior a la 1ª vigencia de precios. ","")&IF(CD15<0,"Contenedor con pérdida. ",""))
A16: =IF(B16="","",ROW()-5) | B16: =IF(ENTRADA!$B16="","",ENTRADA!$B16) | C16: =IF(B16="","",ENTRADA!$C16) | D16: =IF(B16="","",DATE(YEAR(C16),MONTH(C16),1)) | E16: =IF(B16="","",ENTRADA!$D16&"") | F16: =IF(B16="","",ENTRADA!$Z16&"") | G16: =IF(B16="","",N(ENTRADA!$G16)) | H16: =IF(B16="","",N(ENTRADA!$H16)) | I16: =IF(B16="","",N(ENTRADA!$I16)) | J16: =IF(B16="","",G16+H16+I16) | K16: =IF(B16="","",IFERROR(MATCH(SUMPRODUCT(MAX((PRECIOS!$A$6:$A$55<=C16)*PRECIOS!$A$6:$A$55)),PRECIOS!$A$6:$A$55,0),1)) | L16: =IF(B16="","",INDEX(PRECIOS!$A$6:$A$55,K16)) | M16: =IF(B16="","",G16*INDEX(PRECIOS!$B$6:$B$55,K16)) | N16: =IF(B16="","",H16*INDEX(PRECIOS!$C$6:$C$55,K16)) | O16: =IF(B16="","",I16*INDEX(PRECIOS!$D$6:$D$55,K16)) | P16: =IF(B16="","",N(ENTRADA!$X16)) | Q16: =IF(B16="","",M16+N16+O16+P16) | R16: =IF(B16="","",IF(ENTRADA!$J16="",Std_Viajes_Puerto,ENTRADA!$J16)) | S16: =IF(B16="","",R16*INDEX(PRECIOS!$F$6:$F$55,K16)) | T16: =IF(B16="","",R16*Litros_Puerto_Viaje) | U16: =IF(B16="","",IF(ENTRADA!$K16="",T16,ENTRADA!$K16)) | V16: =IF(B16="","",U16*INDEX(PRECIOS!$E$6:$E$55,K16)) | W16: =IF(B16="","",IF(ENTRADA!$L16="",R16*INDEX(PRECIOS!$G$6:$G$55,K16),ENTRADA!$L16)) | X16: =IF(B16="","",R16*Km_Puerto_Viaje*INDEX(PRECIOS!$N$6:$N$55,K16)) | Y16: =IF(B16="","",S16+V16+W16+X16) | Z16: =IF(B16="","",IF(J16=0,0,ROUNDUP(J16/Rend_Desagrupe,0))) | AA16: =IF(B16="","",IF(ENTRADA!$M16="",Z16,ENTRADA!$M16)) | AB16: =IF(B16="","",AA16*INDEX(PRECIOS!$H$6:$H$55,K16)) | AC16: =IF(B16="","",IF(E16="ENCI",INDEX(PRECIOS!$J$6:$J$55,K16),IF(E16="A.V",INDEX(PRECIOS!$K$6:$K$55,K16),0))) | AD16: =IF(B16="","",N(ENTRADA!$N16)) | AE16: =IF(B16="","",AB16+AC16+AD16) | AF16: =IF(B16="","",IF(G16=0,0,ROUNDUP(G16/Cap_Camion_OCC,0))) | AG16: =IF(B16="","",AF16*L_Dist_OCC) | AH16: =IF(B16="","",IF(ENTRADA!$O16="",AG16,ENTRADA!$O16)) | AI16: =IF(B16="","",AH16*INDEX(PRECIOS!$E$6:$E$55,K16)) | AJ16: =IF(B16="","",IF(H16=0,0,ROUNDUP(H16/Cap_Camion_CEN,0))) | AK16: =IF(B16="","",AJ16*L_Tras_CEN) | AL16: =IF(B16="","",IF(ENTRADA!$P16="",AK16,ENTRADA!$P16)) | AM16: =IF(B16="","",AJ16*L_Dist_CEN) | AN16: =IF(B16="","",IF(ENTRADA!$Q16="",AM16,ENTRADA!$Q16)) | AO16: =IF(B16="","",(AL16+AN16)*INDEX(PRECIOS!$E$6:$E$55,K16)) | AP16: =IF(B16="","",IF(H16=0,0,ROUNDUP(H16/Rend_Desagrupe_CT,0))) | AQ16: =IF(B16="","",IF(ENTRADA!$R16="",AP16,ENTRADA!$R16)) | AR16: =IF(B16="","",AQ16*INDEX(PRECIOS!$I$6:$I$55,K16)) | AS16: =IF(B16="","",AO16+AR16) | AT16: =IF(B16="","",IF(I16=0,0,ROUNDUP(I16/Cap_Camion_ORI,0))) | AU16: =IF(B16="","",AT16*L_Tras_ORI) | AV16: =IF(B16="","",IF(ENTRADA!$S16="",AU16,ENTRADA!$S16)) | AW16: =IF(B16="","",AT16*L_Dist_ORI) | AX16: =IF(B16="","",IF(ENTRADA!$T16="",AW16,ENTRADA!$T16)) | AY16: =IF(B16="","",(AV16+AX16)*INDEX(PRECIOS!$E$6:$E$55,K16)) | AZ16: =IF(B16="","",IF(I16=0,0,ROUNDUP(I16/Rend_Desagrupe_CT,0))) | BA16: =IF(B16="","",IF(ENTRADA!$U16="",AZ16,ENTRADA!$U16)) | BB16: =IF(B16="","",BA16*INDEX(PRECIOS!$I$6:$I$55,K16)) | BC16: =IF(B16="","",AY16+BB16) | BD16: =IF(B16="","",AI16+AS16+BC16) | BE16: =IF(B16="","",IF(Base_Comision="% DEL INGRESO",M16*INDEX(PRECIOS!$L$6:$L$55,K16),G16*INDEX(PRECIOS!$M$6:$M$55,K16))) | BF16: =IF(B16="","",IF(Base_Comision="% DEL INGRESO",N16*INDEX(PRECIOS!$L$6:$L$55,K16),H16*INDEX(PRECIOS!$M$6:$M$55,K16))) | BG16: =IF(B16="","",IF(Base_Comision="% DEL INGRESO",O16*INDEX(PRECIOS!$L$6:$L$55,K16),I16*INDEX(PRECIOS!$M$6:$M$55,K16))) | BH16: =IF(B16="","",BE16+BF16+BG16) | BI16: =IF(B16="","",Q16*Pct_Reclamaciones) | BJ16: =IF(B16="","",Q16*Pct_Banco) | BK16: =IF(B16="","",N(ENTRADA!$V16)) | BL16: =IF(B16="","",Y16+AE16+BD16+BH16+BI16+BJ16+BK16) | BM16: =IF(B16="","",Q16-BL16) | BN16: =IF(B16="","",IF(Q16=0,0,BM16/Q16)) | BO16: =IF(B16="","",IF(J16=0,0,BM16/J16)) | BP16: =IF(B16="","",IFERROR(MATCH(D16,COSTOS_FIJOS!$G$5:$AD$5,0),0)) | BQ16: =IF(B16="","",COUNTIFS($D$6:$D$305,D16)) | BR16: =IF(B16="","",SUMIFS($J$6:$J$305,$D$6:$D$305,D16)) | BS16: =IF(B16="","",IF(Metodo_Prorrateo="KG",IF(BR16=0,0,J16/BR16),1/BQ16)) | BT16: =IF(B16="","",IF(BP16=0,0,INDEX(COSTOS_FIJOS!$G$38:$AD$38,BP16))*BS16) | BU16: =IF(B16="","",IF(Metodo_Prorrateo="KG",IF(SUMIFS($G$6:$G$305,$D$6:$D$305,D16)=0,0,G16/SUMIFS($G$6:$G$305,$D$6:$D$305,D16)),IF(G16>0,1/COUNTIFS($D$6:$D$305,D16,$G$6:$G$305,">0"),0))) | BV16: =IF(B16="","",IF(BP16=0,0,INDEX(COSTOS_FIJOS!$G$39:$AD$39,BP16))*BU16) | BW16: =IF(B16="","",IF(Metodo_Prorrateo="KG",IF(SUMIFS($H$6:$H$305,$D$6:$D$305,D16)=0,0,H16/SUMIFS($H$6:$H$305,$D$6:$D$305,D16)),IF(H16>0,1/COUNTIFS($D$6:$D$305,D16,$H$6:$H$305,">0"),0))) | BX16: =IF(B16="","",IF(BP16=0,0,INDEX(COSTOS_FIJOS!$G$40:$AD$40,BP16))*BW16) | BY16: =IF(B16="","",IF(Metodo_Prorrateo="KG",IF(SUMIFS($I$6:$I$305,$D$6:$D$305,D16)=0,0,I16/SUMIFS($I$6:$I$305,$D$6:$D$305,D16)),IF(I16>0,1/COUNTIFS($D$6:$D$305,D16,$I$6:$I$305,">0"),0))) | BZ16: =IF(B16="","",IF(BP16=0,0,INDEX(COSTOS_FIJOS!$G$41:$AD$41,BP16))*BY16) | CA16: =IF(B16="","",BT16+BV16+BX16+BZ16) | CB16: =IF(B16="","",Q16*Imp_Ventas_Serv) | CC16: =IF(B16="","",Q16*Contrib_Territorial) | CD16: =IF(B16="","",BM16-CA16-CB16-CC16) | CE16: =IF(B16="","",MAX(0,CD16)*Imp_Utilidades) | CF16: =IF(B16="","",CD16-CE16) | CG16: =IF(B16="","",IF(Q16=0,0,CF16/Q16)) | CH16: =IF(B16="","",IF(J16=0,0,(BL16+CA16+CB16+CC16)/J16)) | CI16: =IF(B16="","",IF(J16=0,0,Q16/J16)) | CJ16: =IF(B16="","",IF(J16=0,0,CD16/J16)) | CK16: =IF(B16="","",Y16+AE16+BK16+BT16) | CL16: =IF(B16="","",IF(J16=0,0,(M16+P16*G16/J16)*(1-Pct_Reclamaciones-Pct_Banco-Imp_Ventas_Serv-Contrib_Territorial)-AI16-BE16-BV16-CK16*G16/J16)) | CM16: =IF(B16="","",IF(J16=0,0,(N16+P16*H16/J16)*(1-Pct_Reclamaciones-Pct_Banco-Imp_Ventas_Serv-Contrib_Territorial)-AS16-BF16-BX16-CK16*H16/J16)) | CN16: =IF(B16="","",IF(J16=0,0,(O16+P16*I16/J16)*(1-Pct_Reclamaciones-Pct_Banco-Imp_Ventas_Serv-Contrib_Territorial)-BC16-BG16-BZ16-CK16*I16/J16)) | CO16: =IF(B16="","",IF(J16=0,0,ROUND(CD16-CL16-CM16-CN16,4))) | CP16: =IF(B16="","",T16+AG16+AK16+AM16+AU16+AW16) | CQ16: =IF(B16="","",U16+AH16+AL16+AN16+AV16+AX16) | CR16: =IF(B16="","",IF(CP16=0,0,CQ16/CP16-1)) | CS16: =IF(B16="","",IF(ENTRADA!$Y16="","",ENTRADA!$Y16-C16)) | CT16: =IF(B16="","",IF(ENTRADA!$C16="","Falta fecha. ","")&IF(BP16=0,"Mes fuera del rango de COSTOS_FIJOS. ","")&IF(J16=0,"Sin kg. ","")&IF(E16="","Falta transitaria. ","")&IF(AND(T16>0,U16/T16-1>Tolerancia_Comb),"Combustible al puerto "&TEXT(U16/T16-1,"+0%")&" sobre norma. ","")&IF(AND(AG16>0,AH16/AG16-1>Tolerancia_Comb),"Combustible distribución Occidente "&TEXT(AH16/AG16-1,"+0%")&" sobre norma. ","")&IF(AND(AK16>0,AL16/AK16-1>Tolerancia_Comb),"Combustible traslado Centro "&TEXT(AL16/AK16-1,"+0%")&" sobre norma. ","")&IF(AND(AM16>0,AN16/AM16-1>Tolerancia_Comb),"Combustible distribución Centro "&TEXT(AN16/AM16-1,"+0%")&" sobre norma. ","")&IF(AND(AU16>0,AV16/AU16-1>Tolerancia_Comb),"Combustible traslado Oriente "&TEXT(AV16/AU16-1,"+0%")&" sobre norma. ","")&IF(AND(AW16>0,AX16/AW16-1>Tolerancia_Comb),"Combustible distribución Oriente "&TEXT(AX16/AW16-1,"+0%")&" sobre norma. ","")&IF(AND(ENTRADA!$C16<>"",C16<PRECIOS!$A$6),"Fecha anterior a la 1ª vigencia de precios. ","")&IF(CD16<0,"Contenedor con pérdida. ",""))
A17: =IF(B17="","",ROW()-5) | B17: =IF(ENTRADA!$B17="","",ENTRADA!$B17) | C17: =IF(B17="","",ENTRADA!$C17) | D17: =IF(B17="","",DATE(YEAR(C17),MONTH(C17),1)) | E17: =IF(B17="","",ENTRADA!$D17&"") | F17: =IF(B17="","",ENTRADA!$Z17&"") | G17: =IF(B17="","",N(ENTRADA!$G17)) | H17: =IF(B17="","",N(ENTRADA!$H17)) | I17: =IF(B17="","",N(ENTRADA!$I17)) | J17: =IF(B17="","",G17+H17+I17) | K17: =IF(B17="","",IFERROR(MATCH(SUMPRODUCT(MAX((PRECIOS!$A$6:$A$55<=C17)*PRECIOS!$A$6:$A$55)),PRECIOS!$A$6:$A$55,0),1)) | L17: =IF(B17="","",INDEX(PRECIOS!$A$6:$A$55,K17)) | M17: =IF(B17="","",G17*INDEX(PRECIOS!$B$6:$B$55,K17)) | N17: =IF(B17="","",H17*INDEX(PRECIOS!$C$6:$C$55,K17)) | O17: =IF(B17="","",I17*INDEX(PRECIOS!$D$6:$D$55,K17)) | P17: =IF(B17="","",N(ENTRADA!$X17)) | Q17: =IF(B17="","",M17+N17+O17+P17) | R17: =IF(B17="","",IF(ENTRADA!$J17="",Std_Viajes_Puerto,ENTRADA!$J17)) | S17: =IF(B17="","",R17*INDEX(PRECIOS!$F$6:$F$55,K17)) | T17: =IF(B17="","",R17*Litros_Puerto_Viaje) | U17: =IF(B17="","",IF(ENTRADA!$K17="",T17,ENTRADA!$K17)) | V17: =IF(B17="","",U17*INDEX(PRECIOS!$E$6:$E$55,K17)) | W17: =IF(B17="","",IF(ENTRADA!$L17="",R17*INDEX(PRECIOS!$G$6:$G$55,K17),ENTRADA!$L17)) | X17: =IF(B17="","",R17*Km_Puerto_Viaje*INDEX(PRECIOS!$N$6:$N$55,K17)) | Y17: =IF(B17="","",S17+V17+W17+X17) | Z17: =IF(B17="","",IF(J17=0,0,ROUNDUP(J17/Rend_Desagrupe,0))) | AA17: =IF(B17="","",IF(ENTRADA!$M17="",Z17,ENTRADA!$M17)) | AB17: =IF(B17="","",AA17*INDEX(PRECIOS!$H$6:$H$55,K17)) | AC17: =IF(B17="","",IF(E17="ENCI",INDEX(PRECIOS!$J$6:$J$55,K17),IF(E17="A.V",INDEX(PRECIOS!$K$6:$K$55,K17),0))) | AD17: =IF(B17="","",N(ENTRADA!$N17)) | AE17: =IF(B17="","",AB17+AC17+AD17) | AF17: =IF(B17="","",IF(G17=0,0,ROUNDUP(G17/Cap_Camion_OCC,0))) | AG17: =IF(B17="","",AF17*L_Dist_OCC) | AH17: =IF(B17="","",IF(ENTRADA!$O17="",AG17,ENTRADA!$O17)) | AI17: =IF(B17="","",AH17*INDEX(PRECIOS!$E$6:$E$55,K17)) | AJ17: =IF(B17="","",IF(H17=0,0,ROUNDUP(H17/Cap_Camion_CEN,0))) | AK17: =IF(B17="","",AJ17*L_Tras_CEN) | AL17: =IF(B17="","",IF(ENTRADA!$P17="",AK17,ENTRADA!$P17)) | AM17: =IF(B17="","",AJ17*L_Dist_CEN) | AN17: =IF(B17="","",IF(ENTRADA!$Q17="",AM17,ENTRADA!$Q17)) | AO17: =IF(B17="","",(AL17+AN17)*INDEX(PRECIOS!$E$6:$E$55,K17)) | AP17: =IF(B17="","",IF(H17=0,0,ROUNDUP(H17/Rend_Desagrupe_CT,0))) | AQ17: =IF(B17="","",IF(ENTRADA!$R17="",AP17,ENTRADA!$R17)) | AR17: =IF(B17="","",AQ17*INDEX(PRECIOS!$I$6:$I$55,K17)) | AS17: =IF(B17="","",AO17+AR17) | AT17: =IF(B17="","",IF(I17=0,0,ROUNDUP(I17/Cap_Camion_ORI,0))) | AU17: =IF(B17="","",AT17*L_Tras_ORI) | AV17: =IF(B17="","",IF(ENTRADA!$S17="",AU17,ENTRADA!$S17)) | AW17: =IF(B17="","",AT17*L_Dist_ORI) | AX17: =IF(B17="","",IF(ENTRADA!$T17="",AW17,ENTRADA!$T17)) | AY17: =IF(B17="","",(AV17+AX17)*INDEX(PRECIOS!$E$6:$E$55,K17)) | AZ17: =IF(B17="","",IF(I17=0,0,ROUNDUP(I17/Rend_Desagrupe_CT,0))) | BA17: =IF(B17="","",IF(ENTRADA!$U17="",AZ17,ENTRADA!$U17)) | BB17: =IF(B17="","",BA17*INDEX(PRECIOS!$I$6:$I$55,K17)) | BC17: =IF(B17="","",AY17+BB17) | BD17: =IF(B17="","",AI17+AS17+BC17) | BE17: =IF(B17="","",IF(Base_Comision="% DEL INGRESO",M17*INDEX(PRECIOS!$L$6:$L$55,K17),G17*INDEX(PRECIOS!$M$6:$M$55,K17))) | BF17: =IF(B17="","",IF(Base_Comision="% DEL INGRESO",N17*INDEX(PRECIOS!$L$6:$L$55,K17),H17*INDEX(PRECIOS!$M$6:$M$55,K17))) | BG17: =IF(B17="","",IF(Base_Comision="% DEL INGRESO",O17*INDEX(PRECIOS!$L$6:$L$55,K17),I17*INDEX(PRECIOS!$M$6:$M$55,K17))) | BH17: =IF(B17="","",BE17+BF17+BG17) | BI17: =IF(B17="","",Q17*Pct_Reclamaciones) | BJ17: =IF(B17="","",Q17*Pct_Banco) | BK17: =IF(B17="","",N(ENTRADA!$V17)) | BL17: =IF(B17="","",Y17+AE17+BD17+BH17+BI17+BJ17+BK17) | BM17: =IF(B17="","",Q17-BL17) | BN17: =IF(B17="","",IF(Q17=0,0,BM17/Q17)) | BO17: =IF(B17="","",IF(J17=0,0,BM17/J17)) | BP17: =IF(B17="","",IFERROR(MATCH(D17,COSTOS_FIJOS!$G$5:$AD$5,0),0)) | BQ17: =IF(B17="","",COUNTIFS($D$6:$D$305,D17)) | BR17: =IF(B17="","",SUMIFS($J$6:$J$305,$D$6:$D$305,D17)) | BS17: =IF(B17="","",IF(Metodo_Prorrateo="KG",IF(BR17=0,0,J17/BR17),1/BQ17)) | BT17: =IF(B17="","",IF(BP17=0,0,INDEX(COSTOS_FIJOS!$G$38:$AD$38,BP17))*BS17) | BU17: =IF(B17="","",IF(Metodo_Prorrateo="KG",IF(SUMIFS($G$6:$G$305,$D$6:$D$305,D17)=0,0,G17/SUMIFS($G$6:$G$305,$D$6:$D$305,D17)),IF(G17>0,1/COUNTIFS($D$6:$D$305,D17,$G$6:$G$305,">0"),0))) | BV17: =IF(B17="","",IF(BP17=0,0,INDEX(COSTOS_FIJOS!$G$39:$AD$39,BP17))*BU17) | BW17: =IF(B17="","",IF(Metodo_Prorrateo="KG",IF(SUMIFS($H$6:$H$305,$D$6:$D$305,D17)=0,0,H17/SUMIFS($H$6:$H$305,$D$6:$D$305,D17)),IF(H17>0,1/COUNTIFS($D$6:$D$305,D17,$H$6:$H$305,">0"),0))) | BX17: =IF(B17="","",IF(BP17=0,0,INDEX(COSTOS_FIJOS!$G$40:$AD$40,BP17))*BW17) | BY17: =IF(B17="","",IF(Metodo_Prorrateo="KG",IF(SUMIFS($I$6:$I$305,$D$6:$D$305,D17)=0,0,I17/SUMIFS($I$6:$I$305,$D$6:$D$305,D17)),IF(I17>0,1/COUNTIFS($D$6:$D$305,D17,$I$6:$I$305,">0"),0))) | BZ17: =IF(B17="","",IF(BP17=0,0,INDEX(COSTOS_FIJOS!$G$41:$AD$41,BP17))*BY17) | CA17: =IF(B17="","",BT17+BV17+BX17+BZ17) | CB17: =IF(B17="","",Q17*Imp_Ventas_Serv) | CC17: =IF(B17="","",Q17*Contrib_Territorial) | CD17: =IF(B17="","",BM17-CA17-CB17-CC17) | CE17: =IF(B17="","",MAX(0,CD17)*Imp_Utilidades) | CF17: =IF(B17="","",CD17-CE17) | CG17: =IF(B17="","",IF(Q17=0,0,CF17/Q17)) | CH17: =IF(B17="","",IF(J17=0,0,(BL17+CA17+CB17+CC17)/J17)) | CI17: =IF(B17="","",IF(J17=0,0,Q17/J17)) | CJ17: =IF(B17="","",IF(J17=0,0,CD17/J17)) | CK17: =IF(B17="","",Y17+AE17+BK17+BT17) | CL17: =IF(B17="","",IF(J17=0,0,(M17+P17*G17/J17)*(1-Pct_Reclamaciones-Pct_Banco-Imp_Ventas_Serv-Contrib_Territorial)-AI17-BE17-BV17-CK17*G17/J17)) | CM17: =IF(B17="","",IF(J17=0,0,(N17+P17*H17/J17)*(1-Pct_Reclamaciones-Pct_Banco-Imp_Ventas_Serv-Contrib_Territorial)-AS17-BF17-BX17-CK17*H17/J17)) | CN17: =IF(B17="","",IF(J17=0,0,(O17+P17*I17/J17)*(1-Pct_Reclamaciones-Pct_Banco-Imp_Ventas_Serv-Contrib_Territorial)-BC17-BG17-BZ17-CK17*I17/J17)) | CO17: =IF(B17="","",IF(J17=0,0,ROUND(CD17-CL17-CM17-CN17,4))) | CP17: =IF(B17="","",T17+AG17+AK17+AM17+AU17+AW17) | CQ17: =IF(B17="","",U17+AH17+AL17+AN17+AV17+AX17) | CR17: =IF(B17="","",IF(CP17=0,0,CQ17/CP17-1)) | CS17: =IF(B17="","",IF(ENTRADA!$Y17="","",ENTRADA!$Y17-C17)) | CT17: =IF(B17="","",IF(ENTRADA!$C17="","Falta fecha. ","")&IF(BP17=0,"Mes fuera del rango de COSTOS_FIJOS. ","")&IF(J17=0,"Sin kg. ","")&IF(E17="","Falta transitaria. ","")&IF(AND(T17>0,U17/T17-1>Tolerancia_Comb),"Combustible al puerto "&TEXT(U17/T17-1,"+0%")&" sobre norma. ","")&IF(AND(AG17>0,AH17/AG17-1>Tolerancia_Comb),"Combustible distribución Occidente "&TEXT(AH17/AG17-1,"+0%")&" sobre norma. ","")&IF(AND(AK17>0,AL17/AK17-1>Tolerancia_Comb),"Combustible traslado Centro "&TEXT(AL17/AK17-1,"+0%")&" sobre norma. ","")&IF(AND(AM17>0,AN17/AM17-1>Tolerancia_Comb),"Combustible distribución Centro "&TEXT(AN17/AM17-1,"+0%")&" sobre norma. ","")&IF(AND(AU17>0,AV17/AU17-1>Tolerancia_Comb),"Combustible traslado Oriente "&TEXT(AV17/AU17-1,"+0%")&" sobre norma. ","")&IF(AND(AW17>0,AX17/AW17-1>Tolerancia_Comb),"Combustible distribución Oriente "&TEXT(AX17/AW17-1,"+0%")&" sobre norma. ","")&IF(AND(ENTRADA!$C17<>"",C17<PRECIOS!$A$6),"Fecha anterior a la 1ª vigencia de precios. ","")&IF(CD17<0,"Contenedor con pérdida. ",""))
... A305: =IF(B305="","",ROW()-5) | B305: =IF(ENTRADA!$B305="","",ENTRADA!$B305) | C305: =IF(B305="","",ENTRADA!$C305) | D305: =IF(B305="","",DATE(YEAR(C305),MONTH(C305),1)) | E305: =IF(B305="","",ENTRADA!$D305&"") | F305: =IF(B305="","",ENTRADA!$Z305&"") | G305: =IF(B305="","",N(ENTRADA!$G305)) | H305: =IF(B305="","",N(ENTRADA!$H305)) | I305: =IF(B305="","",N(ENTRADA!$I305)) | J305: =IF(B305="","",G305+H305+I305) | K305: =IF(B305="","",IFERROR(MATCH(SUMPRODUCT(MAX((PRECIOS!$A$6:$A$55<=C305)*PRECIOS!$A$6:$A$55)),PRECIOS!$A$6:$A$55,0),1)) | L305: =IF(B305="","",INDEX(PRECIOS!$A$6:$A$55,K305)) | M305: =IF(B305="","",G305*INDEX(PRECIOS!$B$6:$B$55,K305)) | N305: =IF(B305="","",H305*INDEX(PRECIOS!$C$6:$C$55,K305)) | O305: =IF(B305="","",I305*INDEX(PRECIOS!$D$6:$D$55,K305)) | P305: =IF(B305="","",N(ENTRADA!$X305)) | Q305: =IF(B305="","",M305+N305+O305+P305) | R305: =IF(B305="","",IF(ENTRADA!$J305="",Std_Viajes_Puerto,ENTRADA!$J305)) | S305: =IF(B305="","",R305*INDEX(PRECIOS!$F$6:$F$55,K305)) | T305: =IF(B305="","",R305*Litros_Puerto_Viaje) | U305: =IF(B305="","",IF(ENTRADA!$K305="",T305,ENTRADA!$K305)) | V305: =IF(B305="","",U305*INDEX(PRECIOS!$E$6:$E$55,K305)) | W305: =IF(B305="","",IF(ENTRADA!$L305="",R305*INDEX(PRECIOS!$G$6:$G$55,K305),ENTRADA!$L305)) | X305: =IF(B305="","",R305*Km_Puerto_Viaje*INDEX(PRECIOS!$N$6:$N$55,K305)) | Y305: =IF(B305="","",S305+V305+W305+X305) | Z305: =IF(B305="","",IF(J305=0,0,ROUNDUP(J305/Rend_Desagrupe,0))) | AA305: =IF(B305="","",IF(ENTRADA!$M305="",Z305,ENTRADA!$M305)) | AB305: =IF(B305="","",AA305*INDEX(PRECIOS!$H$6:$H$55,K305)) | AC305: =IF(B305="","",IF(E305="ENCI",INDEX(PRECIOS!$J$6:$J$55,K305),IF(E305="A.V",INDEX(PRECIOS!$K$6:$K$55,K305),0))) | AD305: =IF(B305="","",N(ENTRADA!$N305)) | AE305: =IF(B305="","",AB305+AC305+AD305) | AF305: =IF(B305="","",IF(G305=0,0,ROUNDUP(G305/Cap_Camion_OCC,0))) | AG305: =IF(B305="","",AF305*L_Dist_OCC) | AH305: =IF(B305="","",IF(ENTRADA!$O305="",AG305,ENTRADA!$O305)) | AI305: =IF(B305="","",AH305*INDEX(PRECIOS!$E$6:$E$55,K305)) | AJ305: =IF(B305="","",IF(H305=0,0,ROUNDUP(H305/Cap_Camion_CEN,0))) | AK305: =IF(B305="","",AJ305*L_Tras_CEN) | AL305: =IF(B305="","",IF(ENTRADA!$P305="",AK305,ENTRADA!$P305)) | AM305: =IF(B305="","",AJ305*L_Dist_CEN) | AN305: =IF(B305="","",IF(ENTRADA!$Q305="",AM305,ENTRADA!$Q305)) | AO305: =IF(B305="","",(AL305+AN305)*INDEX(PRECIOS!$E$6:$E$55,K305)) | AP305: =IF(B305="","",IF(H305=0,0,ROUNDUP(H305/Rend_Desagrupe_CT,0))) | AQ305: =IF(B305="","",IF(ENTRADA!$R305="",AP305,ENTRADA!$R305)) | AR305: =IF(B305="","",AQ305*INDEX(PRECIOS!$I$6:$I$55,K305)) | AS305: =IF(B305="","",AO305+AR305) | AT305: =IF(B305="","",IF(I305=0,0,ROUNDUP(I305/Cap_Camion_ORI,0))) | AU305: =IF(B305="","",AT305*L_Tras_ORI) | AV305: =IF(B305="","",IF(ENTRADA!$S305="",AU305,ENTRADA!$S305)) | AW305: =IF(B305="","",AT305*L_Dist_ORI) | AX305: =IF(B305="","",IF(ENTRADA!$T305="",AW305,ENTRADA!$T305)) | AY305: =IF(B305="","",(AV305+AX305)*INDEX(PRECIOS!$E$6:$E$55,K305)) | AZ305: =IF(B305="","",IF(I305=0,0,ROUNDUP(I305/Rend_Desagrupe_CT,0))) | BA305: =IF(B305="","",IF(ENTRADA!$U305="",AZ305,ENTRADA!$U305)) | BB305: =IF(B305="","",BA305*INDEX(PRECIOS!$I$6:$I$55,K305)) | BC305: =IF(B305="","",AY305+BB305) | BD305: =IF(B305="","",AI305+AS305+BC305) | BE305: =IF(B305="","",IF(Base_Comision="% DEL INGRESO",M305*INDEX(PRECIOS!$L$6:$L$55,K305),G305*INDEX(PRECIOS!$M$6:$M$55,K305))) | BF305: =IF(B305="","",IF(Base_Comision="% DEL INGRESO",N305*INDEX(PRECIOS!$L$6:$L$55,K305),H305*INDEX(PRECIOS!$M$6:$M$55,K305))) | BG305: =IF(B305="","",IF(Base_Comision="% DEL INGRESO",O305*INDEX(PRECIOS!$L$6:$L$55,K305),I305*INDEX(PRECIOS!$M$6:$M$55,K305))) | BH305: =IF(B305="","",BE305+BF305+BG305) | BI305: =IF(B305="","",Q305*Pct_Reclamaciones) | BJ305: =IF(B305="","",Q305*Pct_Banco) | BK305: =IF(B305="","",N(ENTRADA!$V305)) | BL305: =IF(B305="","",Y305+AE305+BD305+BH305+BI305+BJ305+BK305) | BM305: =IF(B305="","",Q305-BL305) | BN305: =IF(B305="","",IF(Q305=0,0,BM305/Q305)) | BO305: =IF(B305="","",IF(J305=0,0,BM305/J305)) | BP305: =IF(B305="","",IFERROR(MATCH(D305,COSTOS_FIJOS!$G$5:$AD$5,0),0)) | BQ305: =IF(B305="","",COUNTIFS($D$6:$D$305,D305)) | BR305: =IF(B305="","",SUMIFS($J$6:$J$305,$D$6:$D$305,D305)) | BS305: =IF(B305="","",IF(Metodo_Prorrateo="KG",IF(BR305=0,0,J305/BR305),1/BQ305)) | BT305: =IF(B305="","",IF(BP305=0,0,INDEX(COSTOS_FIJOS!$G$38:$AD$38,BP305))*BS305) | BU305: =IF(B305="","",IF(Metodo_Prorrateo="KG",IF(SUMIFS($G$6:$G$305,$D$6:$D$305,D305)=0,0,G305/SUMIFS($G$6:$G$305,$D$6:$D$305,D305)),IF(G305>0,1/COUNTIFS($D$6:$D$305,D305,$G$6:$G$305,">0"),0))) | BV305: =IF(B305="","",IF(BP305=0,0,INDEX(COSTOS_FIJOS!$G$39:$AD$39,BP305))*BU305) | BW305: =IF(B305="","",IF(Metodo_Prorrateo="KG",IF(SUMIFS($H$6:$H$305,$D$6:$D$305,D305)=0,0,H305/SUMIFS($H$6:$H$305,$D$6:$D$305,D305)),IF(H305>0,1/COUNTIFS($D$6:$D$305,D305,$H$6:$H$305,">0"),0))) | BX305: =IF(B305="","",IF(BP305=0,0,INDEX(COSTOS_FIJOS!$G$40:$AD$40,BP305))*BW305) | BY305: =IF(B305="","",IF(Metodo_Prorrateo="KG",IF(SUMIFS($I$6:$I$305,$D$6:$D$305,D305)=0,0,I305/SUMIFS($I$6:$I$305,$D$6:$D$305,D305)),IF(I305>0,1/COUNTIFS($D$6:$D$305,D305,$I$6:$I$305,">0"),0))) | BZ305: =IF(B305="","",IF(BP305=0,0,INDEX(COSTOS_FIJOS!$G$41:$AD$41,BP305))*BY305) | CA305: =IF(B305="","",BT305+BV305+BX305+BZ305) | CB305: =IF(B305="","",Q305*Imp_Ventas_Serv) | CC305: =IF(B305="","",Q305*Contrib_Territorial) | CD305: =IF(B305="","",BM305-CA305-CB305-CC305) | CE305: =IF(B305="","",MAX(0,CD305)*Imp_Utilidades) | CF305: =IF(B305="","",CD305-CE305) | CG305: =IF(B305="","",IF(Q305=0,0,CF305/Q305)) | CH305: =IF(B305="","",IF(J305=0,0,(BL305+CA305+CB305+CC305)/J305)) | CI305: =IF(B305="","",IF(J305=0,0,Q305/J305)) | CJ305: =IF(B305="","",IF(J305=0,0,CD305/J305)) | CK305: =IF(B305="","",Y305+AE305+BK305+BT305) | CL305: =IF(B305="","",IF(J305=0,0,(M305+P305*G305/J305)*(1-Pct_Reclamaciones-Pct_Banco-Imp_Ventas_Serv-Contrib_Territorial)-AI305-BE305-BV305-CK305*G305/J305)) | CM305: =IF(B305="","",IF(J305=0,0,(N305+P305*H305/J305)*(1-Pct_Reclamaciones-Pct_Banco-Imp_Ventas_Serv-Contrib_Territorial)-AS305-BF305-BX305-CK305*H305/J305)) | CN305: =IF(B305="","",IF(J305=0,0,(O305+P305*I305/J305)*(1-Pct_Reclamaciones-Pct_Banco-Imp_Ventas_Serv-Contrib_Territorial)-BC305-BG305-BZ305-CK305*I305/J305)) | CO305: =IF(B305="","",IF(J305=0,0,ROUND(CD305-CL305-CM305-CN305,4))) | CP305: =IF(B305="","",T305+AG305+AK305+AM305+AU305+AW305) | CQ305: =IF(B305="","",U305+AH305+AL305+AN305+AV305+AX305) | CR305: =IF(B305="","",IF(CP305=0,0,CQ305/CP305-1)) | CS305: =IF(B305="","",IF(ENTRADA!$Y305="","",ENTRADA!$Y305-C305)) | CT305: =IF(B305="","",IF(ENTRADA!$C305="","Falta fecha. ","")&IF(BP305=0,"Mes fuera del rango de COSTOS_FIJOS. ","")&IF(J305=0,"Sin kg. ","")&IF(E305="","Falta transitaria. ","")&IF(AND(T305>0,U305/T305-1>Tolerancia_Comb),"Combustible al puerto "&TEXT(U305/T305-1,"+0%")&" sobre norma. ","")&IF(AND(AG305>0,AH305/AG305-1>Tolerancia_Comb),"Combustible distribución Occidente "&TEXT(AH305/AG305-1,"+0%")&" sobre norma. ","")&IF(AND(AK305>0,AL305/AK305-1>Tolerancia_Comb),"Combustible traslado Centro "&TEXT(AL305/AK305-1,"+0%")&" sobre norma. ","")&IF(AND(AM305>0,AN305/AM305-1>Tolerancia_Comb),"Combustible distribución Centro "&TEXT(AN305/AM305-1,"+0%")&" sobre norma. ","")&IF(AND(AU305>0,AV305/AU305-1>Tolerancia_Comb),"Combustible traslado Oriente "&TEXT(AV305/AU305-1,"+0%")&" sobre norma. ","")&IF(AND(AW305>0,AX305/AW305-1>Tolerancia_Comb),"Combustible distribución Oriente "&TEXT(AX305/AW305-1,"+0%")&" sobre norma. ","")&IF(AND(ENTRADA!$C305<>"",C305<PRECIOS!$A$6),"Fecha anterior a la 1ª vigencia de precios. ","")&IF(CD305<0,"Contenedor con pérdida. ",""))

Sheet RESUMEN_MES
A1: Resumen mensual de rentabilidad (automático)
A2: Utilidad del mes = margen de contribución − TODOS los costos fijos del mes − tributos sobre ingresos.
A3: Mes de corte aplicado: | C3: =IF(Mes_Corte="",IF(COUNT(CALCULO!$D$6:$D$305)=0,Fecha_Inicio,MAX(CALCULO!$D$6:$D$305)),DATE(YEAR(Mes_Corte),MONTH(Mes_Corte),1)) -> 46296 | D3: Los meses posteriores al corte no cargan costos fijos (aún no han ocurrido). Ajustable en PARAMETROS > Mes_Corte.
A5: Mes | B5: Contenedores | C5: kg Occidente | D5: kg Centro | E5: kg Oriente | F5: kg total | G5: Ingresos | H5: Costos variables | I5: Margen de contribución | J5: MC % | K5: Costos fijos del mes (hasta el corte) | L5: Fijos absorbidos por los contenedores | M5: Fijos no absorbidos | N5: Tributos sobre ingresos | O5: UTILIDAD ANTES DE IMPUESTO | P5: Margen % | Q5: Costo total por kg | R5: Ingreso por kg | S5: Utilidad por kg | T5: Punto de equilibrio (kg) | U5: Punto de equilibrio (contenedores) | V5: Margen de seguridad | W5: Utilidad Occidente | X5: Utilidad Centro | Y5: Utilidad Oriente | Z5: Ajuste por fijos no absorbidos | AA5: Control (debe ser 0) | AB5: Costos totales | AC5: Desvío medio del combustible
A6: =EDATE(Fecha_Inicio,0) -> 46266 | B6: =COUNTIFS(CALCULO!$D$6:$D$305,$A6) -> 2 | C6: =SUMIFS(CALCULO!$G$6:$G$305,CALCULO!$D$6:$D$305,$A6) -> 9800 | D6: =SUMIFS(CALCULO!$H$6:$H$305,CALCULO!$D$6:$D$305,$A6) -> 4700 | E6: =SUMIFS(CALCULO!$I$6:$I$305,CALCULO!$D$6:$D$305,$A6) -> 5000 | F6: =C6+D6+E6 -> 19500 | G6: =SUMIFS(CALCULO!$Q$6:$Q$305,CALCULO!$D$6:$D$305,$A6) -> 15600 | H6: =SUMIFS(CALCULO!$BL$6:$BL$305,CALCULO!$D$6:$D$305,$A6) -> 6574.2 | I6: =G6-H6 -> 9025.8 | J6: =IF(G6=0,0,I6/G6) -> 0.57857692 | K6: =IF($A6>$C$3,0,INDEX(COSTOS_FIJOS!$G$42:$AD$42,1)) -> 3240.0667 | L6: =SUMIFS(CALCULO!$CA$6:$CA$305,CALCULO!$D$6:$D$305,$A6) -> 3240.0667 | M6: =K6-L6 -> 0 | N6: =SUMIFS(CALCULO!$CB$6:$CB$305,CALCULO!$D$6:$D$305,$A6)+SUMIFS(CALCULO!$CC$6:$CC$305,CALCULO!$D$6:$D$305,$A6) -> 1716 | O6: =I6-K6-N6 -> 4069.7333 | P6: =IF(G6=0,0,O6/G6) -> 0.26088034 | Q6: =IF(F6=0,0,(H6+K6+N6)/F6) -> 0.59129573 | R6: =IF(F6=0,0,G6/F6) -> 0.8 | S6: =IF(F6=0,0,O6/F6) -> 0.20870427 | T6: =IF(F6=0,"s/d",IF(I6-N6<=0,"No cubre",K6/((I6-N6)/F6))) -> 8643.3692 | U6: =IF(ISNUMBER(T6),T6/(F6/B6),"s/d") -> 0.8864994 | V6: =IF(ISNUMBER(T6),(F6-T6)/F6,"s/d") -> 0.5567503 | W6: =SUMIFS(CALCULO!$CL$6:$CL$305,CALCULO!$D$6:$D$305,$A6) -> 3996.5789 | X6: =SUMIFS(CALCULO!$CM$6:$CM$305,CALCULO!$D$6:$D$305,$A6) -> 454.35001 | Y6: =SUMIFS(CALCULO!$CN$6:$CN$305,CALCULO!$D$6:$D$305,$A6) -> -381.19553 | Z6: =-M6 -> 0 | AA6: =ROUND(O6-(W6+X6+Y6+Z6),4) -> 0 | AB6: =H6+K6+N6 -> 11530.267 | AC6: =IFERROR(SUMIFS(CALCULO!$CQ$6:$CQ$305,CALCULO!$D$6:$D$305,$A6)/SUMIFS(CALCULO!$CP$6:$CP$305,CALCULO!$D$6:$D$305,$A6)-1,0) -> 0.012598425
A7: =EDATE(Fecha_Inicio,1) -> 46296 | B7: =COUNTIFS(CALCULO!$D$6:$D$305,$A7) -> 2 | C7: =SUMIFS(CALCULO!$G$6:$G$305,CALCULO!$D$6:$D$305,$A7) -> 9900 | D7: =SUMIFS(CALCULO!$H$6:$H$305,CALCULO!$D$6:$D$305,$A7) -> 4400 | E7: =SUMIFS(CALCULO!$I$6:$I$305,CALCULO!$D$6:$D$305,$A7) -> 6300 | F7: =C7+D7+E7 -> 20600 | G7: =SUMIFS(CALCULO!$Q$6:$Q$305,CALCULO!$D$6:$D$305,$A7) -> 16630 | H7: =SUMIFS(CALCULO!$BL$6:$BL$305,CALCULO!$D$6:$D$305,$A7) -> 6462.05 | I7: =G7-H7 -> 10167.95 | J7: =IF(G7=0,0,I7/G7) -> 0.61142213 | K7: =IF($A7>$C$3,0,INDEX(COSTOS_FIJOS!$G$42:$AD$42,2)) -> 3240.0667 | L7: =SUMIFS(CALCULO!$CA$6:$CA$305,CALCULO!$D$6:$D$305,$A7) -> 3240.0667 | M7: =K7-L7 -> 0 | N7: =SUMIFS(CALCULO!$CB$6:$CB$305,CALCULO!$D$6:$D$305,$A7)+SUMIFS(CALCULO!$CC$6:$CC$305,CALCULO!$D$6:$D$305,$A7) -> 1829.3 | O7: =I7-K7-N7 -> 5098.5833 | P7: =IF(G7=0,0,O7/G7) -> 0.3065895 | Q7: =IF(F7=0,0,(H7+K7+N7)/F7) -> 0.55977751 | R7: =IF(F7=0,0,G7/F7) -> 0.80728155 | S7: =IF(F7=0,0,O7/F7) -> 0.24750405 | T7: =IF(F7=0,"s/d",IF(I7-N7<=0,"No cubre",K7/((I7-N7)/F7))) -> 8004.338 | U7: =IF(ISNUMBER(T7),T7/(F7/B7),"s/d") -> 0.7771202 | V7: =IF(ISNUMBER(T7),(F7-T7)/F7,"s/d") -> 0.6114399 | W7: =SUMIFS(CALCULO!$CL$6:$CL$305,CALCULO!$D$6:$D$305,$A7) -> 4423.642 | X7: =SUMIFS(CALCULO!$CM$6:$CM$305,CALCULO!$D$6:$D$305,$A7) -> 407.28432 | Y7: =SUMIFS(CALCULO!$CN$6:$CN$305,CALCULO!$D$6:$D$305,$A7) -> 267.65703 | Z7: =-M7 -> 0 | AA7: =ROUND(O7-(W7+X7+Y7+Z7),4) -> 0 | AB7: =H7+K7+N7 -> 11531.417 | AC7: =IFERROR(SUMIFS(CALCULO!$CQ$6:$CQ$305,CALCULO!$D$6:$D$305,$A7)/SUMIFS(CALCULO!$CP$6:$CP$305,CALCULO!$D$6:$D$305,$A7)-1,0) -> -0.0039370079
A8: =EDATE(Fecha_Inicio,2) -> 46327 | B8: =COUNTIFS(CALCULO!$D$6:$D$305,$A8) -> 0 | C8: =SUMIFS(CALCULO!$G$6:$G$305,CALCULO!$D$6:$D$305,$A8) -> 0 | D8: =SUMIFS(CALCULO!$H$6:$H$305,CALCULO!$D$6:$D$305,$A8) -> 0 | E8: =SUMIFS(CALCULO!$I$6:$I$305,CALCULO!$D$6:$D$305,$A8) -> 0 | F8: =C8+D8+E8 -> 0 | G8: =SUMIFS(CALCULO!$Q$6:$Q$305,CALCULO!$D$6:$D$305,$A8) -> 0 | H8: =SUMIFS(CALCULO!$BL$6:$BL$305,CALCULO!$D$6:$D$305,$A8) -> 0 | I8: =G8-H8 -> 0 | J8: =IF(G8=0,0,I8/G8) -> 0 | K8: =IF($A8>$C$3,0,INDEX(COSTOS_FIJOS!$G$42:$AD$42,3)) -> 0 | L8: =SUMIFS(CALCULO!$CA$6:$CA$305,CALCULO!$D$6:$D$305,$A8) -> 0 | M8: =K8-L8 -> 0 | N8: =SUMIFS(CALCULO!$CB$6:$CB$305,CALCULO!$D$6:$D$305,$A8)+SUMIFS(CALCULO!$CC$6:$CC$305,CALCULO!$D$6:$D$305,$A8) -> 0 | O8: =I8-K8-N8 -> 0 | P8: =IF(G8=0,0,O8/G8) -> 0 | Q8: =IF(F8=0,0,(H8+K8+N8)/F8) -> 0 | R8: =IF(F8=0,0,G8/F8) -> 0 | S8: =IF(F8=0,0,O8/F8) -> 0 | T8: =IF(F8=0,"s/d",IF(I8-N8<=0,"No cubre",K8/((I8-N8)/F8))) -> s/d | U8: =IF(ISNUMBER(T8),T8/(F8/B8),"s/d") -> s/d | V8: =IF(ISNUMBER(T8),(F8-T8)/F8,"s/d") -> s/d | W8: =SUMIFS(CALCULO!$CL$6:$CL$305,CALCULO!$D$6:$D$305,$A8) -> 0 | X8: =SUMIFS(CALCULO!$CM$6:$CM$305,CALCULO!$D$6:$D$305,$A8) -> 0 | Y8: =SUMIFS(CALCULO!$CN$6:$CN$305,CALCULO!$D$6:$D$305,$A8) -> 0 | Z8: =-M8 -> 0 | AA8: =ROUND(O8-(W8+X8+Y8+Z8),4) -> 0 | AB8: =H8+K8+N8 -> 0 | AC8: =IFERROR(SUMIFS(CALCULO!$CQ$6:$CQ$305,CALCULO!$D$6:$D$305,$A8)/SUMIFS(CALCULO!$CP$6:$CP$305,CALCULO!$D$6:$D$305,$A8)-1,0) -> 0
A9: =EDATE(Fecha_Inicio,3) -> 46357 | B9: =COUNTIFS(CALCULO!$D$6:$D$305,$A9) -> 0 | C9: =SUMIFS(CALCULO!$G$6:$G$305,CALCULO!$D$6:$D$305,$A9) -> 0 | D9: =SUMIFS(CALCULO!$H$6:$H$305,CALCULO!$D$6:$D$305,$A9) -> 0 | E9: =SUMIFS(CALCULO!$I$6:$I$305,CALCULO!$D$6:$D$305,$A9) -> 0 | F9: =C9+D9+E9 -> 0 | G9: =SUMIFS(CALCULO!$Q$6:$Q$305,CALCULO!$D$6:$D$305,$A9) -> 0 | H9: =SUMIFS(CALCULO!$BL$6:$BL$305,CALCULO!$D$6:$D$305,$A9) -> 0 | I9: =G9-H9 -> 0 | J9: =IF(G9=0,0,I9/G9) -> 0 | K9: =IF($A9>$C$3,0,INDEX(COSTOS_FIJOS!$G$42:$AD$42,4)) -> 0 | L9: =SUMIFS(CALCULO!$CA$6:$CA$305,CALCULO!$D$6:$D$305,$A9) -> 0 | M9: =K9-L9 -> 0 | N9: =SUMIFS(CALCULO!$CB$6:$CB$305,CALCULO!$D$6:$D$305,$A9)+SUMIFS(CALCULO!$CC$6:$CC$305,CALCULO!$D$6:$D$305,$A9) -> 0 | O9: =I9-K9-N9 -> 0 | P9: =IF(G9=0,0,O9/G9) -> 0 | Q9: =IF(F9=0,0,(H9+K9+N9)/F9) -> 0 | R9: =IF(F9=0,0,G9/F9) -> 0 | S9: =IF(F9=0,0,O9/F9) -> 0 | T9: =IF(F9=0,"s/d",IF(I9-N9<=0,"No cubre",K9/((I9-N9)/F9))) -> s/d | U9: =IF(ISNUMBER(T9),T9/(F9/B9),"s/d") -> s/d | V9: =IF(ISNUMBER(T9),(F9-T9)/F9,"s/d") -> s/d | W9: =SUMIFS(CALCULO!$CL$6:$CL$305,CALCULO!$D$6:$D$305,$A9) -> 0 | X9: =SUMIFS(CALCULO!$CM$6:$CM$305,CALCULO!$D$6:$D$305,$A9) -> 0 | Y9: =SUMIFS(CALCULO!$CN$6:$CN$305,CALCULO!$D$6:$D$305,$A9) -> 0 | Z9: =-M9 -> 0 | AA9: =ROUND(O9-(W9+X9+Y9+Z9),4) -> 0 | AB9: =H9+K9+N9 -> 0 | AC9: =IFERROR(SUMIFS(CALCULO!$CQ$6:$CQ$305,CALCULO!$D$6:$D$305,$A9)/SUMIFS(CALCULO!$CP$6:$CP$305,CALCULO!$D$6:$D$305,$A9)-1,0) -> 0
A10: =EDATE(Fecha_Inicio,4) -> 46388 | B10: =COUNTIFS(CALCULO!$D$6:$D$305,$A10) -> 0 | C10: =SUMIFS(CALCULO!$G$6:$G$305,CALCULO!$D$6:$D$305,$A10) -> 0 | D10: =SUMIFS(CALCULO!$H$6:$H$305,CALCULO!$D$6:$D$305,$A10) -> 0 | E10: =SUMIFS(CALCULO!$I$6:$I$305,CALCULO!$D$6:$D$305,$A10) -> 0 | F10: =C10+D10+E10 -> 0 | G10: =SUMIFS(CALCULO!$Q$6:$Q$305,CALCULO!$D$6:$D$305,$A10) -> 0 | H10: =SUMIFS(CALCULO!$BL$6:$BL$305,CALCULO!$D$6:$D$305,$A10) -> 0 | I10: =G10-H10 -> 0 | J10: =IF(G10=0,0,I10/G10) -> 0 | K10: =IF($A10>$C$3,0,INDEX(COSTOS_FIJOS!$G$42:$AD$42,5)) -> 0 | L10: =SUMIFS(CALCULO!$CA$6:$CA$305,CALCULO!$D$6:$D$305,$A10) -> 0 | M10: =K10-L10 -> 0 | N10: =SUMIFS(CALCULO!$CB$6:$CB$305,CALCULO!$D$6:$D$305,$A10)+SUMIFS(CALCULO!$CC$6:$CC$305,CALCULO!$D$6:$D$305,$A10) -> 0 | O10: =I10-K10-N10 -> 0 | P10: =IF(G10=0,0,O10/G10) -> 0 | Q10: =IF(F10=0,0,(H10+K10+N10)/F10) -> 0 | R10: =IF(F10=0,0,G10/F10) -> 0 | S10: =IF(F10=0,0,O10/F10) -> 0 | T10: =IF(F10=0,"s/d",IF(I10-N10<=0,"No cubre",K10/((I10-N10)/F10))) -> s/d | U10: =IF(ISNUMBER(T10),T10/(F10/B10),"s/d") -> s/d | V10: =IF(ISNUMBER(T10),(F10-T10)/F10,"s/d") -> s/d | W10: =SUMIFS(CALCULO!$CL$6:$CL$305,CALCULO!$D$6:$D$305,$A10) -> 0 | X10: =SUMIFS(CALCULO!$CM$6:$CM$305,CALCULO!$D$6:$D$305,$A10) -> 0 | Y10: =SUMIFS(CALCULO!$CN$6:$CN$305,CALCULO!$D$6:$D$305,$A10) -> 0 | Z10: =-M10 -> 0 | AA10: =ROUND(O10-(W10+X10+Y10+Z10),4) -> 0 | AB10: =H10+K10+N10 -> 0 | AC10: =IFERROR(SUMIFS(CALCULO!$CQ$6:$CQ$305,CALCULO!$D$6:$D$305,$A10)/SUMIFS(CALCULO!$CP$6:$CP$305,CALCULO!$D$6:$D$305,$A10)-1,0) -> 0
A11: =EDATE(Fecha_Inicio,5) -> 46419 | B11: =COUNTIFS(CALCULO!$D$6:$D$305,$A11) -> 0 | C11: =SUMIFS(CALCULO!$G$6:$G$305,CALCULO!$D$6:$D$305,$A11) -> 0 | D11: =SUMIFS(CALCULO!$H$6:$H$305,CALCULO!$D$6:$D$305,$A11) -> 0 | E11: =SUMIFS(CALCULO!$I$6:$I$305,CALCULO!$D$6:$D$305,$A11) -> 0 | F11: =C11+D11+E11 -> 0 | G11: =SUMIFS(CALCULO!$Q$6:$Q$305,CALCULO!$D$6:$D$305,$A11) -> 0 | H11: =SUMIFS(CALCULO!$BL$6:$BL$305,CALCULO!$D$6:$D$305,$A11) -> 0 | I11: =G11-H11 -> 0 | J11: =IF(G11=0,0,I11/G11) -> 0 | K11: =IF($A11>$C$3,0,INDEX(COSTOS_FIJOS!$G$42:$AD$42,6)) -> 0 | L11: =SUMIFS(CALCULO!$CA$6:$CA$305,CALCULO!$D$6:$D$305,$A11) -> 0 | M11: =K11-L11 -> 0 | N11: =SUMIFS(CALCULO!$CB$6:$CB$305,CALCULO!$D$6:$D$305,$A11)+SUMIFS(CALCULO!$CC$6:$CC$305,CALCULO!$D$6:$D$305,$A11) -> 0 | O11: =I11-K11-N11 -> 0 | P11: =IF(G11=0,0,O11/G11) -> 0 | Q11: =IF(F11=0,0,(H11+K11+N11)/F11) -> 0 | R11: =IF(F11=0,0,G11/F11) -> 0 | S11: =IF(F11=0,0,O11/F11) -> 0 | T11: =IF(F11=0,"s/d",IF(I11-N11<=0,"No cubre",K11/((I11-N11)/F11))) -> s/d | U11: =IF(ISNUMBER(T11),T11/(F11/B11),"s/d") -> s/d | V11: =IF(ISNUMBER(T11),(F11-T11)/F11,"s/d") -> s/d | W11: =SUMIFS(CALCULO!$CL$6:$CL$305,CALCULO!$D$6:$D$305,$A11) -> 0 | X11: =SUMIFS(CALCULO!$CM$6:$CM$305,CALCULO!$D$6:$D$305,$A11) -> 0 | Y11: =SUMIFS(CALCULO!$CN$6:$CN$305,CALCULO!$D$6:$D$305,$A11) -> 0 | Z11: =-M11 -> 0 | AA11: =ROUND(O11-(W11+X11+Y11+Z11),4) -> 0 | AB11: =H11+K11+N11 -> 0 | AC11: =IFERROR(SUMIFS(CALCULO!$CQ$6:$CQ$305,CALCULO!$D$6:$D$305,$A11)/SUMIFS(CALCULO!$CP$6:$CP$305,CALCULO!$D$6:$D$305,$A11)-1,0) -> 0
A12: =EDATE(Fecha_Inicio,6) -> 46447 | B12: =COUNTIFS(CALCULO!$D$6:$D$305,$A12) -> 0 | C12: =SUMIFS(CALCULO!$G$6:$G$305,CALCULO!$D$6:$D$305,$A12) -> 0 | D12: =SUMIFS(CALCULO!$H$6:$H$305,CALCULO!$D$6:$D$305,$A12) -> 0 | E12: =SUMIFS(CALCULO!$I$6:$I$305,CALCULO!$D$6:$D$305,$A12) -> 0 | F12: =C12+D12+E12 -> 0 | G12: =SUMIFS(CALCULO!$Q$6:$Q$305,CALCULO!$D$6:$D$305,$A12) -> 0 | H12: =SUMIFS(CALCULO!$BL$6:$BL$305,CALCULO!$D$6:$D$305,$A12) -> 0 | I12: =G12-H12 -> 0 | J12: =IF(G12=0,0,I12/G12) -> 0 | K12: =IF($A12>$C$3,0,INDEX(COSTOS_FIJOS!$G$42:$AD$42,7)) -> 0 | L12: =SUMIFS(CALCULO!$CA$6:$CA$305,CALCULO!$D$6:$D$305,$A12) -> 0 | M12: =K12-L12 -> 0 | N12: =SUMIFS(CALCULO!$CB$6:$CB$305,CALCULO!$D$6:$D$305,$A12)+SUMIFS(CALCULO!$CC$6:$CC$305,CALCULO!$D$6:$D$305,$A12) -> 0 | O12: =I12-K12-N12 -> 0 | P12: =IF(G12=0,0,O12/G12) -> 0 | Q12: =IF(F12=0,0,(H12+K12+N12)/F12) -> 0 | R12: =IF(F12=0,0,G12/F12) -> 0 | S12: =IF(F12=0,0,O12/F12) -> 0 | T12: =IF(F12=0,"s/d",IF(I12-N12<=0,"No cubre",K12/((I12-N12)/F12))) -> s/d | U12: =IF(ISNUMBER(T12),T12/(F12/B12),"s/d") -> s/d | V12: =IF(ISNUMBER(T12),(F12-T12)/F12,"s/d") -> s/d | W12: =SUMIFS(CALCULO!$CL$6:$CL$305,CALCULO!$D$6:$D$305,$A12) -> 0 | X12: =SUMIFS(CALCULO!$CM$6:$CM$305,CALCULO!$D$6:$D$305,$A12) -> 0 | Y12: =SUMIFS(CALCULO!$CN$6:$CN$305,CALCULO!$D$6:$D$305,$A12) -> 0 | Z12: =-M12 -> 0 | AA12: =ROUND(O12-(W12+X12+Y12+Z12),4) -> 0 | AB12: =H12+K12+N12 -> 0 | AC12: =IFERROR(SUMIFS(CALCULO!$CQ$6:$CQ$305,CALCULO!$D$6:$D$305,$A12)/SUMIFS(CALCULO!$CP$6:$CP$305,CALCULO!$D$6:$D$305,$A12)-1,0) -> 0
A13: =EDATE(Fecha_Inicio,7) -> 46478 | B13: =COUNTIFS(CALCULO!$D$6:$D$305,$A13) -> 0 | C13: =SUMIFS(CALCULO!$G$6:$G$305,CALCULO!$D$6:$D$305,$A13) -> 0 | D13: =SUMIFS(CALCULO!$H$6:$H$305,CALCULO!$D$6:$D$305,$A13) -> 0 | E13: =SUMIFS(CALCULO!$I$6:$I$305,CALCULO!$D$6:$D$305,$A13) -> 0 | F13: =C13+D13+E13 -> 0 | G13: =SUMIFS(CALCULO!$Q$6:$Q$305,CALCULO!$D$6:$D$305,$A13) -> 0 | H13: =SUMIFS(CALCULO!$BL$6:$BL$305,CALCULO!$D$6:$D$305,$A13) -> 0 | I13: =G13-H13 -> 0 | J13: =IF(G13=0,0,I13/G13) -> 0 | K13: =IF($A13>$C$3,0,INDEX(COSTOS_FIJOS!$G$42:$AD$42,8)) -> 0 | L13: =SUMIFS(CALCULO!$CA$6:$CA$305,CALCULO!$D$6:$D$305,$A13) -> 0 | M13: =K13-L13 -> 0 | N13: =SUMIFS(CALCULO!$CB$6:$CB$305,CALCULO!$D$6:$D$305,$A13)+SUMIFS(CALCULO!$CC$6:$CC$305,CALCULO!$D$6:$D$305,$A13) -> 0 | O13: =I13-K13-N13 -> 0 | P13: =IF(G13=0,0,O13/G13) -> 0 | Q13: =IF(F13=0,0,(H13+K13+N13)/F13) -> 0 | R13: =IF(F13=0,0,G13/F13) -> 0 | S13: =IF(F13=0,0,O13/F13) -> 0 | T13: =IF(F13=0,"s/d",IF(I13-N13<=0,"No cubre",K13/((I13-N13)/F13))) -> s/d | U13: =IF(ISNUMBER(T13),T13/(F13/B13),"s/d") -> s/d | V13: =IF(ISNUMBER(T13),(F13-T13)/F13,"s/d") -> s/d | W13: =SUMIFS(CALCULO!$CL$6:$CL$305,CALCULO!$D$6:$D$305,$A13) -> 0 | X13: =SUMIFS(CALCULO!$CM$6:$CM$305,CALCULO!$D$6:$D$305,$A13) -> 0 | Y13: =SUMIFS(CALCULO!$CN$6:$CN$305,CALCULO!$D$6:$D$305,$A13) -> 0 | Z13: =-M13 -> 0 | AA13: =ROUND(O13-(W13+X13+Y13+Z13),4) -> 0 | AB13: =H13+K13+N13 -> 0 | AC13: =IFERROR(SUMIFS(CALCULO!$CQ$6:$CQ$305,CALCULO!$D$6:$D$305,$A13)/SUMIFS(CALCULO!$CP$6:$CP$305,CALCULO!$D$6:$D$305,$A13)-1,0) -> 0
A14: =EDATE(Fecha_Inicio,8) -> 46508 | B14: =COUNTIFS(CALCULO!$D$6:$D$305,$A14) -> 0 | C14: =SUMIFS(CALCULO!$G$6:$G$305,CALCULO!$D$6:$D$305,$A14) -> 0 | D14: =SUMIFS(CALCULO!$H$6:$H$305,CALCULO!$D$6:$D$305,$A14) -> 0 | E14: =SUMIFS(CALCULO!$I$6:$I$305,CALCULO!$D$6:$D$305,$A14) -> 0 | F14: =C14+D14+E14 -> 0 | G14: =SUMIFS(CALCULO!$Q$6:$Q$305,CALCULO!$D$6:$D$305,$A14) -> 0 | H14: =SUMIFS(CALCULO!$BL$6:$BL$305,CALCULO!$D$6:$D$305,$A14) -> 0 | I14: =G14-H14 -> 0 | J14: =IF(G14=0,0,I14/G14) -> 0 | K14: =IF($A14>$C$3,0,INDEX(COSTOS_FIJOS!$G$42:$AD$42,9)) -> 0 | L14: =SUMIFS(CALCULO!$CA$6:$CA$305,CALCULO!$D$6:$D$305,$A14) -> 0 | M14: =K14-L14 -> 0 | N14: =SUMIFS(CALCULO!$CB$6:$CB$305,CALCULO!$D$6:$D$305,$A14)+SUMIFS(CALCULO!$CC$6:$CC$305,CALCULO!$D$6:$D$305,$A14) -> 0 | O14: =I14-K14-N14 -> 0 | P14: =IF(G14=0,0,O14/G14) -> 0 | Q14: =IF(F14=0,0,(H14+K14+N14)/F14) -> 0 | R14: =IF(F14=0,0,G14/F14) -> 0 | S14: =IF(F14=0,0,O14/F14) -> 0 | T14: =IF(F14=0,"s/d",IF(I14-N14<=0,"No cubre",K14/((I14-N14)/F14))) -> s/d | U14: =IF(ISNUMBER(T14),T14/(F14/B14),"s/d") -> s/d | V14: =IF(ISNUMBER(T14),(F14-T14)/F14,"s/d") -> s/d | W14: =SUMIFS(CALCULO!$CL$6:$CL$305,CALCULO!$D$6:$D$305,$A14) -> 0 | X14: =SUMIFS(CALCULO!$CM$6:$CM$305,CALCULO!$D$6:$D$305,$A14) -> 0 | Y14: =SUMIFS(CALCULO!$CN$6:$CN$305,CALCULO!$D$6:$D$305,$A14) -> 0 | Z14: =-M14 -> 0 | AA14: =ROUND(O14-(W14+X14+Y14+Z14),4) -> 0 | AB14: =H14+K14+N14 -> 0 | AC14: =IFERROR(SUMIFS(CALCULO!$CQ$6:$CQ$305,CALCULO!$D$6:$D$305,$A14)/SUMIFS(CALCULO!$CP$6:$CP$305,CALCULO!$D$6:$D$305,$A14)-1,0) -> 0
A15: =EDATE(Fecha_Inicio,9) -> 46539 | B15: =COUNTIFS(CALCULO!$D$6:$D$305,$A15) -> 0 | C15: =SUMIFS(CALCULO!$G$6:$G$305,CALCULO!$D$6:$D$305,$A15) -> 0 | D15: =SUMIFS(CALCULO!$H$6:$H$305,CALCULO!$D$6:$D$305,$A15) -> 0 | E15: =SUMIFS(CALCULO!$I$6:$I$305,CALCULO!$D$6:$D$305,$A15) -> 0 | F15: =C15+D15+E15 -> 0 | G15: =SUMIFS(CALCULO!$Q$6:$Q$305,CALCULO!$D$6:$D$305,$A15) -> 0 | H15: =SUMIFS(CALCULO!$BL$6:$BL$305,CALCULO!$D$6:$D$305,$A15) -> 0 | I15: =G15-H15 -> 0 | J15: =IF(G15=0,0,I15/G15) -> 0 | K15: =IF($A15>$C$3,0,INDEX(COSTOS_FIJOS!$G$42:$AD$42,10)) -> 0 | L15: =SUMIFS(CALCULO!$CA$6:$CA$305,CALCULO!$D$6:$D$305,$A15) -> 0 | M15: =K15-L15 -> 0 | N15: =SUMIFS(CALCULO!$CB$6:$CB$305,CALCULO!$D$6:$D$305,$A15)+SUMIFS(CALCULO!$CC$6:$CC$305,CALCULO!$D$6:$D$305,$A15) -> 0 | O15: =I15-K15-N15 -> 0 | P15: =IF(G15=0,0,O15/G15) -> 0 | Q15: =IF(F15=0,0,(H15+K15+N15)/F15) -> 0 | R15: =IF(F15=0,0,G15/F15) -> 0 | S15: =IF(F15=0,0,O15/F15) -> 0 | T15: =IF(F15=0,"s/d",IF(I15-N15<=0,"No cubre",K15/((I15-N15)/F15))) -> s/d | U15: =IF(ISNUMBER(T15),T15/(F15/B15),"s/d") -> s/d | V15: =IF(ISNUMBER(T15),(F15-T15)/F15,"s/d") -> s/d | W15: =SUMIFS(CALCULO!$CL$6:$CL$305,CALCULO!$D$6:$D$305,$A15) -> 0 | X15: =SUMIFS(CALCULO!$CM$6:$CM$305,CALCULO!$D$6:$D$305,$A15) -> 0 | Y15: =SUMIFS(CALCULO!$CN$6:$CN$305,CALCULO!$D$6:$D$305,$A15) -> 0 | Z15: =-M15 -> 0 | AA15: =ROUND(O15-(W15+X15+Y15+Z15),4) -> 0 | AB15: =H15+K15+N15 -> 0 | AC15: =IFERROR(SUMIFS(CALCULO!$CQ$6:$CQ$305,CALCULO!$D$6:$D$305,$A15)/SUMIFS(CALCULO!$CP$6:$CP$305,CALCULO!$D$6:$D$305,$A15)-1,0) -> 0
A16: =EDATE(Fecha_Inicio,10) -> 46569 | B16: =COUNTIFS(CALCULO!$D$6:$D$305,$A16) -> 0 | C16: =SUMIFS(CALCULO!$G$6:$G$305,CALCULO!$D$6:$D$305,$A16) -> 0 | D16: =SUMIFS(CALCULO!$H$6:$H$305,CALCULO!$D$6:$D$305,$A16) -> 0 | E16: =SUMIFS(CALCULO!$I$6:$I$305,CALCULO!$D$6:$D$305,$A16) -> 0 | F16: =C16+D16+E16 -> 0 | G16: =SUMIFS(CALCULO!$Q$6:$Q$305,CALCULO!$D$6:$D$305,$A16) -> 0 | H16: =SUMIFS(CALCULO!$BL$6:$BL$305,CALCULO!$D$6:$D$305,$A16) -> 0 | I16: =G16-H16 -> 0 | J16: =IF(G16=0,0,I16/G16) -> 0 | K16: =IF($A16>$C$3,0,INDEX(COSTOS_FIJOS!$G$42:$AD$42,11)) -> 0 | L16: =SUMIFS(CALCULO!$CA$6:$CA$305,CALCULO!$D$6:$D$305,$A16) -> 0 | M16: =K16-L16 -> 0 | N16: =SUMIFS(CALCULO!$CB$6:$CB$305,CALCULO!$D$6:$D$305,$A16)+SUMIFS(CALCULO!$CC$6:$CC$305,CALCULO!$D$6:$D$305,$A16) -> 0 | O16: =I16-K16-N16 -> 0 | P16: =IF(G16=0,0,O16/G16) -> 0 | Q16: =IF(F16=0,0,(H16+K16+N16)/F16) -> 0 | R16: =IF(F16=0,0,G16/F16) -> 0 | S16: =IF(F16=0,0,O16/F16) -> 0 | T16: =IF(F16=0,"s/d",IF(I16-N16<=0,"No cubre",K16/((I16-N16)/F16))) -> s/d | U16: =IF(ISNUMBER(T16),T16/(F16/B16),"s/d") -> s/d | V16: =IF(ISNUMBER(T16),(F16-T16)/F16,"s/d") -> s/d | W16: =SUMIFS(CALCULO!$CL$6:$CL$305,CALCULO!$D$6:$D$305,$A16) -> 0 | X16: =SUMIFS(CALCULO!$CM$6:$CM$305,CALCULO!$D$6:$D$305,$A16) -> 0 | Y16: =SUMIFS(CALCULO!$CN$6:$CN$305,CALCULO!$D$6:$D$305,$A16) -> 0 | Z16: =-M16 -> 0 | AA16: =ROUND(O16-(W16+X16+Y16+Z16),4) -> 0 | AB16: =H16+K16+N16 -> 0 | AC16: =IFERROR(SUMIFS(CALCULO!$CQ$6:$CQ$305,CALCULO!$D$6:$D$305,$A16)/SUMIFS(CALCULO!$CP$6:$CP$305,CALCULO!$D$6:$D$305,$A16)-1,0) -> 0
A17: =EDATE(Fecha_Inicio,11) -> 46600 | B17: =COUNTIFS(CALCULO!$D$6:$D$305,$A17) -> 0 | C17: =SUMIFS(CALCULO!$G$6:$G$305,CALCULO!$D$6:$D$305,$A17) -> 0 | D17: =SUMIFS(CALCULO!$H$6:$H$305,CALCULO!$D$6:$D$305,$A17) -> 0 | E17: =SUMIFS(CALCULO!$I$6:$I$305,CALCULO!$D$6:$D$305,$A17) -> 0 | F17: =C17+D17+E17 -> 0 | G17: =SUMIFS(CALCULO!$Q$6:$Q$305,CALCULO!$D$6:$D$305,$A17) -> 0 | H17: =SUMIFS(CALCULO!$BL$6:$BL$305,CALCULO!$D$6:$D$305,$A17) -> 0 | I17: =G17-H17 -> 0 | J17: =IF(G17=0,0,I17/G17) -> 0 | K17: =IF($A17>$C$3,0,INDEX(COSTOS_FIJOS!$G$42:$AD$42,12)) -> 0 | L17: =SUMIFS(CALCULO!$CA$6:$CA$305,CALCULO!$D$6:$D$305,$A17) -> 0 | M17: =K17-L17 -> 0 | N17: =SUMIFS(CALCULO!$CB$6:$CB$305,CALCULO!$D$6:$D$305,$A17)+SUMIFS(CALCULO!$CC$6:$CC$305,CALCULO!$D$6:$D$305,$A17) -> 0 | O17: =I17-K17-N17 -> 0 | P17: =IF(G17=0,0,O17/G17) -> 0 | Q17: =IF(F17=0,0,(H17+K17+N17)/F17) -> 0 | R17: =IF(F17=0,0,G17/F17) -> 0 | S17: =IF(F17=0,0,O17/F17) -> 0 | T17: =IF(F17=0,"s/d",IF(I17-N17<=0,"No cubre",K17/((I17-N17)/F17))) -> s/d | U17: =IF(ISNUMBER(T17),T17/(F17/B17),"s/d") -> s/d | V17: =IF(ISNUMBER(T17),(F17-T17)/F17,"s/d") -> s/d | W17: =SUMIFS(CALCULO!$CL$6:$CL$305,CALCULO!$D$6:$D$305,$A17) -> 0 | X17: =SUMIFS(CALCULO!$CM$6:$CM$305,CALCULO!$D$6:$D$305,$A17) -> 0 | Y17: =SUMIFS(CALCULO!$CN$6:$CN$305,CALCULO!$D$6:$D$305,$A17) -> 0 | Z17: =-M17 -> 0 | AA17: =ROUND(O17-(W17+X17+Y17+Z17),4) -> 0 | AB17: =H17+K17+N17 -> 0 | AC17: =IFERROR(SUMIFS(CALCULO!$CQ$6:$CQ$305,CALCULO!$D$6:$D$305,$A17)/SUMIFS(CALCULO!$CP$6:$CP$305,CALCULO!$D$6:$D$305,$A17)-1,0) -> 0
A18: =EDATE(Fecha_Inicio,12) -> 46631 | B18: =COUNTIFS(CALCULO!$D$6:$D$305,$A18) -> 0 | C18: =SUMIFS(CALCULO!$G$6:$G$305,CALCULO!$D$6:$D$305,$A18) -> 0 | D18: =SUMIFS(CALCULO!$H$6:$H$305,CALCULO!$D$6:$D$305,$A18) -> 0 | E18: =SUMIFS(CALCULO!$I$6:$I$305,CALCULO!$D$6:$D$305,$A18) -> 0 | F18: =C18+D18+E18 -> 0 | G18: =SUMIFS(CALCULO!$Q$6:$Q$305,CALCULO!$D$6:$D$305,$A18) -> 0 | H18: =SUMIFS(CALCULO!$BL$6:$BL$305,CALCULO!$D$6:$D$305,$A18) -> 0 | I18: =G18-H18 -> 0 | J18: =IF(G18=0,0,I18/G18) -> 0 | K18: =IF($A18>$C$3,0,INDEX(COSTOS_FIJOS!$G$42:$AD$42,13)) -> 0 | L18: =SUMIFS(CALCULO!$CA$6:$CA$305,CALCULO!$D$6:$D$305,$A18) -> 0 | M18: =K18-L18 -> 0 | N18: =SUMIFS(CALCULO!$CB$6:$CB$305,CALCULO!$D$6:$D$305,$A18)+SUMIFS(CALCULO!$CC$6:$CC$305,CALCULO!$D$6:$D$305,$A18) -> 0 | O18: =I18-K18-N18 -> 0 | P18: =IF(G18=0,0,O18/G18) -> 0 | Q18: =IF(F18=0,0,(H18+K18+N18)/F18) -> 0 | R18: =IF(F18=0,0,G18/F18) -> 0 | S18: =IF(F18=0,0,O18/F18) -> 0 | T18: =IF(F18=0,"s/d",IF(I18-N18<=0,"No cubre",K18/((I18-N18)/F18))) -> s/d | U18: =IF(ISNUMBER(T18),T18/(F18/B18),"s/d") -> s/d | V18: =IF(ISNUMBER(T18),(F18-T18)/F18,"s/d") -> s/d | W18: =SUMIFS(CALCULO!$CL$6:$CL$305,CALCULO!$D$6:$D$305,$A18) -> 0 | X18: =SUMIFS(CALCULO!$CM$6:$CM$305,CALCULO!$D$6:$D$305,$A18) -> 0 | Y18: =SUMIFS(CALCULO!$CN$6:$CN$305,CALCULO!$D$6:$D$305,$A18) -> 0 | Z18: =-M18 -> 0 | AA18: =ROUND(O18-(W18+X18+Y18+Z18),4) -> 0 | AB18: =H18+K18+N18 -> 0 | AC18: =IFERROR(SUMIFS(CALCULO!$CQ$6:$CQ$305,CALCULO!$D$6:$D$305,$A18)/SUMIFS(CALCULO!$CP$6:$CP$305,CALCULO!$D$6:$D$305,$A18)-1,0) -> 0
A19: =EDATE(Fecha_Inicio,13) -> 46661 | B19: =COUNTIFS(CALCULO!$D$6:$D$305,$A19) -> 0 | C19: =SUMIFS(CALCULO!$G$6:$G$305,CALCULO!$D$6:$D$305,$A19) -> 0 | D19: =SUMIFS(CALCULO!$H$6:$H$305,CALCULO!$D$6:$D$305,$A19) -> 0 | E19: =SUMIFS(CALCULO!$I$6:$I$305,CALCULO!$D$6:$D$305,$A19) -> 0 | F19: =C19+D19+E19 -> 0 | G19: =SUMIFS(CALCULO!$Q$6:$Q$305,CALCULO!$D$6:$D$305,$A19) -> 0 | H19: =SUMIFS(CALCULO!$BL$6:$BL$305,CALCULO!$D$6:$D$305,$A19) -> 0 | I19: =G19-H19 -> 0 | J19: =IF(G19=0,0,I19/G19) -> 0 | K19: =IF($A19>$C$3,0,INDEX(COSTOS_FIJOS!$G$42:$AD$42,14)) -> 0 | L19: =SUMIFS(CALCULO!$CA$6:$CA$305,CALCULO!$D$6:$D$305,$A19) -> 0 | M19: =K19-L19 -> 0 | N19: =SUMIFS(CALCULO!$CB$6:$CB$305,CALCULO!$D$6:$D$305,$A19)+SUMIFS(CALCULO!$CC$6:$CC$305,CALCULO!$D$6:$D$305,$A19) -> 0 | O19: =I19-K19-N19 -> 0 | P19: =IF(G19=0,0,O19/G19) -> 0 | Q19: =IF(F19=0,0,(H19+K19+N19)/F19) -> 0 | R19: =IF(F19=0,0,G19/F19) -> 0 | S19: =IF(F19=0,0,O19/F19) -> 0 | T19: =IF(F19=0,"s/d",IF(I19-N19<=0,"No cubre",K19/((I19-N19)/F19))) -> s/d | U19: =IF(ISNUMBER(T19),T19/(F19/B19),"s/d") -> s/d | V19: =IF(ISNUMBER(T19),(F19-T19)/F19,"s/d") -> s/d | W19: =SUMIFS(CALCULO!$CL$6:$CL$305,CALCULO!$D$6:$D$305,$A19) -> 0 | X19: =SUMIFS(CALCULO!$CM$6:$CM$305,CALCULO!$D$6:$D$305,$A19) -> 0 | Y19: =SUMIFS(CALCULO!$CN$6:$CN$305,CALCULO!$D$6:$D$305,$A19) -> 0 | Z19: =-M19 -> 0 | AA19: =ROUND(O19-(W19+X19+Y19+Z19),4) -> 0 | AB19: =H19+K19+N19 -> 0 | AC19: =IFERROR(SUMIFS(CALCULO!$CQ$6:$CQ$305,CALCULO!$D$6:$D$305,$A19)/SUMIFS(CALCULO!$CP$6:$CP$305,CALCULO!$D$6:$D$305,$A19)-1,0) -> 0
A20: =EDATE(Fecha_Inicio,14) -> 46692 | B20: =COUNTIFS(CALCULO!$D$6:$D$305,$A20) -> 0 | C20: =SUMIFS(CALCULO!$G$6:$G$305,CALCULO!$D$6:$D$305,$A20) -> 0 | D20: =SUMIFS(CALCULO!$H$6:$H$305,CALCULO!$D$6:$D$305,$A20) -> 0 | E20: =SUMIFS(CALCULO!$I$6:$I$305,CALCULO!$D$6:$D$305,$A20) -> 0 | F20: =C20+D20+E20 -> 0 | G20: =SUMIFS(CALCULO!$Q$6:$Q$305,CALCULO!$D$6:$D$305,$A20) -> 0 | H20: =SUMIFS(CALCULO!$BL$6:$BL$305,CALCULO!$D$6:$D$305,$A20) -> 0 | I20: =G20-H20 -> 0 | J20: =IF(G20=0,0,I20/G20) -> 0 | K20: =IF($A20>$C$3,0,INDEX(COSTOS_FIJOS!$G$42:$AD$42,15)) -> 0 | L20: =SUMIFS(CALCULO!$CA$6:$CA$305,CALCULO!$D$6:$D$305,$A20) -> 0 | M20: =K20-L20 -> 0 | N20: =SUMIFS(CALCULO!$CB$6:$CB$305,CALCULO!$D$6:$D$305,$A20)+SUMIFS(CALCULO!$CC$6:$CC$305,CALCULO!$D$6:$D$305,$A20) -> 0 | O20: =I20-K20-N20 -> 0 | P20: =IF(G20=0,0,O20/G20) -> 0 | Q20: =IF(F20=0,0,(H20+K20+N20)/F20) -> 0 | R20: =IF(F20=0,0,G20/F20) -> 0 | S20: =IF(F20=0,0,O20/F20) -> 0 | T20: =IF(F20=0,"s/d",IF(I20-N20<=0,"No cubre",K20/((I20-N20)/F20))) -> s/d | U20: =IF(ISNUMBER(T20),T20/(F20/B20),"s/d") -> s/d | V20: =IF(ISNUMBER(T20),(F20-T20)/F20,"s/d") -> s/d | W20: =SUMIFS(CALCULO!$CL$6:$CL$305,CALCULO!$D$6:$D$305,$A20) -> 0 | X20: =SUMIFS(CALCULO!$CM$6:$CM$305,CALCULO!$D$6:$D$305,$A20) -> 0 | Y20: =SUMIFS(CALCULO!$CN$6:$CN$305,CALCULO!$D$6:$D$305,$A20) -> 0 | Z20: =-M20 -> 0 | AA20: =ROUND(O20-(W20+X20+Y20+Z20),4) -> 0 | AB20: =H20+K20+N20 -> 0 | AC20: =IFERROR(SUMIFS(CALCULO!$CQ$6:$CQ$305,CALCULO!$D$6:$D$305,$A20)/SUMIFS(CALCULO!$CP$6:$CP$305,CALCULO!$D$6:$D$305,$A20)-1,0) -> 0
A21: =EDATE(Fecha_Inicio,15) -> 46722 | B21: =COUNTIFS(CALCULO!$D$6:$D$305,$A21) -> 0 | C21: =SUMIFS(CALCULO!$G$6:$G$305,CALCULO!$D$6:$D$305,$A21) -> 0 | D21: =SUMIFS(CALCULO!$H$6:$H$305,CALCULO!$D$6:$D$305,$A21) -> 0 | E21: =SUMIFS(CALCULO!$I$6:$I$305,CALCULO!$D$6:$D$305,$A21) -> 0 | F21: =C21+D21+E21 -> 0 | G21: =SUMIFS(CALCULO!$Q$6:$Q$305,CALCULO!$D$6:$D$305,$A21) -> 0 | H21: =SUMIFS(CALCULO!$BL$6:$BL$305,CALCULO!$D$6:$D$305,$A21) -> 0 | I21: =G21-H21 -> 0 | J21: =IF(G21=0,0,I21/G21) -> 0 | K21: =IF($A21>$C$3,0,INDEX(COSTOS_FIJOS!$G$42:$AD$42,16)) -> 0 | L21: =SUMIFS(CALCULO!$CA$6:$CA$305,CALCULO!$D$6:$D$305,$A21) -> 0 | M21: =K21-L21 -> 0 | N21: =SUMIFS(CALCULO!$CB$6:$CB$305,CALCULO!$D$6:$D$305,$A21)+SUMIFS(CALCULO!$CC$6:$CC$305,CALCULO!$D$6:$D$305,$A21) -> 0 | O21: =I21-K21-N21 -> 0 | P21: =IF(G21=0,0,O21/G21) -> 0 | Q21: =IF(F21=0,0,(H21+K21+N21)/F21) -> 0 | R21: =IF(F21=0,0,G21/F21) -> 0 | S21: =IF(F21=0,0,O21/F21) -> 0 | T21: =IF(F21=0,"s/d",IF(I21-N21<=0,"No cubre",K21/((I21-N21)/F21))) -> s/d | U21: =IF(ISNUMBER(T21),T21/(F21/B21),"s/d") -> s/d | V21: =IF(ISNUMBER(T21),(F21-T21)/F21,"s/d") -> s/d | W21: =SUMIFS(CALCULO!$CL$6:$CL$305,CALCULO!$D$6:$D$305,$A21) -> 0 | X21: =SUMIFS(CALCULO!$CM$6:$CM$305,CALCULO!$D$6:$D$305,$A21) -> 0 | Y21: =SUMIFS(CALCULO!$CN$6:$CN$305,CALCULO!$D$6:$D$305,$A21) -> 0 | Z21: =-M21 -> 0 | AA21: =ROUND(O21-(W21+X21+Y21+Z21),4) -> 0 | AB21: =H21+K21+N21 -> 0 | AC21: =IFERROR(SUMIFS(CALCULO!$CQ$6:$CQ$305,CALCULO!$D$6:$D$305,$A21)/SUMIFS(CALCULO!$CP$6:$CP$305,CALCULO!$D$6:$D$305,$A21)-1,0) -> 0
